Workbook

Sheet 懸念
B2: dev-td環境の懸念
B4: ・最近開発した新機能が入ってない | C4: テストスタート前に上げたい | D4: → | E4: dev-tdにテスト前に上げてもらえないか、木岡さんと相談 【中里】 | I4: 問い合わせ中 | J4: →反映済み
B5: ・タイムスタンプ、解像度検証、PLP、SSO設定、カード明細 がない | C5: テスト1周中に上げたい | D5: → | E5: 富田(秀)が問合せ | F5: https://beartail.slack.com/archives/C02QY42J0UE/p1729752363703969?thread_ts=1728545201.995399&cid=C02QY42J0UE
B6: ・Autifyがない | C6: テスト1周後に共通ステージングに上げればOK | D6: →
B7: ・テックタッチがない | C7: おそらく影響なし（木岡さん） | D7: → | E7: 確認済（木岡さんに）
B8: ・BtoB連携やるべきか | C8: 賢吾さんに対応を依頼中 | D8: → | E8: やらなくてよさそうとのこと
B9: ・TCを見れる環境がない | C9: 賢吾さんに対応を依頼中 | D9: → | E9: 設定済み
B10: ・送付元アドレス検索 | C10: 共通ステージングに反映する | D10: → | E10: 反映済み
C16: 対応が必要なのを赤字にしてます
B17: シート | C17: 概要 | D17: 列 1 | E17: 対象項目 | F17: JIRA
B18: 領収書原本/PLPサイト | C18: 11/06 起票 | E18: https://docs.google.com/spreadsheets/d/16H4dpcCe490b0qpEyv4WCs_w6i2ItiKabXM2BmqNTcY/edit?gid=114354577#gid=114354577&range=N38 | F18: FA-108
C19: 本番不具合なので「外」としました | E19: https://docs.google.com/spreadsheets/d/16H4dpcCe490b0qpEyv4WCs_w6i2ItiKabXM2BmqNTcY/edit?gid=114354577#gid=114354577&range=P170:P173 | F19: KH-4267
B20: 稟議 | C20: 再QAしたけど直ってなかったとこで止まってる | E20: https://docs.google.com/spreadsheets/d/16H4dpcCe490b0qpEyv4WCs_w6i2ItiKabXM2BmqNTcY/edit?gid=1834201177#gid=1834201177&range=N44 | F20: FA-99
B21: 個人設定 | C21: 本番不具合なので「外」としました | E21: https://docs.google.com/spreadsheets/d/16H4dpcCe490b0qpEyv4WCs_w6i2ItiKabXM2BmqNTcY/edit?gid=201285008#gid=201285008&range=M130:O130 | F21: SC-184
B22: システム設定 | C22: 本番不具合なので「外」としました | E22: https://docs.google.com/spreadsheets/d/16H4dpcCe490b0qpEyv4WCs_w6i2ItiKabXM2BmqNTcY/edit?gid=387648503#gid=387648503&range=O54 | F22: SC-185
C23: 木岡さんが経費チームに問い合わせ中 | E23: https://docs.google.com/spreadsheets/d/16H4dpcCe490b0qpEyv4WCs_w6i2ItiKabXM2BmqNTcY/edit?gid=387648503#gid=387648503&range=O308 https://docs.google.com/spreadsheets/d/16H4dpcCe490b0qpEyv4WCs_w6i2ItiKabXM2BmqNTcY/edit?gid=387648503#gid=387648503&range=O645:O648 | F23: FA-107 | H23: ←これがブロック多い
C24: 木岡さんからQAに質問来て回答済み | E24: https://docs.google.com/spreadsheets/d/16H4dpcCe490b0qpEyv4WCs_w6i2ItiKabXM2BmqNTcY/edit?gid=387648503#gid=387648503&range=O1142 | F24: FA-104
C25: 本番不具合なので「外」としました | E25: https://docs.google.com/spreadsheets/d/16H4dpcCe490b0qpEyv4WCs_w6i2ItiKabXM2BmqNTcY/edit?gid=387648503#gid=387648503&range=O1355 | F25: KH-4196
C26: 本番不具合なので「外」としました | E26: https://docs.google.com/spreadsheets/d/16H4dpcCe490b0qpEyv4WCs_w6i2ItiKabXM2BmqNTcY/edit?gid=387648503#gid=387648503&range=O1372 | F26: KH-4248
C27: 本番不具合なので「外」としました | E27: https://docs.google.com/spreadsheets/d/16H4dpcCe490b0qpEyv4WCs_w6i2ItiKabXM2BmqNTcY/edit?gid=387648503#gid=387648503&range=O1412 | F27: KH-4255
B28: 通知 | C28: 木岡さんが対象のチームに確認中 | E28: https://docs.google.com/spreadsheets/d/16H4dpcCe490b0qpEyv4WCs_w6i2ItiKabXM2BmqNTcY/edit?gid=71246066#gid=71246066&range=R108 | F28: FA-105
B29: 共通 | C29: 本番不具合なので「外」としました | E29: https://docs.google.com/spreadsheets/d/16H4dpcCe490b0qpEyv4WCs_w6i2ItiKabXM2BmqNTcY/edit?gid=1880495727#gid=1880495727&range=N33 https://docs.google.com/spreadsheets/d/16H4dpcCe490b0qpEyv4WCs_w6i2ItiKabXM2BmqNTcY/edit?gid=1880495727#gid=1880495727&range=N58 | F29: SC-179
C30: dev-tdでのみ発生していたようなのでクローズしてもいいか木岡さんに相談中 | E30: https://docs.google.com/spreadsheets/d/16H4dpcCe490b0qpEyv4WCs_w6i2ItiKabXM2BmqNTcY/edit?gid=1880495727#gid=1880495727&range=N183 | F30: FA-101
C31: 本番不具合なので「外」としました | E31: https://docs.google.com/spreadsheets/d/16H4dpcCe490b0qpEyv4WCs_w6i2ItiKabXM2BmqNTcY/edit?gid=1880495727#gid=1880495727&range=N219 | F31: KH-4246

Sheet 進捗
B2: テスト進捗 | E2: 目安：150 / 人日 | M2: 残項目数 | N2: 総ケース数 | P2: バグ発生数(起票数) | Q2: バグ発生率
M3: =SUM(F25:H25) -> 0 | N3: =SUM(F25:J25) -> 7228 | Q3: =P3/N3 -> 0
C6: ステータス | D6: 設計レビュー | E6: テスト実行者 | F6: 未 | G6: NG | H6: 保 | I6: OK | J6: 外 | K6: - | P6: 設計担当 | Q6: 担当 | R6: 工数_見積もり
B7: 新規ボタン | C7: 完了 | D7: 未 | E7: 中里/北川 | F7: =countif(indirect($B7&"!$M:$T"),F$6) -> 0 | G7: =countif(indirect($B7&"!$M:$T"),G$6) -> 0 | H7: =countif(indirect($B7&"!$M:$T"),H$6) -> 0 | I7: =countif(indirect($B7&"!$M:$T"),I$6) -> 84 | J7: =countif(indirect($B7&"!$M:$T"),J$6) -> 0 | K7: =countif(indirect($B7&"!$M:$T"),K$6) -> 2296 | P7: +新規 | Q7: 富田(秀) | R7: 0.5 | S7: 作りかけだったので、＋新規→手入力まで作りました（本橋）
B8: 経費 | C8: 完了 | D8: 済 | E8: 行田 | F8: =countif(indirect($B8&"!$N:$T"),F$6) -> 0 | G8: =countif(indirect($B8&"!$N:$T"),G$6) -> 0 | H8: =countif(indirect($B8&"!$N:$T"),H$6) -> 0 | I8: =countif(indirect($B8&"!$N:$T"),I$6) -> 363 | J8: =countif(indirect($B8&"!$N:$T"),J$6) -> 213 | K8: =countif(indirect($B8&"!$N:$T"),K$6) -> 2020 | P8: 申請 | Q8: 富田(秀) | R8: 0.8
B9: カード明細 | C9: 完了 | D9: 済 | E9: 北川 | F9: =countif(indirect($B9&"!$N:$T"),F$6) -> 0 | G9: =countif(indirect($B9&"!$N:$T"),G$6) -> 0 | H9: =countif(indirect($B9&"!$N:$T"),H$6) -> 0 | I9: =countif(indirect($B9&"!$N:$T"),I$6) -> 110 | J9: =countif(indirect($B9&"!$N:$T"),J$6) -> 2 | K9: =countif(indirect($B9&"!$N:$T"),K$6) -> 320 | P9: 承認 | Q9: 富田(秀) | R9: 0.8
B10: 仮払 | C10: 完了 | D10: 済 | E10: 行田 | F10: =countif(indirect($B10&"!$N:$T"),F$6) -> 0 | G10: =countif(indirect($B10&"!$N:$T"),G$6) -> 0 | H10: =countif(indirect($B10&"!$N:$T"),H$6) -> 0 | I10: =countif(indirect($B10&"!$N:$T"),I$6) -> 124 | J10: =countif(indirect($B10&"!$N:$T"),J$6) -> 0 | K10: =countif(indirect($B10&"!$N:$T"),K$6) -> 0 | P10: 経費 | Q10: 本橋 | R10: 1.5
B11: 集計(経費) | C11: 完了 | D11: 済 | E11: 北川/本橋 | F11: =countif(indirect($B11&"!$N:$T"),F$6) -> 0 | G11: =countif(indirect($B11&"!$N:$T"),G$6) -> 0 | H11: =countif(indirect($B11&"!$N:$T"),H$6) -> 0 | I11: =countif(indirect($B11&"!$N:$T"),I$6) -> 326 | J11: =countif(indirect($B11&"!$N:$T"),J$6) -> 23 | K11: =countif(indirect($B11&"!$N:$T"),K$6) -> 739 | P11: カード明細 | Q11: 本橋 | R11: 0.5
B12: 領収書原本/PLPサイト | C12: 完了 | D12: 済 | E12: 金田 | F12: =countif(indirect($B12&"!$N:$T"),F$6) -> 0 | G12: =countif(indirect($B12&"!$N:$T"),G$6) -> 0 | H12: =countif(indirect($B12&"!$N:$T"),H$6) -> 0 | I12: =countif(indirect($B12&"!$N:$T"),I$6) -> 286 | J12: =countif(indirect($B12&"!$N:$T"),J$6) -> 109 | K12: =countif(indirect($B12&"!$N:$T"),K$6) -> 681 | P12: 仮払 | Q12: 本橋 | R12: 0.2
B13: 稟議 | C13: 完了 | D13: 済 | F13: =countif(indirect($B13&"!$N:$T"),F$6) -> 0 | G13: =countif(indirect($B13&"!$N:$T"),G$6) -> 0 | H13: =countif(indirect($B13&"!$N:$T"),H$6) -> 0 | I13: =countif(indirect($B13&"!$N:$T"),I$6) -> 232 | J13: =countif(indirect($B13&"!$N:$T"),J$6) -> 1 | K13: =countif(indirect($B13&"!$N:$T"),K$6) -> 27 | P13: 集計 | Q13: 本橋 | R13: 0.5
B14: 請求書 | C14: 完了 | D14: 済 | E14: 北川 | F14: =countif(indirect($B14&"!$K:$N"),F$6) -> 0 | G14: =countif(indirect($B14&"!$K:$N"),G$6) -> 0 | H14: =countif(indirect($B14&"!$K:$N"),H$6) -> 0 | I14: =countif(indirect($B14&"!$K:$N"),I$6) -> 347 | J14: =countif(indirect($B14&"!$K:$N"),J$6) -> 1 | K14: =countif(indirect($B14&"!$K:$N"),K$6) -> 340 | P14: 領収書原本/PLP | Q14: 本橋 | R14: 0.2
B15: 個人設定 | C15: 完了 | D15: 済 | E15: 中里/行田 | F15: =countif(indirect($B15&"!$M:$T"),F$6) -> 0 | G15: =countif(indirect($B15&"!$M:$T"),G$6) -> 0 | H15: =countif(indirect($B15&"!$M:$T"),H$6) -> 0 | I15: =countif(indirect($B15&"!$M:$T"),I$6) -> 327 | J15: =countif(indirect($B15&"!$M:$T"),J$6) -> 25 | K15: =countif(indirect($B15&"!$M:$T"),K$6) -> 336 | P15: 稟議 | Q15: 中里 | R15: 0.5
B16: 国税関係書類 | C16: 完了 | D16: 済 | E16: 北川 | F16: =countif(indirect($B16&"!$L:$T"),F$6) -> 0 | G16: =countif(indirect($B16&"!$L:$T"),G$6) -> 0 | H16: =countif(indirect($B16&"!$L:$T"),H$6) -> 0 | I16: =countif(indirect($B16&"!$L:$T"),I$6) -> 264 | J16: =countif(indirect($B16&"!$L:$T"),J$6) -> 364 | K16: =countif(indirect($B16&"!$L:$T"),K$6) -> 471 | P16: 自動入力中書類 | Q16: 七浦 | R16: 0.2
B17: 自動入力中書類 | C17: 完了 | D17: 済 | F17: =countif(indirect($B17&"!$K:$T"),F$6) -> 0 | G17: =countif(indirect($B17&"!$K:$T"),G$6) -> 0 | H17: =countif(indirect($B17&"!$K:$T"),H$6) -> 0 | I17: =countif(indirect($B17&"!$K:$T"),I$6) -> 48 | J17: =countif(indirect($B17&"!$K:$T"),J$6) -> 136 | K17: =countif(indirect($B17&"!$K:$T"),K$6) -> 166 | P17: 請求書 | Q17: 中里 | R17: 1.5
B18: 取引先 | C18: 完了 | D18: 済 | E18: 金子 | F18: =countif(indirect($B18&"!$M:$T"),F$6) -> 0 | G18: =countif(indirect($B18&"!$M:$T"),G$6) -> 0 | H18: =countif(indirect($B18&"!$M:$T"),H$6) -> 0 | I18: =countif(indirect($B18&"!$M:$T"),I$6) -> 220 | J18: =countif(indirect($B18&"!$M:$T"),J$6) -> 421 | K18: =countif(indirect($B18&"!$M:$T"),K$6) -> 399 | P18: 国税関係書類 | Q18: 七浦 | R18: 1 | S18: ※旧UIもいる？
B19: 集計(請求書) | C19: 完了 | D19: 済 | E19: 北川 | F19: =countif(indirect($B19&"!$M:$T"),F$6) -> 0 | G19: =countif(indirect($B19&"!$M:$T"),G$6) -> 0 | H19: =countif(indirect($B19&"!$M:$T"),H$6) -> 0 | I19: =countif(indirect($B19&"!$M:$T"),I$6) -> 169 | J19: =countif(indirect($B19&"!$M:$T"),J$6) -> 147 | K19: =countif(indirect($B19&"!$M:$T"),K$6) -> 790 | P19: 取引先 | Q19: 七浦 | R19: 0.8
B20: システム設定 | C20: 完了 | D20: 済 | E20: 金田/北川/七浦/行田/富田（典） | F20: =countif(indirect($B20&"!$O:$R"),F$6) -> 0 | G20: =countif(indirect($B20&"!$O:$R"),G$6) -> 0 | H20: =countif(indirect($B20&"!$O:$R"),H$6) -> 0 | I20: =countif(indirect($B20&"!$O:$R"),I$6) -> 1730 | J20: =countif(indirect($B20&"!$O:$R"),J$6) -> 250 | K20: =countif(indirect($B20&"!$O:$R"),K$6) -> 4456 | L20: 法人カード | P20: 集計 | Q20: 七浦 | R20: 0.5
B21: 通知 | C21: 完了 | D21: 済 | E21: 金田 | F21: =countif(indirect($B21&"!$O:$R"),F$6) -> 0 | G21: =countif(indirect($B21&"!$O:$R"),G$6) -> 0 | H21: =countif(indirect($B21&"!$O:$R"),H$6) -> 0 | I21: =countif(indirect($B21&"!$O:$R"),I$6) -> 107 | J21: =countif(indirect($B21&"!$O:$R"),J$6) -> 0 | K21: =countif(indirect($B21&"!$O:$R"),K$6) -> 0 | L21: 法人カード | P21: システム設定 | Q21: 富田(典) | R21: 2
B22: 申請 | C22: 完了 | D22: 済 | E22: 金子 | F22: =countif(indirect($B22&"!$M:$T"),F$6) -> 0 | G22: =countif(indirect($B22&"!$M:$T"),G$6) -> 0 | H22: =countif(indirect($B22&"!$M:$T"),H$6) -> 0 | I22: =countif(indirect($B22&"!$M:$T"),I$6) -> 258 | J22: =countif(indirect($B22&"!$M:$T"),J$6) -> 25 | K22: =countif(indirect($B22&"!$M:$T"),K$6) -> 801 | P22: 個人設定 | Q22: 中里 | R22: 1
B23: 承認 | C23: 完了 | D23: 済 | E23: 北川 | F23: =countif(indirect($B23&"!$L:$O"),F$6) -> 0 | G23: =countif(indirect($B23&"!$L:$O"),G$6) -> 0 | H23: =countif(indirect($B23&"!$L:$O"),H$6) -> 0 | I23: =countif(indirect($B23&"!$L:$O"),I$6) -> 175 | J23: =countif(indirect($B23&"!$L:$O"),J$6) -> 3 | K23: =countif(indirect($B23&"!$L:$O"),K$6) -> 498 | P23: 通知 | Q23: 富田(典)
B24: 共通 | C24: 完了 | D24: 済 | E24: 富田（典）/本橋 | F24: =countif(indirect($B24&"!$N:$T"),F$6) -> 0 | G24: =countif(indirect($B24&"!$N:$T"),G$6) -> 0 | H24: =countif(indirect($B24&"!$N:$T"),H$6) -> 0 | I24: =countif(indirect($B24&"!$N:$T"),I$6) -> 331 | J24: =countif(indirect($B24&"!$N:$T"),J$6) -> 7 | K24: =countif(indirect($B24&"!$N:$T"),K$6) -> 1014 | P24: 共通コンポーネント | Q24: 本橋
B25: ※B列にシート名を入れると進捗が反映されます | E25: 合計 | F25: =SUM(F7:F24) -> 0 | G25: =SUM(G7:G24) -> 0 | H25: =SUM(H7:H24) -> 0 | I25: =SUM(I7:I24) -> 5501 | J25: =SUM(J7:J24) -> 1727 | K25: =SUM(K7:K24) -> 15354
J26: =I25+J25 -> 7228
C27: 1日の目標消化数(1人)： | D27: 150 | E27: ←～10/30
D28: 90 | E28: ←10/31～
E29: ↓OK+外
B30: 割り当て人数 | C30: 日付 | D30: 消化数(予定) | E30: 消化数(実績) | F30: 総ケース数
C31: 45586 | D31: 0 | E31: 0 | F31: 6970
C32: 45587 | D32: 2500 | E32: 2500 | F32: 6970
B33: 4 | C33: 45588 | D33: 3937 | E33: 3937 | F33: 6970
B34: 5 | C34: 45589 | D34: =D33+B34*$D$27 -> 4687 | E34: 4879 | F34: 6985
B35: 5.5 | C35: 45590 | D35: =D34+B35*$D$27 -> 5512 | E35: 5678 | F35: 7172
B36: 0 | C36: 45591 | D36: =D35+B36*$D$27 -> 5512 | E36: 5678 | F36: 7172
B37: 0 | C37: 45592 | D37: =D36+B37*$D$27 -> 5512 | E37: 5678 | F37: 7172
B38: 2.7 | C38: 45593 | D38: =D37+B38*$D$27 -> 5917 | E38: 5973 | F38: 7172 | G38: =if(E38=0,"",E38-D38) -> 56
B39: 1 | C39: 45594 | D39: =D38+B39*$D$27 -> 6067 | E39: 6058 | F39: 7152 | G39: =if(E39=0,"",E39-D39) -> -9
B40: 3.3 | C40: 45595 | D40: =D39+B40*$D$27 -> 6562 | E40: 6570 | F40: 7230 | G40: =if(E40=0,"",E40-D40) -> 8
B41: 3.9 | C41: 45596 | D41: =D40+B41*$D$28 -> 6913 | E41: 6946 | F41: 7229 | G41: =if(E41=0,"",E41-D41) -> 33
B42: 2.5 | C42: 45597 | D42: =D41+B42*$D$28 -> 7138 | E42: 7130 | F42: 7229 | G42: =if(E42=0,"",E42-D42) -> -8
B43: 0 | C43: 45598 | D43: =D42+B43*$D$28 -> 7138 | E43: 7130 | F43: =$F$42 -> 7229
B44: 0 | C44: 45599 | D44: =D43+B44*$D$28 -> 7138 | E44: 7130 | F44: =$F$42 -> 7229
B45: 0 | C45: 45600 | D45: =D44+B45*$D$28 -> 7138 | E45: 7130 | F45: =$F$42 -> 7229
B46: 1 | C46: 45601 | D46: =D45+B46*$D$28 -> 7228 | E46: 7150 | F46: 7229
B47: 0 | C47: 45602 | D47: =D46+B47*$D$28 -> 7228 | F47: 7229
B48: 0 | C48: 45603 | D48: =D47+B48*$D$28 -> 7228 | F48: 7229
B49: 0 | C49: 45604 | D49: =D48+B49*$D$28 -> 7228 | F49: 7229
B50: 0 | C50: 45605 | D50: =D49+B50*$D$28 -> 7228 | F50: =$F$49 -> 7229
B51: 0 | C51: 45606 | D51: =D50+B51*$D$28 -> 7228 | F51: =$F$49 -> 7229
B52: 0 | C52: 45607 | D52: =D51+B52*$D$28 -> 7228
B53: 0 | C53: 45608 | D53: =D52+B53*$D$28 -> 7228
B54: 0 | C54: 45609 | D54: =D53+B54*$D$28 -> 7228
B55: 0 | C55: 45610 | D55: =D54+B55*$D$28 -> 7228
B56: 0 | C56: 45611 | D56: =D55+B56*$D$28 -> 7228
B57: 0 | C57: 45612 | D57: =D56+B57*$D$28 -> 7228
B58: 0 | C58: 45613 | D58: =D57+B58*$D$28 -> 7228
B59: 0 | C59: 45614 | D59: =D58+B59*$D$28 -> 7228
B60: 0 | C60: 45615 | D60: =D59+B60*$D$28 -> 7228
B61: 0 | C61: 45616 | D61: =D60+B61*$D$28 -> 7228
B62: 0 | C62: 45617 | D62: =D61+B62*$D$28 -> 7228
B63: 0 | C63: 45618 | D63: =D62+B63*$D$28 -> 7228

Sheet 共通
N2: Win11/ Chrome | O2: Win11/ Edge | P2: Win11/ Firefox | Q2: Win11/ Safari
B3: No | C3: 画面 | D3: 導線 | E3: 詳細 | K3: テスト実行手順 | L3: 期待値 | M3: 備考 | N3: TK+TI+TD | O3: TK+TI+TD | P3: TK単体 | Q3: TK単体 | R3: 実行者 | S3: 実行備考 | T3: 起票JIRA No
B4: =ROW()-ROW($B$3) -> 1 | C4: プロジェクトを選択モーダル | D4: 経費登録、経費編集、稟議登録、稟議編集、請求書登録、請求書編集、国税関係書類登録、国税関係書類編集 | E4: プロジェクト追加 | F4: プロジェクト名 | K4: プロジェクトを選択モーダルを開く プロジェクト名に任意の入力を行う | L4: 入力できること | N4: OK | O4: - | P4: - | Q4: - | R4: 富田（典）
B5: =ROW()-ROW($B$3) -> 2 | F5: プロジェクトID | K5: プロジェクトIDに任意の入力を行う | L5: 入力できること | N5: OK | O5: - | P5: - | Q5: - | R5: 富田（典）
B6: =ROW()-ROW($B$3) -> 3 | F6: プロジェクトを追加 | K6: プロジェクト名、IDに任意の入力を行う プロジェクトを追加ボタンを押下する 新規登録もしくは編集画面のプロジェクトの欄を確認する | L6: 入力したプロジェクトが追加されること 追加したプロジェクトが表示されていること | N6: OK | O6: - | P6: - | Q6: - | R6: 富田（典）
B7: =ROW()-ROW($B$3) -> 4 | F7: 追加されたプロジェクトの確認 | K7: プロジェクト名、IDに任意の入力を行う プロジェクトを追加ボタンを押下する システム設定>プロジェクトで検索を行う | L7: 追加したプロジェクトが表示されること | N7: OK | O7: - | P7: - | Q7: - | R7: 富田（典）
B8: =ROW()-ROW($B$3) -> 5 | E8: 検索 | F8: 検索欄 | G8: 部分一致 | K8: 検索欄にプロジェクト名の一部を入力する 検索ボタンを押下する | L8: 条件に基づいた検索結果が表示されること | N8: OK | O8: - | P8: - | Q8: - | R8: 富田（典）
B9: =ROW()-ROW($B$3) -> 6 | F9: 検索欄 | G9: 全体一致 | K9: 検索欄にプロジェクト名を入力する 検索ボタンを押下する | L9: 同上 | N9: OK | O9: - | P9: - | Q9: - | R9: 富田（典）
B10: =ROW()-ROW($B$3) -> 7 | F10: 検索欄 | G10: ×ボタン | K10: 検索欄にプロジェクト名を入力する ×ボタンを押下する | L10: 検索欄がクリアされること | N10: OK | O10: - | P10: - | Q10: - | R10: 富田（典）
B11: =ROW()-ROW($B$3) -> 8 | F11: 検索欄 | G11: 検索ボタン | K11: 任意のプロジェクト名を入力する 検索ボタンを押下する | L11: 条件に基づいた検索結果が表示されること | N11: OK | O11: - | P11: - | Q11: - | R11: 富田（典）
B12: =ROW()-ROW($B$3) -> 9 | E12: 選択 | K12: 任意のプロジェクトを選択する 新規登録もしくは編集画面のプロジェクトの欄を確認する | L12: 選択したプロジェクトが反映されていること | N12: OK | O12: - | P12: - | Q12: - | R12: 富田（典）
B13: =ROW()-ROW($B$3) -> 10 | E13: ×ボタン | K13: ×ボタンを押下する | L13: モーダルが閉じること | N13: OK | O13: - | P13: - | Q13: - | R13: 富田（典）
B14: =ROW()-ROW($B$3) -> 11 | E14: モーダル外を押下 | K14: モーダル外を押下する | L14: モーダルが閉じること | N14: OK | O14: - | P14: - | Q14: - | R14: 富田（典）
B15: =ROW()-ROW($B$3) -> 12 | C15: 参加者モーダル | D15: 経費登録、経費編集 | E15: 自社 | F15: 自社の参加者を追加 | G15: ヘッダー(合計人数) | K15: 自社:参加者モーダルを開く 「自社の参加者を追加」横の人数を確認する | L15: 合計人数が表示されていること 内容が正しいこと | N15: OK | O15: - | P15: - | Q15: - | R15: 富田（典）
B16: =ROW()-ROW($B$3) -> 13 | G16: 参加者名 | K16: 参加者名を確認する | L16: 参加者名が表示されていること 内容が正しいこと | N16: OK | O16: - | P16: - | Q16: - | R16: 富田（典） | S16: 内容に齟齬は無いが、参加者一覧での表示順が何に沿ってるのか気になる
B17: =ROW()-ROW($B$3) -> 14 | G17: その他 | H17: 詳細 | I17: 人数 | K17: 社員を追加から任意の人数を追加する その他が追加されることを確認 詳細を確認 | L17: 参加者欄にその他が表示されていること 詳細に人数が表示されていること 人数が正しいこと | N17: OK | O17: - | P17: - | Q17: - | R17: 富田（典）
B18: =ROW()-ROW($B$3) -> 15 | G18: その他 | H18: 詳細 | I18: 人数変更 | J18: ∧ | K18: 参加者名その他の詳細欄を確認 人数の∧ボタンを押下する | L18: 人数が1増えること ヘッダーの合計人数に反映されること | N18: OK | O18: - | P18: - | Q18: - | R18: 富田（典）
B19: =ROW()-ROW($B$3) -> 16 | G19: その他 | H19: 詳細 | I19: 人数変更 | J19: ∨ | K19: 参加者名その他の詳細欄を確認 人数の∨ボタンを押下する | L19: 人数が1減ること ヘッダーの合計人数に反映されること | N19: OK | O19: - | P19: - | Q19: - | R19: 富田（典）
B20: =ROW()-ROW($B$3) -> 17 | G20: その他 | H20: 詳細 | I20: 人数変更 | J20: 直接入力 | K20: 参加者名その他の詳細欄を確認 人数欄に直接数字を入力する | L20: 入力できること ヘッダーの合計人数に反映されること | N20: OK | O20: - | P20: - | Q20: - | R20: 富田（典）
B21: =ROW()-ROW($B$3) -> 18 | G21: その他 | H21: 詳細 | I21: 人数変更 | J21: イレギュラーな数字 | K21: 参加者名その他の詳細欄を確認 人数欄にマイナス、小数点以下、0を入力する | L21: 入力できないこと 反映されないこと | N21: OK | O21: - | P21: - | Q21: - | R21: 富田（典）
B22: =ROW()-ROW($B$3) -> 19 | G22: 除外する | K22: 任意の参加者の除外ボタンを押下する | L22: 除外されること ヘッダーの合計人数に反映されること | N22: OK | O22: - | P22: - | Q22: - | R22: 富田（典）
B23: =ROW()-ROW($B$3) -> 20 | F23: 社員を追加 | G23: 氏名 | K23: 社員を追加＞氏名を選択する 氏名欄に任意の入力を行う 追加ボタンを押下する | L23: 入力した氏名が参加者一覧に追加されること ヘッダーの合計人数に反映されること | N23: OK | O23: - | P23: - | Q23: - | R23: 富田（典）
B24: =ROW()-ROW($B$3) -> 21 | G24: 人数 | H24: 任意の数字 | K24: 社員を追加＞人数を追加する 任意の数字を入力する 追加ボタンを押下する | L24: その他が参加者一覧に追加されること 詳細の人数欄が入力した数値であること ヘッダーの合計人数に反映されること | N24: OK | O24: - | P24: - | Q24: - | R24: 富田（典）
B25: =ROW()-ROW($B$3) -> 22 | G25: 人数 | H25: 小数点以下 | K25: 社員を追加＞人数を追加する 小数点以下の数字を入力する 追加ボタンを押下する | L25: エラーメッセージが表示されること 追加されないこと | N25: OK | O25: - | P25: - | Q25: - | R25: 富田（典） | S25: 0.99999…以下ならエラーとなる。 1以上で小数点以下を含む数値を入力したら、小数点以下は切り捨てで整数部分を読み取って、その他の参加者が追加される
B26: =ROW()-ROW($B$3) -> 23 | G26: 人数 | H26: 既に追加されている場合 | K26: 既にその他が参加者に追加されている状態で 社員を追加＞人数を追加する 追加ボタンを押下する | L26: エラーメッセージが表示されること 追加されないこと | N26: OK | O26: - | P26: - | Q26: - | R26: 富田（典）
B27: =ROW()-ROW($B$3) -> 24 | G27: 人数 | H27: 0以下 | K27: 社員を追加＞人数を追加する 0以下の数字を入力する 追加ボタンを押下する | L27: エラーメッセージが表示されること 追加されないこと | N27: OK | O27: - | P27: - | Q27: - | R27: 富田（典）
B28: =ROW()-ROW($B$3) -> 25 | F28: 自社の社員 | G28: 名前 | H28: 部分一致 | K28: 自社の社員を検索 名前の一部を入力する 検索ボタンを押下する | L28: 条件を満たした検索結果が表示されること | N28: OK | O28: - | P28: - | Q28: - | R28: 富田（典） | S28: 検索時、既に参加者として選択済みの従業員は、検索条件に合わなくても一覧に表示され続ける仕様
B29: =ROW()-ROW($B$3) -> 26 | G29: 名前 | H29: 完全一致 | K29: 自社の社員を検索 名前を入力する 検索ボタンを押下する | L29: 同上 | N29: OK | O29: - | P29: - | Q29: - | R29: 富田（典）
B30: =ROW()-ROW($B$3) -> 27 | G30: 部署 | H30: 部分一致 | K30: 自社の部署を検索 部署名の一部を入力する 検索ボタンを押下する | L30: 同上 | N30: OK | O30: - | P30: - | Q30: - | R30: 富田（典）
B31: =ROW()-ROW($B$3) -> 28 | G31: 部署 | H31: 完全一致 | K31: 自社の部署を検索 部署名を入力する 検索ボタンを押下する | L31: 同上 | N31: OK | O31: - | P31: - | Q31: - | R31: 富田（典）
B32: =ROW()-ROW($B$3) -> 29 | G32: 選択 | K32: 任意の検索を行う 名前、部署の横のボックスを押下する | L32: 選択した氏名、部署が参加者一覧に追加されること | N32: OK | O32: - | P32: - | Q32: - | R32: 富田（典）
B33: =ROW()-ROW($B$3) -> 30 | G33: 削除 | K33: 任意の検索を行う 名前、部署の横のボックスを押下する 削除ボタンを押下する | L33: 削除しますか？モーダルが表示されること 削除を選択すると参加者一覧から削除されること | N33: 外 | O33: - | P33: - | Q33: - | R33: 富田（典） | S33: モーダル内で任意に作成した参加者にのみ、 ごみ箱アイコンが表示される 参加者として✅している状態だと、「削除しました」メッセージが出るが 実際には削除できていない（自社社員一覧の最下部に移動するだけ？） (水木)本番不具合なので対象外とします | T33: https://beartail.atlassian.net/browse/SC-179
B34: =ROW()-ROW($B$3) -> 31 | G34: 検索条件をリセット | K34: 任意の検索を行う 検索条件をリセットボタンを押下する | L34: 検索欄がクリアされること 検索結果がクリアされること | N34: OK | O34: - | P34: - | Q34: - | R34: 富田（典）
B35: =ROW()-ROW($B$3) -> 32 | F35: 表示件数 | K35: 表示件数を変更する | L35: 選択した表示件数になること | N35: OK | O35: - | P35: - | Q35: - | R35: 富田（典）
B36: =ROW()-ROW($B$3) -> 33 | F36: 保存 | K36: 参加者に任意の変更を行う 保存ボタンを押下する | L36: モーダルが閉じること 変更が保存されること | N36: OK | O36: - | P36: - | Q36: - | R36: 富田（典）
B37: =ROW()-ROW($B$3) -> 34 | F37: ×ボタン | K37: ×ボタンを押下する | L37: モーダルが閉じること | N37: OK | O37: - | P37: - | Q37: - | R37: 富田（典）
B38: =ROW()-ROW($B$3) -> 35 | F38: モーダル以外を押下 | K38: モーダル以外の部分を押下する | L38: モーダルが閉じること | N38: OK | O38: - | P38: - | Q38: - | R38: 富田（典）
B39: =ROW()-ROW($B$3) -> 36 | F39: 反映 | K39: 参加者に任意の変更を行う モーダルを閉じる 参加者欄を確認する | L39: 変更が反映されていること | N39: OK | O39: - | P39: - | Q39: - | R39: 富田（典）
B40: =ROW()-ROW($B$3) -> 37 | E40: 取引先 | F40: 取引先の参加者を追加 | G40: ヘッダー(合計人数) | K40: 自社:参加者モーダルを開く 「自社の参加者を追加」横の人数を確認する | L40: 合計人数が表示されていること 内容が正しいこと | N40: OK | O40: - | P40: - | Q40: - | R40: 富田（典） | S40: 手順読み替え 自社→取引先
B41: =ROW()-ROW($B$3) -> 38 | G41: 参加者名 | K41: 参加者名を確認する | L41: 参加者名が表示されていること 内容が正しいこと | N41: OK | O41: - | P41: - | Q41: - | R41: 富田（典）
B42: =ROW()-ROW($B$3) -> 39 | G42: その他 | H42: 詳細 | I42: 人数 | K42: 社員を追加から任意の人数を追加する その他が追加されることを確認 詳細を確認 | L42: 参加者欄にその他が表示されていること 詳細に人数が表示されていること 人数が正しいこと | N42: OK | O42: - | P42: - | Q42: - | R42: 富田（典）
B43: =ROW()-ROW($B$3) -> 40 | G43: その他 | H43: 詳細 | I43: 人数変更 | J43: ∧ | K43: 参加者名その他の詳細欄を確認 人数の∧ボタンを押下する | L43: 人数が1増えること ヘッダーの合計人数に反映されること | N43: OK | O43: - | P43: - | Q43: - | R43: 富田（典）
B44: =ROW()-ROW($B$3) -> 41 | G44: その他 | H44: 詳細 | I44: 人数変更 | J44: ∨ | K44: 参加者名その他の詳細欄を確認 人数の∨ボタンを押下する | L44: 人数が1減ること ヘッダーの合計人数に反映されること | N44: OK | O44: - | P44: - | Q44: - | R44: 富田（典）
B45: =ROW()-ROW($B$3) -> 42 | G45: その他 | H45: 詳細 | I45: 人数変更 | J45: 直接入力 | K45: 参加者名その他の詳細欄を確認 人数欄に直接数字を入力する | L45: 入力できること ヘッダーの合計人数に反映されること | N45: OK | O45: - | P45: - | Q45: - | R45: 富田（典）
B46: =ROW()-ROW($B$3) -> 43 | G46: その他 | H46: 詳細 | I46: 人数変更 | J46: イレギュラーな数字 | K46: 参加者名その他の詳細欄を確認 人数欄にマイナス、小数点以下、0を入力する | L46: 入力できないこと 反映されないこと | N46: OK | O46: - | P46: - | Q46: - | R46: 富田（典）
B47: =ROW()-ROW($B$3) -> 44 | G47: 除外する | K47: 任意の参加者の除外ボタンを押下する | L47: 除外されること ヘッダーの合計人数に反映されること | N47: OK | O47: - | P47: - | Q47: - | R47: 富田（典）
B48: =ROW()-ROW($B$3) -> 45 | F48: 社員を追加 | G48: 氏名 | K48: 社員を追加＞氏名を選択する 氏名欄に任意の入力を行う 追加ボタンを押下する | L48: 入力した氏名が参加者一覧に追加されること ヘッダーの合計人数に反映されること | N48: OK | O48: - | P48: - | Q48: - | R48: 富田（典） | S48: 氏名or人数のみでの追加は可能。 会社名のみでの追加は不可で、会社名+氏名or人数なら追加可能
B49: =ROW()-ROW($B$3) -> 46 | G49: 人数 | H49: 任意の数字 | K49: 社員を追加＞人数を追加する 任意の数字を入力する 追加ボタンを押下する | L49: その他が参加者一覧に追加されること 詳細の人数欄が入力した数値であること ヘッダーの合計人数に反映されること | N49: OK | O49: - | P49: - | Q49: - | R49: 富田（典）
B50: =ROW()-ROW($B$3) -> 47 | G50: 人数 | H50: 小数点以下 | K50: 社員を追加＞人数を追加する 小数点以下の数字を入力する 追加ボタンを押下する | L50: エラーメッセージが表示されること 追加されないこと | N50: OK | O50: - | P50: - | Q50: - | R50: 富田（典）
B51: =ROW()-ROW($B$3) -> 48 | G51: 人数 | H51: 既に追加されている場合 | K51: 既にその他が参加者に追加されている状態で 社員を追加＞人数を追加する 追加ボタンを押下する | L51: エラーメッセージが表示されること 追加されないこと | N51: OK | O51: - | P51: - | Q51: - | R51: 富田（典） | S51: 取引先の参加者は会社名ごとに枠が分かれているため、 会社名が異なるなら、その他の参加者は複数追加できる。 同じ会社名の中に複数のその他の参加者は追加できない。
B52: =ROW()-ROW($B$3) -> 49 | G52: 人数 | H52: 0以下 | K52: 社員を追加＞人数を追加する 0以下の数字を入力する 追加ボタンを押下する | L52: エラーメッセージが表示されること 追加されないこと | N52: OK | O52: - | P52: - | Q52: - | R52: 富田（典）
B53: =ROW()-ROW($B$3) -> 50 | F53: 取引先の社員 | G53: 名前 | H53: 部分一致 | K53: 取引先の社員を検索 名前の一部を入力する 検索ボタンを押下する | L53: 条件を満たした検索結果が表示されること | N53: OK | O53: - | P53: - | Q53: - | R53: 富田（典） | S53: 検索時、既に参加者として選択済みの従業員は、検索条件に合わなくても一覧に表示され続ける仕様
B54: =ROW()-ROW($B$3) -> 51 | G54: 名前 | H54: 完全一致 | K54: 取引先の会社名を検索 名前を入力する 検索ボタンを押下する | L54: 同上 | N54: OK | O54: - | P54: - | Q54: - | R54: 富田（典） | S54: 手順読み替え 会社名→社員
B55: =ROW()-ROW($B$3) -> 52 | G55: 部署 | H55: 部分一致 | K55: 取引先の会社名を検索 会社名の一部を入力する 検索ボタンを押下する | L55: 同上 | N55: OK | O55: - | P55: - | Q55: - | R55: 富田（典） | S55: 項目読み替え 部署→会社名
B56: =ROW()-ROW($B$3) -> 53 | G56: 部署 | H56: 完全一致 | K56: 取引先の会社名を検索 会社名を入力する 検索ボタンを押下する | L56: 同上 | N56: OK | O56: - | P56: - | Q56: - | R56: 富田（典） | S56: 項目読み替え 部署→会社名
B57: =ROW()-ROW($B$3) -> 54 | G57: 選択 | K57: 任意の検索を行う 名前、会社名の横のボックスを押下する | L57: 選択した氏名、部署が参加者一覧に追加されること | N57: OK | O57: - | P57: - | Q57: - | R57: 富田（典）
B58: =ROW()-ROW($B$3) -> 55 | G58: 削除 | K58: 任意の検索を行う 名前、会社名の横のボックスを押下する 削除ボタンを押下する | L58: 削除しますか？モーダルが表示されること 削除を選択すると参加者一覧から削除されること | N58: 外 | O58: - | P58: - | Q58: - | R58: 富田（典） | S58: モーダル内で任意に作成した参加者にのみ、 ごみ箱アイコンが表示される 参加者として✅している状態だと、「削除しました」メッセージが出るが 実際には削除できていない（自社社員一覧の最下部に移動するだけ？） (水木)本番不具合なので対象外とします | T58: https://beartail.atlassian.net/browse/SC-179
B59: =ROW()-ROW($B$3) -> 56 | G59: 検索条件をリセット | K59: 任意の検索を行う 検索条件をリセットボタンを押下する | L59: 検索欄がクリアされること 検索結果がクリアされること | N59: OK | O59: - | P59: - | Q59: - | R59: 富田（典）
B60: =ROW()-ROW($B$3) -> 57 | F60: 表示件数 | K60: 表示件数を変更する | L60: 選択した表示件数になること | N60: OK | O60: - | P60: - | Q60: - | R60: 富田（典）
B61: =ROW()-ROW($B$3) -> 58 | F61: 保存 | K61: 参加者に任意の変更を行う 保存ボタンを押下する | L61: モーダルが閉じること 変更が保存されること | N61: OK | O61: - | P61: - | Q61: - | R61: 富田（典） | S61: 保存ボタンを押さなくても変更が保存されてるっぽい
B62: =ROW()-ROW($B$3) -> 59 | F62: ×ボタン | K62: ×ボタンを押下する | L62: モーダルが閉じること | N62: OK | O62: - | P62: - | Q62: - | R62: 富田（典）
B63: =ROW()-ROW($B$3) -> 60 | F63: モーダル以外を押下 | K63: モーダル以外の部分を押下する | L63: モーダルが閉じること | N63: OK | O63: - | P63: - | Q63: - | R63: 富田（典）
B64: =ROW()-ROW($B$3) -> 61 | F64: 反映 | K64: 参加者に任意の変更を行う モーダルを閉じる 参加者欄を確認する | L64: 変更が反映されていること | N64: OK | O64: - | P64: - | Q64: - | R64: 富田（典）
B65: =ROW()-ROW($B$3) -> 62 | C65: 従業員選択 | D65: 取引先-担当者設定 | E65: 検索欄 | F65: 従業員名 | G65: 部分一致 | K65: 検索欄に従業員名の一部を入力する 検索ボタンを押下する 検索結果を確認する | L65: 条件を満たした検索結果が表示されること | N65: OK | O65: - | P65: - | Q65: - | R65: 富田（典）
B66: =ROW()-ROW($B$3) -> 63 | E66: 検索欄 | G66: 完全一致 | K66: 検索欄に従業員名を入力する 検索ボタンを押下する 検索結果を確認する | L66: 同上 | N66: OK | O66: - | P66: - | Q66: - | R66: 富田（典）
B67: =ROW()-ROW($B$3) -> 64 | E67: 検索欄 | F67: メールアドレス | G67: 部分一致 | K67: 検索欄にメールアドレスの一部を入力する 検索ボタンを押下する 検索結果を確認する | L67: 同上 | N67: OK | O67: - | P67: - | Q67: - | R67: 富田（典）
B68: =ROW()-ROW($B$3) -> 65 | E68: 検索欄 | G68: 完全一致 | K68: 検索欄にメールアドレスを入力する 検索ボタンを押下する 検索結果を確認する | L68: 同上 | N68: OK | O68: - | P68: - | Q68: - | R68: 富田（典）
B69: =ROW()-ROW($B$3) -> 66 | E69: 検索欄 | F69: ×ボタン | K69: 検索欄に任意の入力をする ×ボタンを押下する | L69: 検索欄がクリアされること | N69: OK | O69: - | P69: - | Q69: - | R69: 富田（典）
B70: =ROW()-ROW($B$3) -> 67 | E70: 検索結果:件 | K70: 任意の検索を行う 検索結果を確認する | L70: 検索にヒットした件数が表示されていること 件数が合っていること | N70: OK | O70: - | P70: - | Q70: - | R70: 富田（典）
B71: =ROW()-ROW($B$3) -> 68 | E71: 選択 | K71: 任意の従業員を選択する | L71: チェックマークが付くこと 担当者設定に選択した従業員が追加されること | N71: OK | O71: - | P71: - | Q71: - | R71: 富田（典）
B72: =ROW()-ROW($B$3) -> 69 | E72: 閉じる | K72: 閉じるボタンを押下する | L72: モーダルが閉じること | N72: OK | O72: - | P72: - | Q72: - | R72: 富田（典）
B73: =ROW()-ROW($B$3) -> 70 | E73: ×ボタン | K73: ×ボタンを押下する | L73: モーダルが閉じること | N73: OK | O73: - | P73: - | Q73: - | R73: 富田（典）
B74: =ROW()-ROW($B$3) -> 71 | E74: モーダル以外を押下 | K74: モーダル以外を押下する | L74: モーダルが閉じること | N74: OK | O74: - | P74: - | Q74: - | R74: 富田（典）
B75: =ROW()-ROW($B$3) -> 72 | E75: 反映 | K75: 任意の変更を行う モーダルを閉じる 担当者設定を確認する | L75: モーダルでの変更が反映されていること | N75: OK | O75: - | P75: - | Q75: - | R75: 富田（典）
B76: =ROW()-ROW($B$3) -> 73 | C76: 取引先を選択モーダル | D76: 請求書登録/編集、国税関係書類登録/編集、稟議登録/編集 | E76: 検索欄 | F76: 取引先名 | G76: 部分一致 | K76: 検索欄に取引先名の一部を入力する 検索ボタンを押下する 検索結果を確認する | L76: 条件を満たした検索結果が表示されること | N76: OK | O76: - | P76: - | Q76: - | R76: 富田（典）
B77: =ROW()-ROW($B$3) -> 74 | E77: 検索欄 | G77: 完全一致 | K77: 検索欄に取引先名を入力する 検索ボタンを押下する 検索結果を確認する | L77: 同上 | N77: OK | O77: - | P77: - | Q77: - | R77: 富田（典）
B78: =ROW()-ROW($B$3) -> 75 | E78: 検索欄 | F78: 取引先コード | G78: 部分一致 | K78: 検索欄に取引先コードの一部を入力する 検索ボタンを押下する 検索結果を確認する | L78: 同上 | N78: OK | O78: - | P78: - | Q78: - | R78: 富田（典）
B79: =ROW()-ROW($B$3) -> 76 | E79: 検索欄 | G79: 完全一致 | K79: 検索欄に取引先コードを入力する 検索ボタンを押下する 検索結果を確認する | L79: 同上 | N79: OK | O79: - | P79: - | Q79: - | R79: 富田（典）
B80: =ROW()-ROW($B$3) -> 77 | E80: 検索欄 | F80: ×ボタン | K80: 検索欄に任意の入力をする ×ボタンを押下する | L80: 検索欄がクリアされること | N80: OK | O80: - | P80: - | Q80: - | R80: 富田（典）
B81: =ROW()-ROW($B$3) -> 78 | E81: 検索結果:件 | K81: 任意の検索を行う 検索結果を確認する | L81: 検索にヒットした件数が表示されていること 件数が合っていること | N81: OK | O81: - | P81: - | Q81: - | R81: 富田（典）
B82: =ROW()-ROW($B$3) -> 79 | E82: 選択 | K82: 任意の取引先を選択する | L82: チェックマークが付くこと 取引先に選択した取引先が追加されること | N82: OK | O82: - | P82: - | Q82: - | R82: 富田（典） | S82: 期待値読み替え チェックマーク→ラジオボタン
B83: =ROW()-ROW($B$3) -> 80 | E83: 閉じる | K83: 閉じるボタンを押下する | L83: モーダルが閉じること | N83: 外 | O83: - | P83: - | Q83: - | R83: 富田（典） | S83: 閉じるボタンがそもそも無いため対象外とします （コピペで項目作ったから？）
B84: =ROW()-ROW($B$3) -> 81 | E84: ×ボタン | K84: ×ボタンを押下する | L84: モーダルが閉じること | N84: OK | O84: - | P84: - | Q84: - | R84: 富田（典）
B85: =ROW()-ROW($B$3) -> 82 | E85: モーダル以外を押下 | K85: モーダル以外を押下する | L85: モーダルが閉じること | N85: OK | O85: - | P85: - | Q85: - | R85: 富田（典）
B86: =ROW()-ROW($B$3) -> 83 | E86: 反映 | K86: 任意の変更を行う モーダルを閉じる 取引先設定を確認する | L86: モーダルでの変更が反映されていること | N86: OK | O86: - | P86: - | Q86: - | R86: 富田（典）
B87: =ROW()-ROW($B$3) -> 84 | C87: 定期情報設定 | D87: 個人設定>定期区間設定 システム設定>従業員>任意の従業員>定期区間 | E87: 交通機関 | F87: 電車 | K87: 左記の項目のみを選択する 出発駅を検索する | L87: 電車の駅のみが表示されること | N87: OK | O87: - | P87: - | Q87: - | R87: 富田（典）
B88: =ROW()-ROW($B$3) -> 85 | F88: バス | K88: 同上 | L88: バスのターミナルのみが表示されること | N88: OK | O88: - | P88: - | Q88: - | R88: 富田（典）
B89: =ROW()-ROW($B$3) -> 86 | E89: 詳細設定 | F89: 交通機関 | G89: 新幹線 | K89: 左記の項目のみを選択する 経路を検索して登録する | L89: 問題なく登録できること 設定が反映されていること | M89: （駅すぱあとのAPIを利用しているため、検索に不具合があってもTOKIUM側で直せない) | N89: OK | O89: - | P89: - | Q89: - | R89: 富田（典） | S89: 経路検索は、100km以内の区間で試すこと （それ以上の距離だとヒットしない）
B90: =ROW()-ROW($B$3) -> 87 | G90: 有料特急 | K90: 同上 | L90: 同上 | N90: OK | O90: - | P90: - | Q90: - | R90: 富田（典） | S90: 有料特急を利用した経路が提示されていない気がする… 何かしら結果が出ている（恐らく所要時間が少ない順）ので現状はOKとする
B91: =ROW()-ROW($B$3) -> 88 | G91: ライナー | K91: 同上 | L91: 同上 | N91: OK | O91: - | P91: - | Q91: - | R91: 富田（典） | S91: ライナーを利用した経路が提示されていない気がする… 何かしら結果が出ている（恐らく所要時間が少ない順）ので現状はOKとする
B92: =ROW()-ROW($B$3) -> 89 | G92: 路線バス | K92: 同上 | L92: 同上 | N92: OK | O92: - | P92: - | Q92: - | R92: 富田（典） | S92: 路線バスを利用した経路のみに絞れていない気がする… （出発/到着駅をバス停にしたとしても、電車での移動経路を強制される？）
B93: =ROW()-ROW($B$3) -> 90 | G93: 連絡バス | K93: 同上 | L93: 同上 | N93: OK | O93: - | P93: - | Q93: - | R93: 富田（典） | S93: 連絡バスを利用した経路が提示されていない気がする… 何かしら結果が出ている（恐らく所要時間が少ない順）ので現状はOKとする | W93: そもそも連絡バス～海路って定期区間としてありえる？ 選択肢として要らない気がする…
B94: =ROW()-ROW($B$3) -> 91 | G94: 高速バス | K94: 同上 | L94: 同上 | N94: OK | O94: - | P94: - | Q94: - | R94: 富田（典） | S94: 高速バスを利用した経路が提示されていない気がする… 何かしら結果が出ている（恐らく所要時間が少ない順）ので現状はOKとする
B95: =ROW()-ROW($B$3) -> 92 | G95: 深夜急行バス | K95: 同上 | L95: 同上 | N95: OK | O95: - | P95: - | Q95: - | R95: 富田（典） | S95: 深夜急行バスを利用した経路が提示されていない気がする… 何かしら結果が出ている（恐らく所要時間が少ない順）ので現状はOKとする
B96: =ROW()-ROW($B$3) -> 93 | G96: 空路 | K96: 同上 | L96: 同上 | N96: OK | O96: - | P96: - | Q96: - | R96: 富田（典） | S96: 空路を利用した経路が提示されていない気がする… 何かしら結果が出ている（恐らく所要時間が少ない順）ので現状はOKとする
B97: =ROW()-ROW($B$3) -> 94 | G97: 海路 | K97: 同上 | L97: 同上 | N97: OK | O97: - | P97: - | Q97: - | R97: 富田（典） | S97: 海路を利用した経路が提示されていない気がする… 何かしら結果が出ている（恐らく所要時間が少ない順）ので現状はOKとする
B98: =ROW()-ROW($B$3) -> 95 | F98: 新幹線割引 | G98: EX予約 | K98: 同上 | L98: 同上 | N98: OK | O98: - | P98: - | Q98: - | R98: 富田（典） | S98: 新幹線割引のいずれを設定しても、1か月分の定期として算出した金額には影響しなかった。 設定することで経路がおかしくなる等は起こっていない。
B99: =ROW()-ROW($B$3) -> 96 | G99: EX予約e特急券 | K99: 同上 | L99: 同上 | N99: OK | O99: - | P99: - | Q99: - | R99: 富田（典） | S99: 同上
B100: =ROW()-ROW($B$3) -> 97 | G100: EX予約早得 | K100: 同上 | L100: 同上 | N100: OK | O100: - | P100: - | Q100: - | R100: 富田（典） | S100: 同上
B101: =ROW()-ROW($B$3) -> 98 | G101: EX予約早得21 | K101: 同上 | L101: 同上 | N101: OK | O101: - | P101: - | Q101: - | R101: 富田（典） | S101: 同上
...

Sheet 本橋作業用
N2: Win11/ Chrome | P2: Win11/ Edge | Q2: Win11/ Firefox | R2: Win11/ Safari
B3: No | C3: 画面 | D3: 確認対象 | E3: 詳細 | K3: テスト実行手順 | L3: 期待値 | M3: 備考 | N3: TK+TI+TD | O3: TK+TD | P3: TI+TD | Q3: TK単体 | R3: TD単体 | S3: 実行者 | T3: 実行備考 | U3: 起票JIRA No
B4: =ROW()-ROW($B$3) -> 1 | C4: 経費一覧 | D4: 経費を登録する | E4: 手入力 | K4: 経費を登録する＞手入力を押下する 任意の設定で経費を登録する | L4: 指定した経費が作成できること 保存した経費に入力した内容が反映されていること | M4: 新規ボタンと共通なので項目は省略 | N4: 未 | O4: 未 | P4: 未 | Q4: 未 | R4: 未
B5: =ROW()-ROW($B$3) -> 2 | C5: 経費一覧 | E5: 交通費入力 | K5: 経費を登録する＞交通費入力を押下する 任意の設定で経費を登録する | L5: - | M5: 新規ボタンと共通なので項目は省略 | N5: 未 | O5: 未 | P5: 未 | Q5: 未 | R5: 未
B6: =ROW()-ROW($B$3) -> 3 | C6: 経費一覧 | E6: 日当 | K6: 経費を登録する＞日当を押下する 任意の設定で経費を登録する | L6: - | M6: 新規ボタンと共通なので項目は省略 | N6: 未 | O6: 未 | P6: 未 | Q6: 未 | R6: 未
B7: =ROW()-ROW($B$3) -> 4 | C7: 経費一覧 | E7: 自動入力 | K7: 経費を登録する＞自動入力を押下する | L7: 自動入力新規登録画面に遷移すること | M7: 新規ボタンと共通なので項目は省略 | N7: 未 | O7: 未 | P7: 未 | Q7: 未 | R7: 未
B8: =ROW()-ROW($B$3) -> 5 | C8: 経費一覧 | D8: 検索条件 | E8: 会社全体 | K8: 左記の検索条件を設定して検索 | L8: 条件に基づいた検索結果が表示されること | N8: 未 | O8: 未 | P8: 未 | Q8: 未 | R8: 未
B9: =ROW()-ROW($B$3) -> 6 | C9: 経費一覧 | E9: 削除済み | G9: - | H9: - | K9: 同上 | L9: 同上 | N9: 未 | O9: 未 | P9: 未 | Q9: 未 | R9: 未
B10: =ROW()-ROW($B$3) -> 7 | C10: 経費一覧 | E10: 従業員 | G10: - | H10: - | K10: 同上 | L10: 同上 | N10: 未 | O10: 未 | P10: 未 | Q10: 未 | R10: 未
B11: =ROW()-ROW($B$3) -> 8 | C11: 経費一覧 | E11: 申請ID | G11: - | H11: - | K11: 同上 | L11: 同上 | N11: 未 | O11: 未 | P11: 未 | Q11: 未 | R11: 未
B12: =ROW()-ROW($B$3) -> 9 | C12: 経費一覧 | E12: 利用日 | F12: 〇〇から | G12: - | H12: - | K12: 同上 | L12: 同上 | N12: 未 | O12: 未 | P12: 未 | Q12: 未 | R12: 未
B13: =ROW()-ROW($B$3) -> 10 | C13: 経費一覧 | F13: 〇〇まで | G13: - | H13: - | K13: 同上 | L13: 同上 | N13: 未 | O13: 未 | P13: 未 | Q13: 未 | R13: 未
B14: =ROW()-ROW($B$3) -> 11 | C14: 経費一覧 | F14: 空白検索 | G14: - | H14: - | K14: 同上 | L14: 同上 | N14: 未 | O14: 未 | P14: 未 | Q14: 未 | R14: 未
B15: =ROW()-ROW($B$3) -> 12 | C15: 経費一覧 | E15: 支払先 | G15: - | H15: - | K15: 同上 | L15: 同上 | N15: 未 | O15: 未 | P15: 未 | Q15: 未 | R15: 未
B16: =ROW()-ROW($B$3) -> 13 | C16: 経費一覧 | F16: 空白検索 | G16: - | H16: - | K16: 同上 | L16: 同上 | N16: 未 | O16: 未 | P16: 未 | Q16: 未 | R16: 未
B17: =ROW()-ROW($B$3) -> 14 | C17: 経費一覧 | E17: 金額 | F17: 〇〇から | G17: - | H17: - | K17: 同上 | L17: 同上 | N17: 未 | O17: 未 | P17: 未 | Q17: 未 | R17: 未
B18: =ROW()-ROW($B$3) -> 15 | C18: 経費一覧 | F18: 〇〇まで | G18: - | H18: - | K18: 同上 | L18: 同上 | N18: 未 | O18: 未 | P18: 未 | Q18: 未 | R18: 未
B19: =ROW()-ROW($B$3) -> 16 | C19: 経費一覧 | F19: 空白検索 | G19: - | H19: - | K19: 同上 | L19: 同上 | N19: 未 | O19: 未 | P19: 未 | Q19: 未 | R19: 未
B20: =ROW()-ROW($B$3) -> 17 | C20: 経費一覧 | E20: 経費科目 | G20: - | H20: - | K20: 同上 | L20: 同上 | N20: 未 | O20: 未 | P20: 未 | Q20: 未 | R20: 未
B21: =ROW()-ROW($B$3) -> 18 | C21: 経費一覧 | E21: 所属部署 | G21: - | H21: - | K21: 同上 | L21: 同上 | N21: 未 | O21: 未 | P21: 未 | Q21: 未 | R21: 未
B22: =ROW()-ROW($B$3) -> 19 | C22: 経費一覧 | F22: 下位部署を含む | G22: - | H22: - | K22: 同上 | L22: 同上 | N22: 未 | O22: 未 | P22: 未 | Q22: 未 | R22: 未
B23: =ROW()-ROW($B$3) -> 20 | C23: 経費一覧 | E23: 精算区分 | F23: 精算対象 | G23: - | H23: - | K23: 同上 | L23: 同上 | N23: 未 | O23: 未 | P23: 未 | Q23: 未 | R23: 未
B24: =ROW()-ROW($B$3) -> 21 | C24: 経費一覧 | F24: 精算対象外 | G24: - | H24: - | K24: 同上 | L24: 同上 | N24: 未 | O24: 未 | P24: 未 | Q24: 未 | R24: 未
B25: =ROW()-ROW($B$3) -> 22 | C25: 経費一覧 | E25: コーポレートカード利用 | F25: あり | G25: - | H25: - | K25: 同上 | L25: 同上 | N25: 未 | O25: 未 | P25: 未 | Q25: 未 | R25: 未
B26: =ROW()-ROW($B$3) -> 23 | C26: 経費一覧 | F26: なし | G26: - | H26: - | K26: 同上 | L26: 同上 | N26: 未 | O26: 未 | P26: 未 | Q26: 未 | R26: 未
B27: =ROW()-ROW($B$3) -> 24 | C27: 経費一覧 | E27: 原本確認 | F27: 確認済み | K27: 同上 | L27: 同上 | N27: 未 | O27: 未 | P27: 未 | Q27: 未 | R27: 未
B28: =ROW()-ROW($B$3) -> 25 | C28: 経費一覧 | F28: 確認済みステータス更新 | K28: 同上 | L28: 同上 | N28: 未 | O28: 未 | P28: 未 | Q28: 未 | R28: 未
B29: =ROW()-ROW($B$3) -> 26 | C29: 経費一覧 | F29: 未確認 | K29: 同上 | L29: 同上 | N29: 未 | O29: 未 | P29: 未 | Q29: 未 | R29: 未
B30: =ROW()-ROW($B$3) -> 27 | C30: 経費一覧 | F30: 不要 | K30: 同上 | L30: 同上 | N30: 未 | O30: 未 | P30: 未 | Q30: 未 | R30: 未
B31: =ROW()-ROW($B$3) -> 28 | C31: 経費一覧 | E31: 出力ID | G31: - | H31: - | K31: 同上 | L31: 同上 | M31: 適当なIDで検索して検索結果が出なければOK | N31: 未 | O31: 未 | P31: 未 | Q31: 未 | R31: 未
B32: =ROW()-ROW($B$3) -> 29 | C32: 経費一覧 | E32: 電子領収書区分 | F32: 電子領収書 | G32: - | H32: - | K32: 同上 | L32: 同上 | N32: 未 | O32: 未 | P32: 未 | Q32: 未 | R32: 未
B33: =ROW()-ROW($B$3) -> 30 | C33: 経費一覧 | F33: 電子領収書以外 | K33: 同上 | L33: 同上 | N33: 未 | O33: 未 | P33: 未 | Q33: 未 | R33: 未
B34: =ROW()-ROW($B$3) -> 31 | C34: 経費一覧 | E34: 汎用マスタ | F34: コード | G34: - | H34: - | K34: 同上 | L34: 同上 | N34: 未 | O34: 未 | P34: 未 | Q34: 未 | R34: 未
B35: =ROW()-ROW($B$3) -> 32 | C35: 経費一覧 | F35: 名称 | K35: 同上 | L35: 同上 | N35: 未 | O35: 未 | P35: 未 | Q35: 未 | R35: 未
B36: =ROW()-ROW($B$3) -> 33 | C36: 経費一覧 | E36: 登録番号 | G36: - | H36: - | K36: 同上 | L36: 同上 | N36: 未 | O36: 未 | P36: 未 | Q36: 未 | R36: 未
B37: =ROW()-ROW($B$3) -> 34 | C37: 経費一覧 | F37: 空白検索 | G37: - | H37: - | K37: 同上 | L37: 同上 | N37: 未 | O37: 未 | P37: 未 | Q37: 未 | R37: 未
B38: =ROW()-ROW($B$3) -> 35 | C38: 経費一覧 | E38: 適格請求書の取り扱い | F38: あり | G38: - | H38: - | K38: 同上 | L38: 同上 | N38: 未 | O38: 未 | P38: 未 | Q38: 未 | R38: 未
B39: =ROW()-ROW($B$3) -> 36 | C39: 経費一覧 | F39: なし | G39: - | H39: - | K39: 同上 | L39: 同上 | N39: 未 | O39: 未 | P39: 未 | Q39: 未 | R39: 未
B40: =ROW()-ROW($B$3) -> 37 | C40: 経費一覧 | E40: ステータス | F40: 未申請 | G40: - | H40: - | K40: 同上 | L40: 同上 | N40: 未 | O40: 未 | P40: 未 | Q40: 未 | R40: 未
B41: =ROW()-ROW($B$3) -> 38 | C41: 経費一覧 | F41: 下書き保存中の申請を含める | G41: - | H41: - | K41: 同上 | L41: 同上 | N41: 未 | O41: 未 | P41: 未 | Q41: 未 | R41: 未
B42: =ROW()-ROW($B$3) -> 39 | C42: 経費一覧 | F42: データ化中 | G42: - | H42: - | K42: 同上 | L42: 同上 | N42: 未 | O42: 未 | P42: 未 | Q42: 未 | R42: 未
B43: =ROW()-ROW($B$3) -> 40 | C43: 経費一覧 | F43: データ化失敗 | G43: - | H43: - | K43: 同上 | L43: 同上 | N43: 未 | O43: 未 | P43: 未 | Q43: 未 | R43: 未
B44: =ROW()-ROW($B$3) -> 41 | C44: 経費一覧 | F44: 承認待ち | G44: - | H44: - | K44: 同上 | L44: 同上 | N44: 未 | O44: 未 | P44: 未 | Q44: 未 | R44: 未
B45: =ROW()-ROW($B$3) -> 42 | C45: 経費一覧 | F45: 承認済み | G45: - | H45: - | K45: 同上 | L45: 同上 | N45: 未 | O45: 未 | P45: 未 | Q45: 未 | R45: 未
B46: =ROW()-ROW($B$3) -> 43 | C46: 経費一覧 | E46: 検索条件をリセット | K46: 検索条件をリセットを押下 | L46: 検索条件がリセットされること | N46: 未 | O46: 未 | P46: 未 | Q46: 未 | R46: 未
B47: =ROW()-ROW($B$3) -> 44 | C47: 経費一覧 | E47: この条件で検索 | K47: 任意の検索条件を設定してこの条件で検索を押下 | L47: 条件に基づいた検索結果が表示されること | N47: 未 | O47: 未 | P47: 未 | Q47: 未 | R47: 未
B48: =ROW()-ROW($B$3) -> 45 | C48: 経費一覧 | D48: 申請 | E48: 申請する | K48: 任意の経費を選択する 申請>申請するを押下する 承認フローを通して申請を送る | L48: 申請が送れること | N48: 未 | O48: 未 | P48: 未 | Q48: 未 | R48: 未
B49: =ROW()-ROW($B$3) -> 46 | C49: 経費一覧 | E49: 申請書を下書き保存する | K49: 任意の経費を選択する 申請>申請を下書き保存するを押下 | L49: 未申請の申請が作成されること 未申請の申請詳細画面に遷移すること | N49: 未 | O49: 未 | P49: 未 | Q49: 未 | R49: 未
B50: =ROW()-ROW($B$3) -> 47 | C50: 経費一覧 | D50: タイムスタンプ検証 | K50: タイムスタンプ検証を押下 検証を開始する 検証結果をダウンロードする | L50: 一連の動作がエラーなく動作すること タイムスタンプ検証結果の列が追加されること ファイル内容が経費と一致していること | M50: タイムスタンプ検証モーダル | N50: 未 | O50: 未 | P50: 未 | Q50: 未 | R50: 未
B51: =ROW()-ROW($B$3) -> 48 | C51: 経費一覧 | D51: 表示項目設定 | E51: 表示 | K51: 表示項目設定を押下 任意の表示項目を設定する 保存を行う | L51: 設定した表示項目が経費一覧に表示されていること | M51: 表示項目の設定モーダル | N51: 未 | O51: 未 | P51: 未 | Q51: 未 | R51: 未
B52: =ROW()-ROW($B$3) -> 49 | E52: 非表示 | K52: 表示項目設定を押下 任意の表示項目を非表示に設定する 保存を行う | L52: 設定した表示項目が経費一覧に表示されないこと
B53: =ROW()-ROW($B$3) -> 50 | E53: 並び替え | K53: 表示項目設定を押下 任意の表示項目の順番を入れ替える 保存を行う | L53: 設定した表示項目が設定した順番で経費一覧に表示されていること
B54: =ROW()-ROW($B$3) -> 51 | E54: 汎用マスタ | K54: 汎用マスタを新規に設定する 任意の表示項目を設定する 保存を行う | L54: 設定した汎用マスタが経費一覧に表示されていること
B55: =ROW()-ROW($B$3) -> 52 | E55: 初期設定に戻す | K55: 表示項目設定を押下 初期設定に戻すボタンを押下する | L55: 初期設定に戻ること
B56: =ROW()-ROW($B$3) -> 53 | C56: 経費一覧 | D56: ソート | E56: 利用日 | K56: 左記の表示項目を設定する 表示項目横の▲▼アイコンを押下する | L56: 昇順降順が切り替わること 設定に応じて表示順が変わること | N56: 未 | O56: 未 | P56: 未 | Q56: 未 | R56: 未
B57: =ROW()-ROW($B$3) -> 54 | C57: 経費一覧 | E57: 支払先/訪問先 | K57: 同上 | L57: 同上 | N57: 未 | O57: 未 | P57: 未 | Q57: 未 | R57: 未
B58: =ROW()-ROW($B$3) -> 55 | C58: 経費一覧 | E58: 金額 | K58: 同上 | L58: 同上 | N58: 未 | O58: 未 | P58: 未 | Q58: 未 | R58: 未
B59: =ROW()-ROW($B$3) -> 56 | C59: 経費一覧 | E59: 経費科目 | K59: 同上 | L59: 同上 | N59: 未 | O59: 未 | P59: 未 | Q59: 未 | R59: 未
B60: =ROW()-ROW($B$3) -> 57 | C60: 経費一覧 | E60: 所属部署 | K60: 同上 | L60: 同上 | N60: 未 | O60: 未 | P60: 未 | Q60: 未 | R60: 未
B61: =ROW()-ROW($B$3) -> 58 | C61: 経費一覧 | E61: 経費申請書名 | K61: 同上 | L61: 同上 | N61: 未 | O61: 未 | P61: 未 | Q61: 未 | R61: 未
B62: =ROW()-ROW($B$3) -> 59 | C62: 経費一覧 | E62: ステータス | K62: 同上 | L62: 同上 | N62: 未 | O62: 未 | P62: 未 | Q62: 未 | R62: 未
B63: =ROW()-ROW($B$3) -> 60 | C63: 経費一覧 | E63: 登録日 | K63: 同上 | L63: 同上 | N63: 未 | O63: 未 | P63: 未 | Q63: 未 | R63: 未
B64: =ROW()-ROW($B$3) -> 61 | C64: 経費一覧 | E64: プロジェクト | K64: 同上 | L64: 同上 | N64: 未 | O64: 未 | P64: 未 | Q64: 未 | R64: 未
B65: =ROW()-ROW($B$3) -> 62 | C65: 経費一覧 | D65: 表示件数 | K65: 表示件数を押下する 任意の件数に変更する | L65: 表示件数が切り替わること | N65: 未 | O65: 未 | P65: 未 | Q65: 未 | R65: 未
B66: =ROW()-ROW($B$3) -> 63 | C66: 経費一覧 | D66: ページネーション | E66: ページ指定 | K66: 任意のページを押下する | L66: 指定したページに移動すること | N66: 未 | O66: 未 | P66: 未 | Q66: 未 | R66: 未
B67: =ROW()-ROW($B$3) -> 64 | C67: 経費一覧 | E67: > | K67: >を押下する | L67: 指定したページに移動すること | N67: 未 | O67: 未 | P67: 未 | Q67: 未 | R67: 未
B68: =ROW()-ROW($B$3) -> 65 | C68: 経費一覧 | E68: >> | K68: >>を押下する | L68: 最後尾のページに移動すること | N68: 未 | O68: 未 | P68: 未 | Q68: 未 | R68: 未
B69: =ROW()-ROW($B$3) -> 66 | C69: 経費一覧 | E69: < | K69: <を押下する | L69: 指定したページに移動すること | N69: 未 | O69: 未 | P69: 未 | Q69: 未 | R69: 未
B70: =ROW()-ROW($B$3) -> 67 | C70: 経費一覧 | E70: << | K70: <<を押下する | L70: 先頭のページに移動すること | N70: 未 | O70: 未 | P70: 未 | Q70: 未 | R70: 未
B71: =ROW()-ROW($B$3) -> 68 | C71: 経費一覧 | D71: 経費一覧の表示項目 | E71: アラート | F71: タイムスタンプ | K71: 左記の表示項目を設定する タイムスタンプが押された経費の表示項目を確認する アイコンをマウスオーバーする | L71: タイムスタンプのアイコンが表示されること マウスオーバーすると設定に応じて以下が表示されること 「表面/裏面,ver.日付.日時」 | N71: 未 | O71: 未 | P71: 未 | Q71: 未 | R71: 未
B72: =ROW()-ROW($B$3) -> 69 | C72: 経費一覧 | F72: 警告アラート | K72: 左記の表示項目を設定する 警告アラートの条件を満たした経費の表示項目を確認する アイコンをマウスオーバーする | L72: 警告アラートのアイコンが表示されること マウスオーバーすると警告の内容が表示されること | N72: 未 | O72: 未 | P72: 未 | Q72: 未 | R72: 未
B73: =ROW()-ROW($B$3) -> 70 | C73: 経費一覧 | F73: 申請不可アラート | K73: 左記の表示項目を設定する 申請不可アラートの条件を満たした経費の表示項目を確認する アイコンをマウスオーバーする | L73: 申請不可アラートのアイコンが表示されること マウスオーバーすると申請不可である理由が表示されること | N73: 未 | O73: 未 | P73: 未 | Q73: 未 | R73: 未
B74: =ROW()-ROW($B$3) -> 71 | C74: 経費一覧 | F74: なし | K74: 左記の表示項目を設定する アラートの条件を満たさない経費を設定して確認する | L74: アラートアイコンが何も表示されていないこと | N74: 未 | O74: 未 | P74: 未 | Q74: 未 | R74: 未
B75: =ROW()-ROW($B$3) -> 72 | C75: 経費一覧 | E75: 利用日 | F75: 任意の日付 | K75: 左記の表示項目を設定する 経費に任意の日付を設定する 経費一覧の表示項目を確認する | L75: 任意の日付が表示されること | N75: 未 | O75: 未 | P75: 未 | Q75: 未 | R75: 未
B76: =ROW()-ROW($B$3) -> 73 | C76: 経費一覧 | F76: 未入力 | K76: 左記の表示項目を設定する 経費に日付を設定しない 経費一覧の表示項目を確認する | L76: [未入力]が表示されること | N76: 未 | O76: 未 | P76: 未 | Q76: 未 | R76: 未
B77: =ROW()-ROW($B$3) -> 74 | C77: 経費一覧 | E77: ラベル | F77: サムネイル画像 | K77: 左記の表示項目を設定する 左記の条件を満たす経費を作成する 経費一覧の表示項目を確認する アイコンをマウスオーバーする | L77: 該当のアイコンが表示されること マウスオーバーすると経費に設定した領収書画像のサムネイル画像が表示されること | N77: 未 | O77: 未 | P77: 未 | Q77: 未 | R77: 未
B78: =ROW()-ROW($B$3) -> 75 | C78: 経費一覧 | F78: 自動入力された経費 | K78: 同上 | L78: 該当のアイコンが表示されること マウスオーバーした時内容がわかる文言が表示されること | N78: 未 | O78: 未 | P78: 未 | Q78: 未 | R78: 未
B79: =ROW()-ROW($B$3) -> 76 | C79: 経費一覧 | F79: 外貨を利用した経費 | K79: 同上 | L79: 同上 | N79: 未 | O79: 未 | P79: 未 | Q79: 未 | R79: 未
B80: =ROW()-ROW($B$3) -> 77 | C80: 経費一覧 | F80: 電子領収書 | K80: 同上 | L80: 同上 | N80: 未 | O80: 未 | P80: 未 | Q80: 未 | R80: 未
B81: =ROW()-ROW($B$3) -> 78 | C81: 経費一覧 | F81: 精算対象外 | K81: 同上 | L81: 同上 | N81: 未 | O81: 未 | P81: 未 | Q81: 未 | R81: 未
B82: =ROW()-ROW($B$3) -> 79 | C82: 経費一覧 | F82: カード連携 | K82: 同上 | L82: 同上 | N82: 未 | O82: 未 | P82: 未 | Q82: 未 | R82: 未
B83: =ROW()-ROW($B$3) -> 80 | C83: 経費一覧 | F83: 参加者 | K83: 同上 | L83: 同上 | N83: 未 | O83: 未 | P83: 未 | Q83: 未 | R83: 未
B84: =ROW()-ROW($B$3) -> 81 | C84: 経費一覧 | F84: メモ | K84: 同上 | L84: 同上 | N84: 未 | O84: 未 | P84: 未 | Q84: 未 | R84: 未
B85: =ROW()-ROW($B$3) -> 82 | C85: 経費一覧 | F85: タイムスタンプ付与失敗 | K85: 領収書画像でタイムスタンプの付与に失敗した経費を用意する 経費一覧の表示項目を確認する アイコンをマウスオーバーする | L85: 同上 | N85: 未 | O85: 未 | P85: 未 | Q85: 未 | R85: 未
B86: =ROW()-ROW($B$3) -> 83 | C86: 経費一覧 | E86: 電子領収書 | F86: チェック | K86: 左記の表示項目を設定する 経費に左記の設定を行う 経費一覧で該当の経費の表示項目を確認する | L86: 左記の表示項目が一覧に表示されること | N86: 未 | O86: 未 | P86: 未 | Q86: 未 | R86: 未
B87: =ROW()-ROW($B$3) -> 84 | C87: 経費一覧 | F87: 未設定 | K87: 同上 | L87: 左記の表示項目が空欄で経費一覧に表示されれること | N87: 未 | O87: 未 | P87: 未 | Q87: 未 | R87: 未
B88: =ROW()-ROW($B$3) -> 85 | C88: 経費一覧 | E88: 支払先/訪問先 | F88: 任意の設定 | K88: 同上 | L88: 左記の表示項目が一覧に表示されること | N88: 未 | O88: 未 | P88: 未 | Q88: 未 | R88: 未
B89: =ROW()-ROW($B$3) -> 86 | C89: 経費一覧 | F89: 未設定 | K89: 同上 | L89: 左記の表示項目が空欄で経費一覧に表示されれること
B90: =ROW()-ROW($B$3) -> 87 | C90: 経費一覧 | E90: 金額 | F90: 任意の設定 | K90: 同上 | L90: 左記の表示項目が一覧に表示されること | N90: 未 | O90: 未 | P90: 未 | Q90: 未 | R90: 未
B91: =ROW()-ROW($B$3) -> 88 | C91: 経費一覧 | F91: 未設定 | K91: 同上 | L91: 左記の表示項目が空欄で経費一覧に表示されれること
B92: =ROW()-ROW($B$3) -> 89 | C92: 経費一覧 | E92: 経費科目 | F92: 任意の設定 | K92: 同上 | L92: 左記の表示項目が一覧に表示されること | N92: 未 | O92: 未 | P92: 未 | Q92: 未 | R92: 未
B93: =ROW()-ROW($B$3) -> 90 | C93: 経費一覧 | F93: 未設定 | K93: 同上 | L93: 左記の表示項目が空欄で経費一覧に表示されれること
B94: =ROW()-ROW($B$3) -> 91 | C94: 経費一覧 | E94: 税区分 | F94: 任意の設定 | K94: 同上 | L94: 左記の表示項目が一覧に表示されること | N94: 未 | O94: 未 | P94: 未 | Q94: 未 | R94: 未
B95: =ROW()-ROW($B$3) -> 92 | C95: 経費一覧 | F95: 未設定 | K95: 同上 | L95: 左記の表示項目が空欄で経費一覧に表示されれること
B96: =ROW()-ROW($B$3) -> 93 | C96: 経費一覧 | E96: 所属部署 | F96: 任意の設定 | K96: 同上 | L96: 左記の表示項目が一覧に表示されること | N96: 未 | O96: 未 | P96: 未 | Q96: 未 | R96: 未
B97: =ROW()-ROW($B$3) -> 94 | C97: 経費一覧 | F97: 未設定 | K97: 同上 | L97: 左記の表示項目が空欄で経費一覧に表示されれること
B98: =ROW()-ROW($B$3) -> 95 | C98: 経費一覧 | E98: 費用負担部署 | F98: 任意の設定 | K98: 同上 | L98: 左記の表示項目が一覧に表示されること | N98: 未 | O98: 未 | P98: 未 | Q98: 未 | R98: 未
B99: =ROW()-ROW($B$3) -> 96 | C99: 経費一覧 | F99: 未設定 | K99: 同上 | L99: 左記の表示項目が空欄で経費一覧に表示されれること
B100: =ROW()-ROW($B$3) -> 97 | C100: 経費一覧 | E100: 経費申請書名 | F100: 任意の設定 | K100: 同上 | L100: 左記の表示項目が一覧に表示されること | N100: 未 | O100: 未 | P100: 未 | Q100: 未 | R100: 未
B101: =ROW()-ROW($B$3) -> 98 | C101: 経費一覧 | F101: 未設定 | K101: 同上 | L101: 左記の表示項目が空欄で経費一覧に表示されれること
...

Sheet 新規ボタン
C2: ↓「+新規」ボタン の導線を確認 | M2: Win11/ Chrome | N2: Win11/ Edge | O2: Win11/ Firefox | P2: Win11/ Safari
B3: No | C3: 画面 | D3: 確認対象 | E3: 詳細 | J3: テスト実行手順 | K3: 期待値 | L3: 備考 | M3: TK+TI+TD | N3: TK+TI+TD | O3: TI+TD | P3: TK単体 | Q3: 実行者 | R3: 実行備考 | S3: 起票JIRA No
B4: =ROW()-ROW($B$3) -> 1 | C4: 経費精算 | D4: 経費を選択して申請する | E4: 今月分を選択する | K4: 今月分のデータのみ✅がつく | M4: OK | N4: - | O4: - | P4: - | Q4: 中里
B5: =ROW()-ROW($B$3) -> 2 | E5: 先月分を選択する | K5: 先月分のデータのみ✅がつく | M5: OK | N5: - | O5: - | P5: - | Q5: 中里
B6: =ROW()-ROW($B$3) -> 3 | E6: プロジェクトから選択する | K6: 選んだプロジェクトのデータのみ✅がつく | M6: OK | N6: - | O6: - | P6: - | Q6: 中里
B7: =ROW()-ROW($B$3) -> 4 | E7: 請求書先から選択 | F7: 自分(精算対象) | K7: 精算対象のデータに✅がつくこと | M7: OK | N7: - | O7: - | P7: - | Q7: 中里
B8: =ROW()-ROW($B$3) -> 5 | F8: 法人 | K8: 精算対象外のデータに✅がつく | M8: OK | N8: - | O8: - | P8: - | Q8: 中里
B9: =ROW()-ROW($B$3) -> 6 | E9: 選択した経費を編集するボタン | F9: チェックなし | K9: ボタンが非活性 | M9: OK | N9: - | O9: - | P9: - | Q9: 中里
B10: =ROW()-ROW($B$3) -> 7 | F10: チェックあり | K10: ・ボタンが活性 ・一括編集できること | M10: OK | N10: - | O10: - | P10: - | Q10: 中里
B11: =ROW()-ROW($B$3) -> 8 | E11: ソート | F11: 利用日 | J11: 左記の表示項目を設定する 表示項目横の▲▼アイコンを押下する | K11: 昇順降順が切り替わること 設定に応じて表示順が変わること | M11: OK | N11: - | O11: - | P11: - | Q11: 中里
B12: =ROW()-ROW($B$3) -> 9 | F12: 支払先/訪問先 | J12: 同上 | K12: 同上 | M12: OK | N12: - | O12: - | P12: - | Q12: 中里
B13: =ROW()-ROW($B$3) -> 10 | F13: 金額 | J13: 同上 | K13: 同上 | M13: OK | N13: - | O13: - | P13: - | Q13: 中里
B14: =ROW()-ROW($B$3) -> 11 | F14: 経費科目 | J14: 同上 | K14: 同上 | M14: OK | N14: - | O14: - | P14: - | Q14: 中里
B15: =ROW()-ROW($B$3) -> 12 | F15: 所属部署 | J15: 同上 | K15: 同上 | M15: OK | N15: - | O15: - | P15: - | Q15: 中里
B16: =ROW()-ROW($B$3) -> 13 | F16: 経費申請書名 | J16: 同上 | K16: 同上 | M16: OK | N16: - | O16: - | P16: - | Q16: 中里
B17: =ROW()-ROW($B$3) -> 14 | F17: ステータス | J17: 同上 | K17: 同上 | M17: OK | N17: - | O17: - | P17: - | Q17: 中里
B18: =ROW()-ROW($B$3) -> 15 | F18: 登録日 | J18: 同上 | K18: 同上 | M18: OK | N18: - | O18: - | P18: - | Q18: 中里
B19: =ROW()-ROW($B$3) -> 16 | F19: プロジェクト | J19: 同上 | K19: 同上 | M19: OK | N19: - | O19: - | P19: - | Q19: 中里
B20: =ROW()-ROW($B$3) -> 17 | E20: 経費一覧を押下 | K20: 経費詳細が開かれること | M20: OK | N20: - | O20: - | P20: - | Q20: 中里
B21: =ROW()-ROW($B$3) -> 18 | E21: 経費一覧の表示項目 | F21: アラート | G21: タイムスタンプ | J21: 左記の表示項目を設定する タイムスタンプが押された経費の表示項目を確認する アイコンをマウスオーバーする | K21: タイムスタンプのアイコンが表示されること マウスオーバーすると設定に応じて以下が表示されること 「表面/裏面,ver.日付.日時」 | M21: OK | N21: - | O21: - | P21: - | Q21: 北川 | R21: dev-tdではタイムスタンプ確認不可
B22: =ROW()-ROW($B$3) -> 19 | G22: 警告アラート | J22: 左記の表示項目を設定する 警告アラートの条件を満たした経費の表示項目を確認する アイコンをマウスオーバーする | K22: 警告アラートのアイコンが表示されること マウスオーバーすると警告の内容が表示されること | M22: OK | N22: - | O22: - | P22: - | Q22: 中里
B23: =ROW()-ROW($B$3) -> 20 | G23: 申請不可アラート | J23: 左記の表示項目を設定する 申請不可アラートの条件を満たした経費の表示項目を確認する アイコンをマウスオーバーする | K23: 申請不可アラートのアイコンが表示されること マウスオーバーすると申請不可である理由が表示されること | M23: OK | N23: - | O23: - | P23: - | Q23: 中里
B24: =ROW()-ROW($B$3) -> 21 | G24: なし | J24: 左記の表示項目を設定する アラートの条件を満たさない経費を設定して確認する | K24: アラートアイコンが何も表示されていないこと | M24: OK | N24: - | O24: - | P24: - | Q24: 中里
B25: =ROW()-ROW($B$3) -> 22 | F25: 利用日 | G25: 任意の日付 | J25: 左記の表示項目を設定する 経費に任意の日付を設定する 経費一覧の表示項目を確認する | K25: 任意の日付が表示されること | M25: OK | N25: - | O25: - | P25: - | Q25: 中里
B26: =ROW()-ROW($B$3) -> 23 | F26: ラベル | G26: サムネイル画像 | J26: 左記の表示項目を設定する 左記の条件を満たす経費を作成する 経費一覧の表示項目を確認する アイコンをマウスオーバーする | K26: 該当のアイコンが表示されること マウスオーバーすると経費に設定した領収書画像のサムネイル画像が表示されること | M26: OK | N26: - | O26: - | P26: - | Q26: 中里
B27: =ROW()-ROW($B$3) -> 24 | G27: 自動入力された経費 | J27: 同上 | K27: 該当のアイコンが表示されること マウスオーバーした時内容がわかる文言が表示されること | M27: OK | N27: - | O27: - | P27: - | Q27: 北川
B28: =ROW()-ROW($B$3) -> 25 | G28: 外貨を利用した経費 | J28: 同上 | K28: 同上 | M28: OK | N28: - | O28: - | P28: - | Q28: 中里
B29: =ROW()-ROW($B$3) -> 26 | G29: 電子領収書 | J29: 同上 | K29: 同上 | M29: OK | N29: - | O29: - | P29: - | Q29: 中里
B30: =ROW()-ROW($B$3) -> 27 | G30: 精算対象外 | J30: 同上 | K30: 同上 | M30: OK | N30: - | O30: - | P30: - | Q30: 中里
B31: =ROW()-ROW($B$3) -> 28 | G31: カード連携 | J31: 同上 | K31: 同上 | M31: OK | N31: - | O31: - | P31: - | Q31: 北川 | R31: dev-tdでカード明細が実施不可 「関連するカード連携のデータが存在します」
B32: =ROW()-ROW($B$3) -> 29 | G32: 参加者 | J32: 同上 | K32: 同上 | M32: OK | N32: - | O32: - | P32: - | Q32: 中里
B33: =ROW()-ROW($B$3) -> 30 | G33: メモ | J33: 同上 | K33: 同上 | M33: OK | N33: - | O33: - | P33: - | Q33: 中里
B34: =ROW()-ROW($B$3) -> 31 | G34: タイムスタンプ付与失敗 | J34: 領収書画像でタイムスタンプの付与に失敗した経費を用意する 経費一覧の表示項目を確認する アイコンをマウスオーバーする | K34: 同上 | L34: Pass付PDFをアップロードする | M34: OK | N34: - | O34: - | P34: - | Q34: 北川 | R34: dev-tdではタイムスタンプ確認不可 「領収書画像へのタイムスタンプ付与に失敗しました。お手数ですがもう一度アップロードしてください」
B35: =ROW()-ROW($B$3) -> 32 | F35: 電子領収書 | G35: チェック | J35: 左記の表示項目を設定する 経費に左記の設定を行う 経費一覧で該当の経費の表示項目を確認する | K35: 左記の表示項目が一覧に表示されること | M35: OK | N35: - | O35: - | P35: - | Q35: 中里
B36: =ROW()-ROW($B$3) -> 33 | F36: 支払先/訪問先 | G36: 任意の設定 | J36: 同上 | K36: 同上 | M36: OK | N36: - | O36: - | P36: - | Q36: 中里
B37: =ROW()-ROW($B$3) -> 34 | F37: 金額 | G37: 任意の設定 | J37: 同上 | K37: 同上 | M37: OK | N37: - | O37: - | P37: - | Q37: 中里
B38: =ROW()-ROW($B$3) -> 35 | F38: 経費科目 | G38: 任意の設定 | J38: 同上 | K38: 同上 | M38: OK | N38: - | O38: - | P38: - | Q38: 中里
B39: =ROW()-ROW($B$3) -> 36 | F39: 税区分 | G39: 任意の設定 | J39: 同上 | K39: 同上 | M39: OK | N39: - | O39: - | P39: - | Q39: 中里
B40: =ROW()-ROW($B$3) -> 37 | F40: 所属部署 | G40: 任意の設定 | J40: 同上 | K40: 同上 | M40: OK | N40: - | O40: - | P40: - | Q40: 中里
B41: =ROW()-ROW($B$3) -> 38 | F41: 費用負担部署 | G41: 任意の設定 | J41: 同上 | K41: 同上 | M41: OK | N41: - | O41: - | P41: - | Q41: 中里
B42: =ROW()-ROW($B$3) -> 39 | F42: 経費申請書名 | G42: 任意の設定 | J42: 同上 | K42: 同上 | M42: OK | N42: - | O42: - | P42: - | Q42: 中里
B43: =ROW()-ROW($B$3) -> 40 | F43: ステータス | G43: 未申請 | J43: 同上 | K43: 同上 | M43: OK | N43: - | O43: - | P43: - | Q43: 中里
B44: =ROW()-ROW($B$3) -> 41 | G44: データ化中 | J44: 同上 | K44: 同上 | M44: OK | N44: - | O44: - | P44: - | Q44: 中里
B45: =ROW()-ROW($B$3) -> 42 | G45: データ化失敗 | J45: 同上 | K45: 同上 | M45: OK | N45: - | O45: - | P45: - | Q45: 中里
B46: =ROW()-ROW($B$3) -> 43 | G46: 承認待ち | J46: 同上 | K46: 同上 | M46: OK | N46: - | O46: - | P46: - | Q46: 中里
B47: =ROW()-ROW($B$3) -> 44 | G47: 承認済み | J47: 同上 | K47: 同上 | M47: OK | N47: - | O47: - | P47: - | Q47: 中里
B48: =ROW()-ROW($B$3) -> 45 | F48: 登録日 | J48: 同上 | K48: 同上 | M48: OK | N48: - | O48: - | P48: - | Q48: 中里
B49: =ROW()-ROW($B$3) -> 46 | F49: 登録番号 | G49: 任意の設定 | J49: 同上 | K49: 同上 | M49: OK | N49: - | O49: - | P49: - | Q49: 中里
B50: =ROW()-ROW($B$3) -> 47 | F50: 適格請求書 | G50: チェック | J50: 同上 | K50: 同上 | M50: OK | N50: - | O50: - | P50: - | Q50: 中里
B51: =ROW()-ROW($B$3) -> 48 | F51: 交通費支払先 | G51: 任意の設定 | J51: 同上 | K51: 同上 | M51: OK | N51: - | O51: - | P51: - | Q51: 中里
B52: =ROW()-ROW($B$3) -> 49 | F52: メモ | G52: 任意の設定 | J52: 同上 | K52: 同上 | M52: OK | N52: - | O52: - | P52: - | Q52: 中里
B53: =ROW()-ROW($B$3) -> 50 | F53: 参加者 | G53: 任意の設定 | J53: 同上 | K53: 同上 | M53: OK | N53: - | O53: - | P53: - | Q53: 中里
B54: =ROW()-ROW($B$3) -> 51 | F54: 訪問先 | G54: 任意の設定 | J54: 同上 | K54: 同上 | M54: OK | N54: - | O54: - | P54: - | Q54: 中里
B55: =ROW()-ROW($B$3) -> 52 | F55: 発着地 | G55: 任意の設定 | J55: 同上 | K55: 同上 | M55: OK | N55: - | O55: - | P55: - | Q55: 中里
B56: =ROW()-ROW($B$3) -> 53 | F56: 目的 | G56: 任意の設定 | J56: 同上 | K56: 同上 | M56: OK | N56: - | O56: - | P56: - | Q56: 中里
B57: =ROW()-ROW($B$3) -> 54 | F57: プロジェクト | G57: 任意の設定 | J57: 同上 | K57: 同上 | M57: OK | N57: - | O57: - | P57: - | Q57: 中里
B58: =ROW()-ROW($B$3) -> 55 | F58: 貸方勘定科目 | G58: 任意の設定 | J58: 同上 | K58: 同上 | M58: OK | N58: - | O58: - | P58: - | Q58: 中里
B59: =ROW()-ROW($B$3) -> 56 | F59: 経費申請ID | G59: 任意の設定 | J59: 同上 | K59: 同上 | M59: OK | N59: - | O59: - | P59: - | Q59: 中里
B60: =ROW()-ROW($B$3) -> 57 | F60: 汎用マスタ | G60: 任意の設定 | J60: 同上 | K60: 同上 | M60: OK | N60: - | O60: - | P60: - | Q60: 中里
B61: =ROW()-ROW($B$3) -> 58 | F61: 幅を変更する | J61: 任意の表示項目のヘッダーの境界をドラッグする | K61: 幅が変更できること | M61: OK | N61: - | O61: - | P61: - | Q61: 中里
B62: =ROW()-ROW($B$3) -> 59 | E62: 表示件数 | J62: 表示件数を押下する 任意の件数に変更する | K62: 表示件数が切り替わること | M62: OK | N62: - | O62: - | P62: - | Q62: 中里
B63: =ROW()-ROW($B$3) -> 60 | E63: ページネーション | F63: ページ指定 | K63: 任意のページを押下する | M63: OK | N63: - | O63: - | P63: - | Q63: 中里
B64: =ROW()-ROW($B$3) -> 61 | F64: > | K64: >を押下する | M64: OK | N64: - | O64: - | P64: - | Q64: 中里
B65: =ROW()-ROW($B$3) -> 62 | F65: >> | K65: >>を押下する | M65: OK | N65: - | O65: - | P65: - | Q65: 中里
B66: =ROW()-ROW($B$3) -> 63 | F66: < | K66: <を押下する | M66: OK | N66: - | O66: - | P66: - | Q66: 中里
B67: =ROW()-ROW($B$3) -> 64 | F67: << | K67: <<を押下する | M67: OK | N67: - | O67: - | P67: - | Q67: 中里
B68: =ROW()-ROW($B$3) -> 65 | E68: 選択した経費を申請するボタン | K68: 申請できること | M68: OK | N68: OK | O68: - | P68: OK | Q68: 中里
B69: =ROW()-ROW($B$3) -> 66 | E69: 下書き保存するボタン | K69: 下書き保存できること | M69: OK | N69: - | O69: - | P69: - | Q69: 中里
B70: =ROW()-ROW($B$3) -> 67 | E70: キャンセルボタン | K70: モーダルが閉じること | M70: OK | N70: - | O70: - | P70: - | Q70: 中里
B71: =ROW()-ROW($B$3) -> 68 | D71: 未精算の事前申請を選択して精算する | E71: 事前申請一覧の表示項目 | F71: 事前申請名 | K71: 表示されていること | M71: OK | N71: - | O71: - | P71: - | Q71: 中里
B72: =ROW()-ROW($B$3) -> 69 | F72: プロジェクト | K72: 表示されていること | M72: OK | N72: - | O72: - | P72: - | Q72: 中里
B73: =ROW()-ROW($B$3) -> 70 | F73: 所属部署 | K73: 表示されていること | M73: OK | N73: - | O73: - | P73: - | Q73: 中里
B74: =ROW()-ROW($B$3) -> 71 | F74: 事前申請額 | K74: 表示されていること | M74: OK | N74: - | O74: - | P74: - | Q74: 中里
B75: =ROW()-ROW($B$3) -> 72 | F75: 申請状況 | K75: 表示されていること | M75: OK | N75: - | O75: - | P75: - | Q75: 中里
B76: =ROW()-ROW($B$3) -> 73 | F76: 申請ID | K76: 表示されていること | M76: OK | N76: - | O76: - | P76: - | Q76: 中里
B77: =ROW()-ROW($B$3) -> 74 | C77: 事前申請 | J77: +新規 > 事前申請 を押下 | K77: 事前申請作成画面に遷移 | M77: OK | N77: - | O77: - | P77: - | Q77: 中里
B78: =ROW()-ROW($B$3) -> 75 | C78: 汎用申請 | J78: +新規 > その他の申請 > 事前申請 を押下 | K78: 汎用申請作成画面に遷移 | M78: OK | N78: - | O78: - | P78: - | Q78: 中里
B79: =ROW()-ROW($B$3) -> 76 | C79: 自動入力 | J79: +新規 > 自動入力 を押下 | K79: 自動入力作成画面に遷移 | M79: OK | N79: - | O79: - | P79: - | Q79: 中里
B80: =ROW()-ROW($B$3) -> 77 | C80: 経費を登録する 手入力 | D80: 利用日 | E80: 直接入力 | J80: 左記の導線で任意の利用日を入力して登録する →保存した後に経費を開いて確認する | K80: 問題なく登録できること 入力した設定が反映されていること | M80: - | N80: - | O80: - | P80: - | Q80: 中里
B81: =ROW()-ROW($B$3) -> 78 | C81: 手入力 | E81: カレンダーの選択 | J81: 同上 | K81: 同上 | M81: - | N81: - | O81: - | P81: - | Q81: 中里
B82: =ROW()-ROW($B$3) -> 79 | C82: 手入力 | E82: 今日 | J82: 同上 | K82: 同上 | M82: - | N82: - | O82: - | P82: - | Q82: 中里
B83: =ROW()-ROW($B$3) -> 80 | C83: 手入力 | E83: クリア | J83: 同上 | K83: 同上 | M83: - | N83: - | O83: - | P83: - | Q83: 中里
B84: =ROW()-ROW($B$3) -> 81 | C84: 手入力 | E84: 複数日選択 | J84: 同上 | K84: 同上 | M84: - | N84: - | O84: - | P84: - | Q84: 中里
B85: =ROW()-ROW($B$3) -> 82 | C85: 手入力 | D85: 金額 | E85: JPY | F85: プラス | J85: 金額欄に左記の数値を入力して経費を作成する | K85: 問題なく登録できること 設定が反映されていること | M85: - | N85: - | O85: - | P85: - | Q85: 中里
B86: =ROW()-ROW($B$3) -> 83 | C86: 手入力 | F86: マイナス | J86: 同上 | K86: 同上 | M86: - | N86: - | O86: - | P86: - | Q86: 中里
B87: =ROW()-ROW($B$3) -> 84 | C87: 手入力 | F87: ゼロ | J87: 同上 | K87: 同上 | M87: - | N87: - | O87: - | P87: - | Q87: 中里
B88: =ROW()-ROW($B$3) -> 85 | C88: 手入力 | F88: 小数点 | J88: 同上 | K88: 同上 | M88: - | N88: - | O88: - | P88: - | Q88: 中里
B89: =ROW()-ROW($B$3) -> 86 | C89: 手入力 | E89: 任意の外貨 | F89: プラス | J89: 同上 | K89: 同上 | M89: - | N89: - | O89: - | P89: - | Q89: 中里
B90: =ROW()-ROW($B$3) -> 87 | C90: 手入力 | F90: マイナス | J90: 同上 | K90: 同上 | M90: - | N90: - | O90: - | P90: - | Q90: 中里
B91: =ROW()-ROW($B$3) -> 88 | C91: 手入力 | F91: ゼロ | J91: 同上 | K91: 同上 | M91: - | N91: - | O91: - | P91: - | Q91: 中里
B92: =ROW()-ROW($B$3) -> 89 | C92: 手入力 | F92: 小数点 | J92: 同上 | K92: 同上 | M92: - | N92: - | O92: - | P92: - | Q92: 中里
B93: =ROW()-ROW($B$3) -> 90 | C93: 手入力 | D93: 支払先/訪問先 | E93: 任意の入力 | J93: 同上 | K93: 同上 | M93: - | N93: - | O93: - | P93: - | Q93: 中里
B94: =ROW()-ROW($B$3) -> 91 | C94: 手入力 | D94: 経費科目 | E94: 参加者 | F94: 設定:なし | J94: 参加者の設定がない経費科目を設定する 該当の経費科目を選択して経費を作成する | K94: 経費登録/編集画面に左記の設定が表示されないこと | M94: - | N94: - | O94: - | P94: - | Q94: 中里
B95: =ROW()-ROW($B$3) -> 92 | C95: 手入力 | F95: 設定:あり | G95: 氏名 | H95: 自社0人/取引先0人 | I95: 自社0人/取引先0人 | J95: 参加者の設定がある経費科目を設定する 「社員を追加:氏名」から左記の設定にして経費を作成する。 | K95: 問題なく登録できること 設定が反映されていること | L95: 自社の参加者を追加モーダルあり | M95: - | N95: - | O95: - | P95: - | Q95: 中里
B96: =ROW()-ROW($B$3) -> 93 | C96: 手入力 | H96: 自社1人/取引先1人 | I96: 自社1人/取引先1人 | J96: 同上 | K96: 同上 | L96: 自社の参加者を追加モーダルあり | M96: - | N96: - | O96: - | P96: - | Q96: 中里
B97: =ROW()-ROW($B$3) -> 94 | C97: 手入力 | G97: 人数 | H97: 自社0人/取引先0人 | I97: 自社0人/取引先0人 | J97: 参加者の設定がある経費科目を設定する 「社員を追加:人数」から左記の設定にして経費を作成する。 | K97: 同上 | M97: - | N97: - | O97: - | P97: - | Q97: 中里
B98: =ROW()-ROW($B$3) -> 95 | C98: 手入力 | H98: 自社1人/取引先1人 | I98: 自社1人/取引先1人 | J98: 同上 | K98: 同上 | M98: - | N98: - | O98: - | P98: - | Q98: 中里
B99: =ROW()-ROW($B$3) -> 96 | C99: 手入力 | E99: 出発地 | F99: 設定なし | J99: 出発地の設定がない経費科目を設定する 該当の経費科目を選択して経費を作成する | K99: 経費登録/編集画面に左記の設定が表示されないこと | M99: - | N99: - | O99: - | P99: - | Q99: 中里
B100: =ROW()-ROW($B$3) -> 97 | C100: 手入力 | F100: 設定あり | G100: 入力する | J100: 出発地の設定がある経費科目を設定する 出発地に任意の入力を行って経費を登録する | K100: 問題なく登録できること 設定が反映されていること | M100: - | N100: - | O100: - | P100: - | Q100: 中里
B101: =ROW()-ROW($B$3) -> 98 | C101: 手入力 | G101: 入力しない（スキップ） | J101: 出発地の設定がない経費科目を設定する 出発地に入力を行わず経費を登録する | K101: 同上 | M101: - | N101: - | O101: - | P101: - | Q101: 中里
...

Sheet 集計(経費)
N2: Win11/ Chrome | O2: Win11/ Edge | P2: Win11/ Firefox | Q2: MacOS/ Safari
B3: No | C3: 画面 | D3: 確認対象 | E3: 詳細 | K3: テスト実行手順 | L3: 期待値 | M3: 備考 | N3: TK+TI+TD | O3: TK+TI+TD | P3: TK単体 | Q3: TK単体 | R3: 実行者 | S3: 実行備考 | T3: 起票JIRA No
B4: =ROW()-ROW($B$3) -> 1 | C4: 集計画面(TK) | D4: 集計履歴 | E4: 経費申請タブ | K4: 集計一覧を開く 左記のタブを確認 左記のタブを押下 | L4: タブの横に表示件数が表示されること タブが切り替わること | N4: OK | O4: OK | P4: OK | Q4: OK | R4: 北川
B5: =ROW()-ROW($B$3) -> 2 | C5: 集計画面(TK) | E5: 事前申請タブ | K5: 同上 | L5: 同上 | N5: OK | O5: OK | P5: OK | Q5: OK | R5: 北川
B6: =ROW()-ROW($B$3) -> 3 | C6: 集計画面(TK) | E6: 旅費申請タブ | K6: 同上 | L6: 同上 | N6: OK | O6: OK | P6: OK | Q6: OK | R6: 北川
B7: =ROW()-ROW($B$3) -> 4 | C7: 集計画面(TK) | E7: 検索条件を設定 | K7: 検索条件を設定を押下して展開 任意の検索設定を設定する | L7: 任意の検索設定が設定できること | N7: OK | O7: OK | P7: OK | Q7: OK | R7: 北川
B8: =ROW()-ROW($B$3) -> 5 | C8: 集計画面(TK) | E8: 検索条件をリセット | K8: 検索条件をリセットを押下 | L8: 検索設定がリセットされること | N8: OK | O8: OK | P8: OK | Q8: OK | R8: 北川
B9: =ROW()-ROW($B$3) -> 6 | C9: 集計画面(TK) | E9: この条件で検索 | K9: 任意の設定で検索 | L9: 設定に基づいた検索結果が表示されること | N9: OK | O9: - | P9: - | Q9: - | R9: 本橋
B10: =ROW()-ROW($B$3) -> 7 | C10: 集計画面(TK) | F10: 作成日時～から | K10: 左記の設定を入力して検索 | L10: 同上 | N10: OK | O10: - | P10: - | Q10: - | R10: 本橋
B11: =ROW()-ROW($B$3) -> 8 | C11: 集計画面(TK) | F11: 作成日時～まで | K11: 同上 | L11: 同上 | N11: OK | O11: - | P11: - | Q11: - | R11: 本橋
B12: =ROW()-ROW($B$3) -> 9 | C12: 集計画面(TK) | F12: 総額～から | K12: 同上 | L12: 同上 | N12: OK | O12: - | P12: - | Q12: - | R12: 本橋
B13: =ROW()-ROW($B$3) -> 10 | C13: 集計画面(TK) | F13: 総額～まで | K13: 同上 | L13: 同上 | N13: OK | O13: - | P13: - | Q13: - | R13: 本橋
B14: =ROW()-ROW($B$3) -> 11 | C14: 集計画面(TK) | F14: 集計名 | K14: 同上 | L14: 同上 | N14: OK | O14: - | P14: - | Q14: - | R14: 本橋
B15: =ROW()-ROW($B$3) -> 12 | C15: 集計画面(TK) | F15: 支払ステータス:処理済み | K15: 同上 | L15: 同上 | N15: OK | O15: - | P15: - | Q15: - | R15: 本橋
B16: =ROW()-ROW($B$3) -> 13 | C16: 集計画面(TK) | F16: 支払ステータス:未払い | K16: 同上 | L16: 同上 | N16: OK | O16: - | P16: - | Q16: - | R16: 本橋
B17: =ROW()-ROW($B$3) -> 14 | C17: 集計画面(TK) | F17: 会計データ出力:出力済み | K17: 同上 | L17: 同上 | N17: OK | O17: - | P17: - | Q17: - | R17: 本橋
B18: =ROW()-ROW($B$3) -> 15 | C18: 集計画面(TK) | F18: 会計データ出力:未出力 | K18: 同上 | L18: 同上 | N18: OK | O18: - | P18: - | Q18: - | R18: 本橋
B19: =ROW()-ROW($B$3) -> 16 | C19: 集計画面(TK) | E19: ページネーション | F19: ページ指定 | K19: 任意のページを押下する | L19: 指定したページに移動すること | N19: OK | O19: - | P19: - | Q19: - | R19: 北川
B20: =ROW()-ROW($B$3) -> 17 | C20: 集計画面(TK) | F20: > | K20: >を押下する | L20: 指定したページに移動すること | N20: OK | O20: - | P20: - | Q20: - | R20: 北川
B21: =ROW()-ROW($B$3) -> 18 | C21: 集計画面(TK) | F21: >> | K21: >>を押下する | L21: 最後尾のページに移動すること | M21: 表示には51件以上の蓄積が必要 | N21: OK | O21: - | P21: - | Q21: - | R21: 北川
B22: =ROW()-ROW($B$3) -> 19 | C22: 集計画面(TK) | F22: < | K22: <を押下する | L22: 指定したページに移動すること | N22: OK | O22: - | P22: - | Q22: - | R22: 北川
B23: =ROW()-ROW($B$3) -> 20 | C23: 集計画面(TK) | F23: << | K23: <<を押下する | L23: 先頭のページに移動すること | M23: 表示には51件以上の蓄積が必要 | N23: OK | O23: - | P23: - | Q23: - | R23: 北川
B24: =ROW()-ROW($B$3) -> 21 | C24: 集計画面(TK) | E24: 表示件数 | K24: 表示件数を押下する 任意の件数に変更する | L24: 表示件数が切り替わること | N24: OK | O24: - | P24: - | Q24: - | R24: 北川
B25: =ROW()-ROW($B$3) -> 22 | C25: 集計画面(TK) | E25: ソート | F25: 経費申請 | G25: 作成日時 | K25: 左記の▲▼アイコンを押下 | L25: 昇順降順が切り替わり、設定した順序に並び変わること | N25: OK | O25: OK | P25: - | Q25: - | R25: 北川
B26: =ROW()-ROW($B$3) -> 23 | C26: 集計画面(TK) | G26: 集計名 | K26: 同上 | L26: 同上 | N26: OK | O26: OK | P26: - | Q26: - | R26: 北川
B27: =ROW()-ROW($B$3) -> 24 | C27: 集計画面(TK) | F27: 事前申請（仮払） | G27: 作成日時 | K27: 同上 | L27: 同上 | N27: OK | O27: OK | P27: - | Q27: - | R27: 北川
B28: =ROW()-ROW($B$3) -> 25 | C28: 集計画面(TK) | G28: 集計名 | K28: 同上 | L28: 同上 | N28: OK | O28: OK | P28: - | Q28: - | R28: 北川
B29: =ROW()-ROW($B$3) -> 26 | C29: 集計画面(TK) | F29: 旅費申請 | G29: 作成日時 | K29: 同上 | L29: 同上 | N29: OK | O29: OK | P29: - | Q29: - | R29: 北川
B30: =ROW()-ROW($B$3) -> 27 | C30: 集計画面(TK) | G30: 集計名 | K30: 同上 | L30: 同上 | N30: OK | O30: OK | P30: - | Q30: - | R30: 北川
B31: =ROW()-ROW($B$3) -> 28 | C31: 集計画面(TK) | E31: 表示項目 | F31: 経費申請 | G31: 作成日時 | K31: 左記の表示項目を確認する 任意の集計詳細を開き内容を確認する | L31: 左記の表示項目が表示されていること 項目の内容が正しいこと | N31: OK | O31: OK | P31: - | Q31: - | R31: 本橋
B32: =ROW()-ROW($B$3) -> 29 | C32: 集計画面(TK) | G32: 集計名 | K32: 同上 | L32: 同上 | N32: OK | O32: OK | P32: - | Q32: - | R32: 本橋
B33: =ROW()-ROW($B$3) -> 30 | C33: 集計画面(TK) | G33: 支払ステータス | K33: 同上 | L33: 同上 | N33: OK | O33: OK | P33: - | Q33: - | R33: 本橋
B34: =ROW()-ROW($B$3) -> 31 | C34: 集計画面(TK) | G34: 集計方法 | K34: 同上 | L34: 同上 | N34: OK | O34: OK | P34: - | Q34: - | R34: 本橋 | S34: 会計データ出力のオプションが必要
B35: =ROW()-ROW($B$3) -> 32 | C35: 集計画面(TK) | G35: 会計データ出力 | K35: 同上 | L35: 同上 | N35: OK | O35: OK | P35: - | Q35: - | R35: 本橋
B36: =ROW()-ROW($B$3) -> 33 | C36: 集計画面(TK) | G36: 経費数 | K36: 同上 | L36: 同上 | N36: OK | O36: OK | P36: - | Q36: - | R36: 本橋
B37: =ROW()-ROW($B$3) -> 34 | C37: 集計画面(TK) | G37: 総額 | K37: 同上 | L37: 同上 | N37: OK | O37: OK | P37: - | Q37: - | R37: 本橋
B38: =ROW()-ROW($B$3) -> 35 | C38: 集計画面(TK) | G38: 削除ボタン | K38: 削除ボタンを押下する | L38: 任意の集計が削除されること | N38: OK | O38: OK | P38: - | Q38: - | R38: 本橋
B39: =ROW()-ROW($B$3) -> 36 | C39: 集計画面(TK) | F39: 事前申請（仮払） | G39: 作成日時 | K39: 左記の表示項目を確認する 任意の集計詳細を開き内容を確認する | L39: 左記の表示項目が表示されていること 項目の内容が正しいこと | N39: OK | O39: OK | P39: - | Q39: - | R39: 本橋
B40: =ROW()-ROW($B$3) -> 37 | C40: 集計画面(TK) | G40: 集計名 | K40: 同上 | L40: 同上 | N40: OK | O40: OK | P40: - | Q40: - | R40: 本橋
B41: =ROW()-ROW($B$3) -> 38 | C41: 集計画面(TK) | G41: 支払ステータス | K41: 同上 | L41: 同上 | N41: OK | O41: OK | P41: - | Q41: - | R41: 本橋
B42: =ROW()-ROW($B$3) -> 39 | C42: 集計画面(TK) | G42: 集計方法 | K42: 同上 | L42: 同上 | N42: OK | O42: OK | P42: - | Q42: - | R42: 本橋
B43: =ROW()-ROW($B$3) -> 40 | C43: 集計画面(TK) | G43: 会計データ出力 | K43: 同上 | L43: 同上 | N43: OK | O43: OK | P43: - | Q43: - | R43: 本橋
B44: =ROW()-ROW($B$3) -> 41 | C44: 集計画面(TK) | G44: 経費数 | K44: 同上 | L44: 同上 | N44: OK | O44: OK | P44: - | Q44: - | R44: 本橋
B45: =ROW()-ROW($B$3) -> 42 | C45: 集計画面(TK) | G45: 総額 | K45: 同上 | L45: 同上 | N45: OK | O45: OK | P45: - | Q45: - | R45: 本橋
B46: =ROW()-ROW($B$3) -> 43 | C46: 集計画面(TK) | G46: 削除ボタン | K46: 削除ボタンを押下する | L46: 任意の集計が削除されること | N46: OK | O46: OK | P46: - | Q46: - | R46: 本橋
B47: =ROW()-ROW($B$3) -> 44 | C47: 集計画面(TK) | F47: 旅費申請 | G47: 作成日時 | K47: 左記の表示項目を確認する 任意の集計詳細を開き内容を確認する | L47: 左記の表示項目が表示されていること 項目の内容が正しいこと | N47: OK | O47: OK | P47: - | Q47: - | R47: 本橋
B48: =ROW()-ROW($B$3) -> 45 | C48: 集計画面(TK) | G48: 集計名 | K48: 同上 | L48: 同上 | N48: OK | O48: OK | P48: - | Q48: - | R48: 本橋
B49: =ROW()-ROW($B$3) -> 46 | C49: 集計画面(TK) | G49: 集計方法 | K49: 同上 | L49: 同上 | N49: OK | O49: OK | P49: - | Q49: - | R49: 本橋
B50: =ROW()-ROW($B$3) -> 47 | C50: 集計画面(TK) | G50: 経費数 | K50: 同上 | L50: 同上 | N50: OK | O50: OK | P50: - | Q50: - | R50: 本橋
B51: =ROW()-ROW($B$3) -> 48 | C51: 集計画面(TK) | G51: 総額 | K51: 同上 | L51: 同上 | N51: OK | O51: OK | P51: - | Q51: - | R51: 本橋
B52: =ROW()-ROW($B$3) -> 49 | C52: 集計画面(TK) | G52: 削除ボタン | K52: 削除ボタンを押下する | L52: 任意の集計が削除されること | N52: OK | O52: OK | P52: - | Q52: - | R52: 本橋
B53: =ROW()-ROW($B$3) -> 50 | C53: 集計画面(TK) | D53: 申請一覧 | E53: 経費申請タブ | K53: 左記のタブを押下 | L53: 切り替わること | N53: OK | O53: OK | P53: - | Q53: - | R53: 北川
B54: =ROW()-ROW($B$3) -> 51 | C54: 集計画面(TK) | E54: 事前申請タブ | K54: 同上 | L54: 同上 | N54: OK | O54: OK | P54: OK | Q54: OK | R54: 北川
B55: =ROW()-ROW($B$3) -> 52 | C55: 集計画面(TK) | E55: 旅費申請タブ | K55: 同上 | L55: 同上 | N55: OK | O55: OK | P55: OK | Q55: OK | R55: 北川
B56: =ROW()-ROW($B$3) -> 53 | C56: 集計画面(TK) | E56: 検索条件を設定 | K56: 検索条件を設定を押下して展開 任意の検索設定を設定する | L56: 任意の検索設定が設定できること | N56: OK | O56: - | P56: - | Q56: - | R56: 北川
B57: =ROW()-ROW($B$3) -> 54 | C57: 集計画面(TK) | F57: 申請日~から | K57: 左記の検索条件を設定して検索 | L57: 条件に基づいた検索結果が表示されること | N57: OK | O57: - | P57: - | Q57: - | R57: 北川
B58: =ROW()-ROW($B$3) -> 55 | C58: 集計画面(TK) | F58: 申請日~まで | K58: 同上 | L58: 同上 | N58: OK | O58: - | P58: - | Q58: - | R58: 北川
B59: =ROW()-ROW($B$3) -> 56 | C59: 集計画面(TK) | F59: 利用日経費~から | K59: 同上 | L59: 同上 | N59: OK | O59: - | P59: - | Q59: - | R59: 北川
B60: =ROW()-ROW($B$3) -> 57 | C60: 集計画面(TK) | F60: 利用日経費~まで | K60: 同上 | L60: 同上 | N60: OK | O60: - | P60: - | Q60: - | R60: 北川
B61: =ROW()-ROW($B$3) -> 58 | C61: 集計画面(TK) | F61: 最終承認日~から | K61: 同上 | L61: 同上 | N61: OK | O61: - | P61: - | Q61: - | R61: 北川
B62: =ROW()-ROW($B$3) -> 59 | C62: 集計画面(TK) | F62: 最終承認日~まで | K62: 同上 | L62: 同上 | N62: OK | O62: - | P62: - | Q62: - | R62: 北川
B63: =ROW()-ROW($B$3) -> 60 | C63: 集計画面(TK) | F63: 申請者の所属部署 | K63: 同上 | L63: 同上 | N63: OK | O63: - | P63: - | Q63: - | R63: 北川
B64: =ROW()-ROW($B$3) -> 61 | C64: 集計画面(TK) | F64: 申請者の役職 | K64: 同上 | L64: 同上 | N64: OK | O64: - | P64: - | Q64: - | R64: 北川
B65: =ROW()-ROW($B$3) -> 62 | C65: 集計画面(TK) | F65: 承認済みの承認者 | K65: 同上 | L65: 同上 | N65: OK | O65: - | P65: - | Q65: - | R65: 北川
B66: =ROW()-ROW($B$3) -> 63 | C66: 集計画面(TK) | F66: 費用負担部署 | K66: 同上 | L66: 同上 | N66: OK | O66: - | P66: - | Q66: - | R66: 北川
B67: =ROW()-ROW($B$3) -> 64 | C67: 集計画面(TK) | F67: プロジェクト名 | K67: 同上 | L67: 同上 | N67: OK | O67: - | P67: - | Q67: - | R67: 北川
B68: =ROW()-ROW($B$3) -> 65 | C68: 集計画面(TK) | F68: プロジェクトID | K68: 同上 | L68: 同上 | N68: OK | O68: - | P68: - | Q68: - | R68: 北川
... B74: =ROW()-ROW($B$3) -> 71 | C74: 集計画面(TK) | F74: 適格請求書の取り扱いなし | K74: 同上 | L74: 同上 | N74: OK | O74: - | P74: - | Q74: - | R74: 北川
B75: =ROW()-ROW($B$3) -> 72 | C75: 集計画面(TK) | F75: 集計状況:未集計 | K75: 同上 | L75: 同上 | M75: 集計状況・会計データ～・支払い状況の影響を受けやすいため、対象以外のチェックをはずして確認する | N75: OK | O75: - | P75: - | Q75: - | R75: 北川
B76: =ROW()-ROW($B$3) -> 73 | C76: 集計画面(TK) | F76: 集計状況:集計済み | K76: 同上 | L76: 同上 | N76: OK | O76: - | P76: - | Q76: - | R76: 北川
B77: =ROW()-ROW($B$3) -> 74 | C77: 集計画面(TK) | F77: 会計データ未出力 | K77: 同上 | L77: 同上 | N77: OK | O77: - | P77: - | Q77: - | R77: 北川
B78: =ROW()-ROW($B$3) -> 75 | C78: 集計画面(TK) | F78: 会計データ出力済み | K78: 同上 | L78: 同上 | N78: OK | O78: - | P78: - | Q78: - | R78: 北川
B79: =ROW()-ROW($B$3) -> 76 | C79: 集計画面(TK) | F79: 支払い状況:未払い | K79: 同上 | L79: 同上 | N79: OK | O79: - | P79: - | Q79: - | R79: 北川
B80: =ROW()-ROW($B$3) -> 77 | C80: 集計画面(TK) | F80: 支払状況:支払処理済み | K80: 同上 | L80: 同上 | N80: OK | O80: - | P80: - | Q80: - | R80: 北川
B81: =ROW()-ROW($B$3) -> 78 | C81: 集計画面(TK) | E81: 検索条件をリセット | K81: 検索条件をリセットを押下 | L81: 検索設定がリセットされること | N81: OK | O81: - | P81: - | Q81: - | R81: 北川
B82: =ROW()-ROW($B$3) -> 79 | C82: 集計画面(TK) | E82: この条件で検索 | K82: 任意の設定で検索 | L82: 設定に基づいた検索結果が表示されること | N82: OK | O82: OK | P82: OK | Q82: OK | R82: 北川
B83: =ROW()-ROW($B$3) -> 80 | C83: 集計画面(TK) | E83: この条件で集計 | K83: 任意の検索条件を設定して検索する この条件で集計を押下 | L83: 設定に基づいた検索結果が表示されること 検索結果が集計されること | M83: 検索結果は表示されないが、条件に相当する内容が集計される | N83: OK | O83: OK | P83: OK | Q83: OK | R83: 北川
B84: =ROW()-ROW($B$3) -> 81 | C84: 集計画面(TK) | E84: ページネーション | F84: ページ指定 | K84: カード一覧の任意のページを押下する | L84: 指定したページに移動すること | N84: OK | O84: OK | P84: OK | Q84: OK | R84: 北川
B85: =ROW()-ROW($B$3) -> 82 | C85: 集計画面(TK) | F85: > | K85: カード一覧の>を押下する | L85: 指定したページに移動すること | N85: OK | O85: OK | P85: OK | Q85: OK | R85: 北川
B86: =ROW()-ROW($B$3) -> 83 | C86: 集計画面(TK) | F86: >> | K86: カード一覧の>>を押下する | L86: 最後尾のページに移動すること | M86: 151件以上の登録が必要 | N86: OK | O86: OK | P86: OK | Q86: OK | R86: 北川
B87: =ROW()-ROW($B$3) -> 84 | C87: 集計画面(TK) | F87: < | K87: カード一覧の<を押下する | L87: 指定したページに移動すること | N87: OK | O87: OK | P87: OK | Q87: OK | R87: 北川
B88: =ROW()-ROW($B$3) -> 85 | C88: 集計画面(TK) | F88: << | K88: カード一覧の<<を押下する | L88: 先頭のページに移動すること | M88: 151件以上の登録が必要 | N88: OK | O88: OK | P88: OK | Q88: OK | R88: 北川
B89: =ROW()-ROW($B$3) -> 86 | C89: 集計画面(TK) | E89: 表示件数 | K89: 表示件数を押下する 任意の件数に変更する | L89: 表示件数が切り替わること | N89: OK | O89: OK | P89: OK | Q89: OK | R89: 北川
B90: =ROW()-ROW($B$3) -> 87 | C90: 集計画面(TK) | E90: 選択した件の申請を集計する | K90: 任意の集計を選択する | L90: 集計できること | N90: OK | O90: OK | P90: OK | Q90: OK | R90: 北川
B91: =ROW()-ROW($B$3) -> 88 | C91: 集計画面(TK) | E91: 表示項目設定 | F91: 表示 | K91: 同上 | L91: 表示項目設定を押下 任意の表示項目を設定する 保存を行う | M91: 設定した表示項目が経費一覧に表示されていること | N91: OK | O91: - | P91: - | Q91: - | R91: 本橋
B92: =ROW()-ROW($B$3) -> 89 | C92: 集計画面(TK) | F92: 非表示 | K92: 同上 | L92: 表示項目設定を押下 任意の表示項目を非表示に設定する 保存を行う | M92: 設定した表示項目が経費一覧に表示されないこと | N92: OK | O92: - | P92: - | Q92: - | R92: 本橋
B93: =ROW()-ROW($B$3) -> 90 | C93: 集計画面(TK) | F93: 並び替え | K93: 同上 | L93: 表示項目設定を押下 任意の表示項目の順番を入れ替える 保存を行う | M93: 設定した表示項目が設定した順番で経費一覧に表示されていること | N93: OK | O93: - | P93: - | Q93: - | R93: 本橋
B94: =ROW()-ROW($B$3) -> 91 | C94: 集計画面(TK) | F94: 初期設定に戻す | K94: 同上 | L94: 表示項目設定を押下 初期設定に戻すボタンを押下する | M94: 初期設定に戻ること | N94: OK | O94: - | P94: - | Q94: - | R94: 本橋
B95: =ROW()-ROW($B$3) -> 92 | C95: 集計画面(TK) | E95: 表示項目 | F95: 経費精算 | G95: 経費申請名 | K95: 集計一覧を開き左記のタブを開く 表示項目設定で該当の表示項目を表示させる 内容を確認する | L95: 左記の表示項目が表示されること 内容が正しいこと | N95: OK | O95: - | P95: - | Q95: - | R95: 本橋
B96: =ROW()-ROW($B$3) -> 93 | C96: 集計画面(TK) | G96: 申請ID | K96: 同上 | L96: 同上 | N96: OK | O96: - | P96: - | Q96: - | R96: 本橋
B97: =ROW()-ROW($B$3) -> 94 | C97: 集計画面(TK) | G97: 申請者名 | K97: 同上 | L97: 同上 | N97: OK | O97: - | P97: - | Q97: - | R97: 本橋
B98: =ROW()-ROW($B$3) -> 95 | C98: 集計画面(TK) | G98: 申請者の所属部署 | K98: 同上 | L98: 同上 | N98: OK | O98: - | P98: - | Q98: - | R98: 本橋
B99: =ROW()-ROW($B$3) -> 96 | C99: 集計画面(TK) | G99: 費用負担部署 | K99: 同上 | L99: 同上 | N99: OK | O99: - | P99: - | Q99: - | R99: 本橋
B100: =ROW()-ROW($B$3) -> 97 | C100: 集計画面(TK) | G100: プロジェクト | K100: 同上 | L100: 同上 | N100: OK | O100: - | P100: - | Q100: - | R100: 本橋
B101: =ROW()-ROW($B$3) -> 98 | C101: 集計画面(TK) | G101: 総額 | K101: 同上 | L101: 同上 | N101: OK | O101: - | P101: - | Q101: - | R101: 本橋
B102: =ROW()-ROW($B$3) -> 99 | C102: 集計画面(TK) | G102: 集計状況 | K102: 同上 | L102: 同上 | N102: OK | O102: - | P102: - | Q102: - | R102: 本橋
B103: =ROW()-ROW($B$3) -> 100 | C103: 集計画面(TK) | G103: 会計データ出力状況 | K103: 同上 | L103: 同上 | N103: OK | O103: - | P103: - | Q103: - | R103: 本橋
B104: =ROW()-ROW($B$3) -> 101 | C104: 集計画面(TK) | G104: 支払状況 | K104: 同上 | L104: 同上 | N104: OK | O104: - | P104: - | Q104: - | R104: 本橋
B105: =ROW()-ROW($B$3) -> 102 | C105: 集計画面(TK) | G105: 表示項目の幅を変化させる | K105: 表示項目と表示項目の間をドラッグして幅を変更する | L105: 変更できること | N105: OK | O105: - | P105: - | Q105: - | R105: 本橋
B106: =ROW()-ROW($B$3) -> 103 | C106: 集計画面(TK) | F106: 事前申請(仮払) | G106: 経費申請名 | K106: 集計一覧を開き左記のタブを開く 表示項目設定で該当の表示項目を表示させる 内容を確認する | L106: 左記の表示項目が表示されること 内容が正しいこと | N106: OK | O106: - | P106: - | Q106: - | R106: 本橋
...

Sheet 申請
M2: Win11/ Chrome | N2: Win11/ Edge | O2: Win11/ Firefox | P2: Win11/ Safari
B3: No | C3: 画面 | D3: 確認対象 | E3: 項目3 | F3: 項目4 | G3: 項目5 | H3: 項目6 | I3: 項目7 | J3: テスト実行手順 | K3: 期待値 | L3: 備考 | M3: TK+TI+TD | N3: TI+TD | O3: TI+TD | P3: TK単体 | Q3: 実行者 | R3: 実行備考 | S3: 起票JIRA No
B4: =ROW()-ROW($B$3) -> 1 | C4: 申請一覧 | D4: 申請するボタン | E4: 経費精算 | J4: 1.申請するボタンから経費精算を選ぶ 2.経費一覧が出るので任意の経費を選び、「選択した経費を申請する」を押下 3.申請書名を入力モーダル→完了ボタンを押下 4.申請内容を確認モーダル→申請するボタンを押下 | K4: 申請詳細へ遷移 | M4: OK | N4: - | O4: - | P4: OK | Q4: 金子 金田
B5: =ROW()-ROW($B$3) -> 2 | E5: 事前申請 | J5: 1.申請するボタンから事前申請を選ぶ →事前申請作成画面へ遷移される 3.事前申請内容＆事前申請項目を入力 3.保存して申請するを押下 | K5: 申請詳細へ遷移 | M5: OK | N5: - | O5: - | P5: OK | Q5: 金子 金田
B6: =ROW()-ROW($B$3) -> 3 | E6: 汎用申請 | J6: 1.申請するボタンから汎用申請を選ぶ 2.汎用申請作成画面が遷移され、任意の項目入力後に「申請する」を押下 3.申請モーダル→申請を提出ボタンを押下 | K6: 申請詳細へ遷移 | M6: OK | N6: - | O6: - | P6: OK | Q6: 金子 金田
B7: =ROW()-ROW($B$3) -> 4 | E7: 支払依頼申請 | J7: 1.申請するボタンから支払依頼申請を選ぶ | K7: 請求書一覧へ遷移 | M7: OK | N7: OK | O7: OK | P7: - | Q7: 金子 金田
B8: =ROW()-ROW($B$3) -> 5 | E8: 稟議申請 | J8: 1.申請するボタンから稟議申請を選ぶ | K8: 発注稟議作成画面へ遷移 | M8: OK | N8: OK | O8: OK | P8: - | Q8: 金子 金田
B9: =ROW()-ROW($B$3) -> 6 | E9: 一括支払依頼申請 | J9: 1.申請するボタンから一括支払依頼申請を選ぶ | K9: 請求書一覧へ遷移 | M9: OK | N9: OK | O9: OK | P9: - | Q9: 金子 金田
B10: =ROW()-ROW($B$3) -> 7 | D10: 検索条件を指定 | E10: 経費精算タブ | J10: 任意の項目で検索 | K10: 検索通りに絞り込めること | M10: OK | N10: - | O10: - | P10: - | Q10: 金子
B11: =ROW()-ROW($B$3) -> 8 | E11: 事前申請タブ | J11: 任意の項目で検索 | K11: 検索通りに絞り込めること | M11: OK | N11: - | O11: - | P11: - | Q11: 金子
B12: =ROW()-ROW($B$3) -> 9 | E12: 汎用申請タブ | J12: 任意の項目で検索 | K12: 検索通りに絞り込めること | M12: OK | N12: - | O12: - | P12: - | Q12: 金子
B13: =ROW()-ROW($B$3) -> 10 | E13: 支払依頼申請タブ | J13: 任意の項目で検索 | K13: 検索通りに絞り込めること | M13: OK | N13: - | O13: - | P13: - | Q13: 金子
B14: =ROW()-ROW($B$3) -> 11 | E14: 稟議申請タブ | J14: 任意の項目で検索 | K14: 検索通りに絞り込めること | M14: OK | N14: - | O14: - | P14: - | Q14: 金子
B15: =ROW()-ROW($B$3) -> 12 | E15: 一括支払依頼申請 | J15: 任意の項目で検索 | K15: 検索通りに絞り込めること | M15: OK | N15: - | O15: - | P15: - | Q15: 金子
B16: =ROW()-ROW($B$3) -> 13 | D16: 検索条件をリセット | J16: 検索条件をリセットを押下 | K16: リセットできること | M16: OK | N16: - | O16: - | P16: - | Q16: 金子
B17: =ROW()-ROW($B$3) -> 14 | D17: 経費精算タブ | E17: 表示項目設定 | J17: 任意の項目で表示項目設定する | K17: 設定どおりに一覧が最新化されること | M17: OK | N17: - | O17: - | P17: - | Q17: 金子
B18: =ROW()-ROW($B$3) -> 15 | E18: ソートボタン | F18: 申請ID | J18: 申請IDカラムのソートボタンを押下 | K18: 一覧がID順になること | M18: OK | N18: - | O18: - | P18: - | Q18: 金子
B19: =ROW()-ROW($B$3) -> 16 | F19: 申請種別 | J19: 1.申請種別カラムを押下 2.経費申請、精算(仮払以外)、精算(仮払)の✅を外す | K19: 外したものが一覧から外れること | M19: OK | N19: - | O19: - | P19: - | Q19: 金子
B20: =ROW()-ROW($B$3) -> 17 | E20: 申請状況 | F20: 未申請 | J20: 1.経費を下書き保存する 2.申請一覧を確認 | K20: 未申請ステータスになること | M20: OK | N20: - | O20: - | P20: - | Q20: 金子
B21: =ROW()-ROW($B$3) -> 18 | F21: 承認待ち | J21: 1.経費申請する 2.申請一覧を確認 | K21: 承認待ちステータスになること | M21: OK | N21: - | O21: - | P21: - | Q21: 金子
B22: =ROW()-ROW($B$3) -> 19 | F22: 取下げ | J22: 1.経費を取り下げる 2.申請一覧を確認 | K22: 取下げステータスになること | M22: OK | N22: - | O22: - | P22: - | Q22: 金子
B23: =ROW()-ROW($B$3) -> 20 | F23: 差し戻し | J23: 1.(承認者が)経費を差し戻す 2.申請一覧を確認 | K23: 差し戻しステータスになること | M23: OK | N23: - | O23: - | P23: - | Q23: 金子
B24: =ROW()-ROW($B$3) -> 21 | F24: フロー変更待ち | J24: 1.経費申請後に当該申請フローを変更する 2.申請一覧を確認 | K24: フロー変更待ちステータスになること | M24: OK | N24: - | O24: - | P24: - | Q24: 金子
B25: =ROW()-ROW($B$3) -> 22 | F25: 承認済み | J25: 1.経費申請する 2.(承認者が)承認する 3.申請一覧を確認 | K25: 承認待ちステータスになること | M25: OK | N25: - | O25: - | P25: - | Q25: 金子
B26: =ROW()-ROW($B$3) -> 23 | F26: 支払処理済み | J26: 1.経費申請する 2.(承認者が)承認する 3.(集計者が)支払処理する 4.申請一覧を確認 | K26: 支払処理済みステータスになること | M26: OK | N26: - | O26: - | P26: - | Q26: 金子
B27: =ROW()-ROW($B$3) -> 24 | E27: 出力ボタン | F27: 精算申請書出力 | K27: 精算申請書をダウンロードできること | M27: OK | N27: - | O27: - | P27: - | Q27: 金子
B28: =ROW()-ROW($B$3) -> 25 | F28: 会計データ出力 | G28: 任意のフォーマット | H28: メールで送信 | K28: メールで通知されること | M28: OK | N28: - | O28: - | P28: - | Q28: 金子
B29: =ROW()-ROW($B$3) -> 26 | H29: ダウンロード | K29: 会計データが出力されること | M29: OK | N29: - | O29: - | P29: - | Q29: 金子
B30: =ROW()-ROW($B$3) -> 27 | E30: 削除ボタン | K30: 削除できること | M30: OK | N30: - | O30: - | P30: - | Q30: 金子
B31: =ROW()-ROW($B$3) -> 28 | E31: 表示件数 | K31: 表示件数を変更できること | M31: OK | N31: - | O31: - | P31: - | Q31: 金田
B32: =ROW()-ROW($B$3) -> 29 | E32: ページネーション | F32: 数字のボタン | K32: 押下した通りにページ遷移できること | M32: OK | N32: - | O32: - | P32: - | Q32: 金田
B33: =ROW()-ROW($B$3) -> 30 | F33: 「>」ボタン | K33: 押下した通りにページ遷移できること | M33: OK | N33: - | O33: - | P33: - | Q33: 金田
B34: =ROW()-ROW($B$3) -> 31 | F34: 「<」ボタン | K34: 押下した通りにページ遷移できること | M34: OK | N34: - | O34: - | P34: - | Q34: 金田
B35: =ROW()-ROW($B$3) -> 32 | F35: 「>>」ボタン | K35: 押下した通りにページ遷移できること | M35: OK | N35: - | O35: - | P35: - | Q35: 金田
B36: =ROW()-ROW($B$3) -> 33 | F36: 「<<」ボタン | K36: 押下した通りにページ遷移できること | M36: OK | N36: - | O36: - | P36: - | Q36: 金田
B37: =ROW()-ROW($B$3) -> 34 | D37: 事前申請タブ | E37: 表示項目設定 | J37: 任意の項目で表示項目設定する | K37: 設定どおりに一覧が最新化されること | M37: OK | N37: - | O37: - | P37: - | Q37: 金子
B38: =ROW()-ROW($B$3) -> 35 | E38: ソートボタン | F38: 申請ID | J38: 申請IDカラムのソートボタンを押下 | K38: 一覧がID順になること | M38: OK | N38: - | O38: - | P38: - | Q38: 金子
B39: =ROW()-ROW($B$3) -> 36 | E39: 申請状況 | F39: 未申請 | K39: 未申請ステータスになること | M39: OK | N39: - | O39: - | P39: - | Q39: 北川 | R39: （金子）実施方法不明 →事前申請を作成し、保存して申請するを押下後、事前申請ダイアログで申請せずにダイアログを閉じる
B40: =ROW()-ROW($B$3) -> 37 | F40: 承認待ち(事前申請) | K40: 承認待ち(事前申請)になること | M40: OK | N40: - | O40: - | P40: - | Q40: 金子
B41: =ROW()-ROW($B$3) -> 38 | F41: 取下げ(事前申請) | K41: 取下げ(事前申請)になること | M41: OK | N41: - | O41: - | P41: - | Q41: 金子
B42: =ROW()-ROW($B$3) -> 39 | F42: 差し戻し(事前申請) | K42: 差し戻し(事前申請)になること | M42: OK | N42: - | O42: - | P42: - | Q42: 金子
B43: =ROW()-ROW($B$3) -> 40 | F43: フロー変更待ち(事前申請) | K43: フロー変更待ち(事前申請)になること | M43: OK | N43: - | O43: - | P43: - | Q43: 金子
B44: =ROW()-ROW($B$3) -> 41 | F44: 未精算 | K44: 未精算になること | M44: OK | N44: - | O44: - | P44: - | Q44: 金子
B45: =ROW()-ROW($B$3) -> 42 | F45: 仮払待ち | J45: 事前申請(仮払い)を承認 | K45: 仮払待ちになること | M45: OK | N45: - | O45: - | P45: - | Q45: 金子
B46: =ROW()-ROW($B$3) -> 43 | F46: 仮払差額返金待ち | J46: 事前申請(仮払い) に紐づけた経費に差額がある状態で承認 | K46: 仮払差額返金待ちになること | M46: OK | N46: - | O46: - | P46: - | Q46: 金子
B47: =ROW()-ROW($B$3) -> 44 | F47: 取下げ(精算申請) | K47: 取下げ(精算申請)になること | M47: OK | N47: - | O47: - | P47: - | Q47: 金子
B48: =ROW()-ROW($B$3) -> 45 | F48: 差し戻し(精算申請) | K48: 差し戻し(精算申請)になること | M48: OK | N48: - | O48: - | P48: - | Q48: 金子
B49: =ROW()-ROW($B$3) -> 46 | F49: フロー変更待ち(精算申請) | K49: フロー変更待ち(精算申請)になること | M49: OK | N49: - | O49: - | P49: - | Q49: 金子
B50: =ROW()-ROW($B$3) -> 47 | F50: 承認待ち(精算申請) | K50: 承認待ち(精算申請)になること | M50: OK | N50: - | O50: - | P50: - | Q50: 金子
B51: =ROW()-ROW($B$3) -> 48 | F51: 精算済み | K51: 精算済みになること | M51: OK | N51: - | O51: - | P51: - | Q51: 金子
B52: =ROW()-ROW($B$3) -> 49 | F52: 支払処理済み | K52: 支払処理済みになること | M52: OK | N52: - | O52: - | P52: - | Q52: 金子 | R52: 経費精算タブに表示される
B53: =ROW()-ROW($B$3) -> 50 | E53: 出力ボタン | F53: 事前申請書出力 | K53: 精算申請書をダウンロードできること | M53: OK | N53: - | O53: - | P53: - | Q53: 金子
B54: =ROW()-ROW($B$3) -> 51 | F54: 会計データ出力 | G54: 任意のフォーマット | H54: メールで送信 | K54: メールで通知されること | M54: OK | N54: - | O54: - | P54: - | Q54: 金子
B55: =ROW()-ROW($B$3) -> 52 | H55: ダウンロード | K55: 会計データが出力されること | M55: OK | N55: - | O55: - | P55: - | Q55: 金子
B56: =ROW()-ROW($B$3) -> 53 | E56: 削除ボタン | K56: 削除できること | M56: OK | N56: - | O56: - | P56: - | Q56: 金子
B57: =ROW()-ROW($B$3) -> 54 | E57: 表示件数 | K57: 表示件数を変更できること | M57: OK | N57: - | O57: - | P57: - | Q57: 金田
B58: =ROW()-ROW($B$3) -> 55 | E58: ページネーション | F58: 数字のボタン | K58: 押下した通りにページ遷移できること | M58: OK | N58: - | O58: - | P58: - | Q58: 金田
B59: =ROW()-ROW($B$3) -> 56 | F59: 「>」ボタン | K59: 押下した通りにページ遷移できること | M59: OK | N59: - | O59: - | P59: - | Q59: 金田
B60: =ROW()-ROW($B$3) -> 57 | F60: 「<」ボタン | K60: 押下した通りにページ遷移できること | M60: OK | N60: - | O60: - | P60: - | Q60: 金田
B61: =ROW()-ROW($B$3) -> 58 | F61: 「>>」ボタン | K61: 押下した通りにページ遷移できること | M61: OK | N61: - | O61: - | P61: - | Q61: 金田
B62: =ROW()-ROW($B$3) -> 59 | F62: 「<<」ボタン | K62: 押下した通りにページ遷移できること | M62: OK | N62: - | O62: - | P62: - | Q62: 金田
B63: =ROW()-ROW($B$3) -> 60 | D63: 汎用申請タブ | E63: 表示項目設定 | J63: 任意の項目で表示項目設定する | K63: 設定どおりに一覧が最新化されること | M63: OK | N63: - | O63: - | P63: - | Q63: 金子
B64: =ROW()-ROW($B$3) -> 61 | E64: ソートボタン | F64: 申請ID | J64: 申請IDカラムのソートボタンを押下 | K64: 一覧がID順になること | M64: OK | N64: - | O64: - | P64: - | Q64: 金子
B65: =ROW()-ROW($B$3) -> 62 | E65: 申請状況 | F65: 承認待ち | J65: 1.汎用申請する 2.申請一覧を確認 | K65: 承認待ちステータスになること | M65: OK | N65: - | O65: - | P65: - | Q65: 金子
B66: =ROW()-ROW($B$3) -> 63 | F66: 取下げ | J66: 1.汎用申請を取り下げる 2.申請一覧を確認 | K66: 取下げステータスになること | M66: OK | N66: - | O66: - | P66: - | Q66: 金子
B67: =ROW()-ROW($B$3) -> 64 | J67: 1.(承認者が)汎用申請を差し戻す 2.申請一覧を確認 | K67: 差し戻しステータスになること | M67: OK | N67: - | O67: - | P67: - | Q67: 金子
B68: =ROW()-ROW($B$3) -> 65 | F68: フロー変更待ち | J68: 1.汎用申請後に当該申請フローを変更する 2.申請一覧を確認 | K68: フロー変更待ちステータスになること | M68: OK | N68: - | O68: - | P68: - | Q68: 金子
B69: =ROW()-ROW($B$3) -> 66 | F69: 承認済み | J69: 1.汎用申請する 2.(承認者が)承認する 3.申請一覧を確認 | K69: 承認待ちステータスになること | M69: OK | N69: - | O69: - | P69: - | Q69: 金子
B70: =ROW()-ROW($B$3) -> 67 | F70: 支払処理済み | J70: 1.汎用申請する 2.(承認者が)承認する 3.(集計者が)支払処理する 4.申請一覧を確認 | K70: 支払処理済みステータスになること | M70: 外 | N70: - | O70: - | P70: - | Q70: 北川 | R70: 汎用申請には支払処理済みステータスが存在しない
B71: =ROW()-ROW($B$3) -> 68 | E71: 削除ボタン | K71: 削除できること | M71: OK | N71: - | O71: - | P71: - | Q71: 金子
B72: =ROW()-ROW($B$3) -> 69 | E72: 表示件数 | K72: 表示件数を変更できること | M72: OK | N72: - | O72: - | P72: - | Q72: 金田
B73: =ROW()-ROW($B$3) -> 70 | E73: ページネーション | F73: 数字のボタン | K73: 押下した通りにページ遷移できること | M73: OK | N73: - | O73: - | P73: - | Q73: 金田
B74: =ROW()-ROW($B$3) -> 71 | F74: 「>」ボタン | K74: 押下した通りにページ遷移できること | M74: OK | N74: - | O74: - | P74: - | Q74: 金田
B75: =ROW()-ROW($B$3) -> 72 | F75: 「<」ボタン | K75: 押下した通りにページ遷移できること | M75: OK | N75: - | O75: - | P75: - | Q75: 金田
B76: =ROW()-ROW($B$3) -> 73 | F76: 「>>」ボタン | K76: 押下した通りにページ遷移できること | M76: OK | N76: - | O76: - | P76: - | Q76: 金田
B77: =ROW()-ROW($B$3) -> 74 | F77: 「<<」ボタン | K77: 押下した通りにページ遷移できること | M77: OK | N77: - | O77: - | P77: - | Q77: 金田
B78: =ROW()-ROW($B$3) -> 75 | D78: 支払依頼申請タブ | E78: 表示項目設定 | J78: 任意の項目で表示項目設定する | K78: 設定どおりに一覧が最新化されること | M78: OK | N78: - | O78: - | P78: - | Q78: 金子
B79: =ROW()-ROW($B$3) -> 76 | E79: ソートボタン | F79: 支払期日 | J79: カラムのソートボタンを押下 | K79: 一覧が支払期日順になること | M79: OK | N79: - | O79: - | P79: - | Q79: 金子
B80: =ROW()-ROW($B$3) -> 77 | F80: 支払希望日 | J80: 同上 | K80: 一覧が支払希望日順になること | M80: OK | N80: - | O80: - | P80: - | Q80: 金子
B81: =ROW()-ROW($B$3) -> 78 | F81: 申請ID | J81: 同上 | K81: 一覧がID順になること | M81: OK | N81: - | O81: - | P81: - | Q81: 金子
B82: =ROW()-ROW($B$3) -> 79 | E82: 申請状況 | F82: 承認待ち | J82: 1.支払依頼申請する 2.申請一覧を確認 | K82: 承認待ちステータスになること | M82: OK | N82: - | O82: - | P82: - | Q82: 金子
B83: =ROW()-ROW($B$3) -> 80 | F83: 取下げ | J83: 1.支払依頼申請を取り下げる 2.申請一覧を確認 | K83: 取下げステータスになること | M83: OK | N83: - | O83: - | P83: - | Q83: 金子
B84: =ROW()-ROW($B$3) -> 81 | F84: 差し戻し | J84: 1.(承認者が)支払依頼申請を差し戻す 2.申請一覧を確認 | K84: 差し戻しステータスになること | M84: OK | N84: - | O84: - | P84: - | Q84: 金子
B85: =ROW()-ROW($B$3) -> 82 | F85: フロー変更待ち | J85: 1.支払依頼申請後に当該申請フローを変更する 2.申請一覧を確認 | K85: フロー変更待ちステータスになること | M85: OK | N85: - | O85: - | P85: - | Q85: 金子
B86: =ROW()-ROW($B$3) -> 83 | F86: 承認済み | J86: 1.支払依頼申請する 2.(承認者が)承認する 3.申請一覧を確認 | K86: 承認待ちステータスになること | M86: OK | N86: - | O86: - | P86: - | Q86: 金子
B87: =ROW()-ROW($B$3) -> 84 | F87: 支払処理済み | J87: 1.支払依頼申請する 2.(承認者が)承認する 3.(集計者が)支払依頼申請する 4.申請一覧を確認 | K87: 支払処理済みステータスになること | M87: OK | N87: - | O87: - | P87: - | Q87: 金子
B88: =ROW()-ROW($B$3) -> 85 | E88: 削除ボタン | K88: 削除できること | M88: OK | N88: - | O88: - | P88: - | Q88: 金子
B89: =ROW()-ROW($B$3) -> 86 | E89: 表示件数 | K89: 表示件数を変更できること | M89: OK | N89: - | O89: - | P89: - | Q89: 金田
B90: =ROW()-ROW($B$3) -> 87 | E90: ページネーション | F90: 数字のボタン | K90: 押下した通りにページ遷移できること | M90: OK | N90: - | O90: - | P90: - | Q90: 金田
B91: =ROW()-ROW($B$3) -> 88 | F91: 「>」ボタン | K91: 押下した通りにページ遷移できること | M91: OK | N91: - | O91: - | P91: - | Q91: 金田
B92: =ROW()-ROW($B$3) -> 89 | F92: 「<」ボタン | K92: 押下した通りにページ遷移できること | M92: OK | N92: - | O92: - | P92: - | Q92: 金田
B93: =ROW()-ROW($B$3) -> 90 | F93: 「>>」ボタン | K93: 押下した通りにページ遷移できること | M93: OK | N93: - | O93: - | P93: - | Q93: 金田
B94: =ROW()-ROW($B$3) -> 91 | F94: 「<<」ボタン | K94: 押下した通りにページ遷移できること | M94: OK | N94: - | O94: - | P94: - | Q94: 金田
B95: =ROW()-ROW($B$3) -> 92 | D95: 稟議申請タブ | E95: 表示項目設定 | J95: 任意の項目で表示項目設定する | K95: 設定どおりに一覧が最新化されること | M95: OK | N95: - | O95: - | P95: - | Q95: 金子
B96: =ROW()-ROW($B$3) -> 93 | E96: ソートボタン | F96: 支払期日 | J96: カラムのソートボタンを押下 | K96: 一覧が支払期日順になること | M96: 外 | N96: - | O96: - | P96: - | Q96: 金子 | R96: 該当のカラムがない →本番環境でも同様
B97: =ROW()-ROW($B$3) -> 94 | F97: 支払希望日 | J97: 同上 | K97: 一覧が支払希望日順になること | M97: 外 | N97: - | O97: - | P97: - | Q97: 金子 | R97: 該当のカラムがない →本番環境でも同様
B98: =ROW()-ROW($B$3) -> 95 | F98: 申請ID | J98: 同上 | K98: 一覧がID順になること | M98: OK | N98: - | O98: - | P98: - | Q98: 金子
B99: =ROW()-ROW($B$3) -> 96 | E99: 申請状況 | F99: 承認待ち | J99: 1.支払依頼申請する 2.申請一覧を確認 | K99: 承認待ちステータスになること | M99: OK | N99: - | O99: - | P99: - | Q99: 金子
B100: =ROW()-ROW($B$3) -> 97 | F100: 取下げ | J100: 1.支払依頼申請を取り下げる 2.申請一覧を確認 | K100: 取下げステータスになること | M100: OK | N100: - | O100: - | P100: - | Q100: 金子
B101: =ROW()-ROW($B$3) -> 98 | F101: 差し戻し | J101: 1.(承認者が)支払依頼申請を差し戻す 2.申請一覧を確認 | K101: 差し戻しステータスになること | M101: OK | N101: - | O101: - | P101: - | Q101: 金子
...

Sheet 承認
L2: Win11/ Chrome | M2: Win11/ Edge | N2: Win11/ Firefox | O2: Mac/ Safari
B3: No | C3: 画面 | D3: 確認対象 | E3: 項目3 | F3: 項目4 | G3: 項目5 | H3: 項目6 | I3: テスト実行手順 | J3: 期待値 | K3: 備考 | L3: TK+TI+TD | M3: TI+TD | N3: TI+TD | O3: TK単体 | P3: 実行者 | Q3: 実行備考 | R3: 起票JIRA No
B4: =ROW()-ROW($B$3) -> 1 | C4: 承認一覧 | D4: ファイル出力確認 | E4: 経費精算タブ | F4: この条件で会計データ作成を開始ボタン | G4: メールで送信 | J4: メール通知されること | L4: OK | M4: - | N4: - | O4: OK | P4: 金田
B5: =ROW()-ROW($B$3) -> 2 | G5: ダウンロード | J5: 指定したファイルでダウンロードされること | L5: OK | M5: - | N5: - | O5: OK | P5: 金田
B6: =ROW()-ROW($B$3) -> 3 | E6: 事前申請タブ | F6: この条件でファイル出力するボタン | G6: 最新の出力ファイルを開始 | J6: 最新のファイルがダウンロードできること | L6: OK | M6: - | N6: - | O6: - | P6: 金田 | Q6: ファイル出力を行おうとした際にエラーで出力が出来ない | R6: FA-98 ⇒修正確認済
B7: =ROW()-ROW($B$3) -> 4 | E7: 汎用申請タブ | F7: この条件でファイル出力するボタン | J7: 最新のファイルがダウンロードできること | L7: OK | M7: - | N7: - | O7: - | P7: 金田
B8: =ROW()-ROW($B$3) -> 5 | E8: 支払依頼申請タブ | F8: この条件で会計データ作成を開始ボタン | G8: ダウンロード | J8: 指定したファイルでダウンロードされること | L8: OK | M8: OK | N8: OK | O8: - | P8: 金田
B9: =ROW()-ROW($B$3) -> 6 | E9: 一括支払依頼申請タブ | F9: ボタン非表示確認 | J9: ファイル出力ボタンが非表示 | L9: OK | M9: OK | N9: OK | O9: - | P9: 金田
B10: =ROW()-ROW($B$3) -> 7 | E10: 稟議申請タブ | F10: ボタン非表示確認 | J10: ファイル出力ボタンが非表示 | L10: OK | M10: - | N10: - | O10: - | P10: 北川 | Q10: 項目修正依頼中 →仕様変更により表示される
B11: =ROW()-ROW($B$3) -> 8 | D11: 検索条件を指定 | E11: 経費精算タブ | I11: 任意の項目で検索 | J11: 検索通りに絞り込めること | L11: OK | M11: - | N11: - | O11: - | P11: 金田
B12: =ROW()-ROW($B$3) -> 9 | E12: 事前申請タブ | I12: 任意の項目で検索 | J12: 検索通りに絞り込めること | L12: OK | M12: - | N12: - | O12: - | P12: 金田
B13: =ROW()-ROW($B$3) -> 10 | E13: 汎用申請タブ | I13: 任意の項目で検索 | J13: 検索通りに絞り込めること | L13: OK | M13: - | N13: - | O13: - | P13: 金田
B14: =ROW()-ROW($B$3) -> 11 | E14: 支払依頼申請タブ | I14: 任意の項目で検索 | J14: 検索通りに絞り込めること | L14: OK | M14: - | N14: - | O14: - | P14: 金田
B15: =ROW()-ROW($B$3) -> 12 | E15: 稟議申請タブ | I15: 任意の項目で検索 | J15: 検索通りに絞り込めること | L15: OK | M15: - | N15: - | O15: - | P15: 金田
B16: =ROW()-ROW($B$3) -> 13 | E16: 一括支払依頼申請 | I16: 任意の項目で検索 | J16: 検索通りに絞り込めること | L16: OK | M16: - | N16: - | O16: - | P16: 金田
B17: =ROW()-ROW($B$3) -> 14 | D17: 検索条件をリセット | I17: 検索条件をリセットを押下 | J17: リセットできること | L17: OK | M17: - | N17: - | O17: - | P17: 金田
B18: =ROW()-ROW($B$3) -> 15 | D18: 経費精算タブ | E18: 一括承認 | I18: 前提：システム設定 > 申請フロー で一括承認設定をONにする 1.承認一覧で、任意のデータにチェックをいれて、一括承認ボタンを押下 | J18: 一括承認できること | L18: OK | M18: - | N18: - | O18: - | P18: 金田
B19: =ROW()-ROW($B$3) -> 16 | E19: 表示項目設定 | I19: 任意の項目で表示項目設定する | J19: 設定どおりに一覧が最新化されること | L19: OK | M19: - | N19: - | O19: - | P19: 金田
B20: =ROW()-ROW($B$3) -> 17 | E20: ソートボタン | F20: 申請ID | I20: 申請IDカラムのソートボタンを押下 | J20: 一覧がID順になること | L20: OK | M20: - | N20: - | O20: - | P20: 金田
B21: =ROW()-ROW($B$3) -> 18 | F21: 申請種別 | I21: 1.申請種別カラムを押下 2.経費申請、精算(仮払以外)、精算(仮払)の✅を外す | J21: 外したものが一覧から外れること | L21: OK | M21: - | N21: - | O21: - | P21: 金子
B22: =ROW()-ROW($B$3) -> 19 | E22: 申請状況 | F22: 承認待ち | I22: 1.申請者：経費申請する 2.承認者：承認一覧を確認 | J22: 承認待ちステータスになること | L22: OK | M22: - | N22: - | O22: - | P22: 金田
B23: =ROW()-ROW($B$3) -> 20 | F23: 承認済み | I23: 1.申請者：経費申請する 2.承認者：承認する 3.承認者：承認一覧を確認 | J23: 承認待ちステータスになること | L23: OK | M23: - | N23: - | O23: - | P23: 金田
B24: =ROW()-ROW($B$3) -> 21 | F24: 承認見込み | I24: 1.申請者：経費申請する 2.承認者：差し戻す 3.承認者：申請一覧を確認 | J24: 承認見込みステータスになること | L24: OK | M24: - | N24: - | O24: - | P24: 北川 | Q24: 左記手順では承認見込みステータスにならない場合がある。 第２承認で第１承認者に差し戻した際、承認見込みステータスになることを確認 ↑本番と見比べたらOKつけてよいです！（富田）
B25: =ROW()-ROW($B$3) -> 22 | E25: 出力ボタン | F25: 精算申請書出力 | J25: 精算申請書をダウンロードできること | L25: OK | M25: - | N25: - | O25: - | P25: 金田
B26: =ROW()-ROW($B$3) -> 23 | F26: 会計データ出力 | G26: 任意のフォーマット | H26: メールで送信 | J26: メールで通知されること | L26: OK | M26: - | N26: - | O26: - | P26: 金田
B27: =ROW()-ROW($B$3) -> 24 | H27: ダウンロード | J27: 会計データが出力されること | L27: OK | M27: - | N27: - | O27: - | P27: 金田
B28: =ROW()-ROW($B$3) -> 25 | E28: 削除ボタン | J28: 削除できること | L28: OK | M28: - | N28: - | O28: - | P28: 金田
B29: =ROW()-ROW($B$3) -> 26 | E29: 表示件数 | J29: 表示件数を変更できること | L29: OK | M29: - | N29: - | O29: - | P29: 金田
B30: =ROW()-ROW($B$3) -> 27 | E30: ページネーション | F30: 数字のボタン | J30: 押下した通りにページ遷移できること | L30: OK | M30: - | N30: - | O30: - | P30: 金田
B31: =ROW()-ROW($B$3) -> 28 | F31: 「>」ボタン | J31: 押下した通りにページ遷移できること | L31: OK | M31: - | N31: - | O31: - | P31: 金田
B32: =ROW()-ROW($B$3) -> 29 | F32: 「<」ボタン | J32: 押下した通りにページ遷移できること | L32: OK | M32: - | N32: - | O32: - | P32: 金田
B33: =ROW()-ROW($B$3) -> 30 | F33: 「>>」ボタン | J33: 押下した通りにページ遷移できること | L33: OK | M33: - | N33: - | O33: - | P33: 金田
B34: =ROW()-ROW($B$3) -> 31 | F34: 「<<」ボタン | J34: 押下した通りにページ遷移できること | L34: OK | M34: - | N34: - | O34: - | P34: 金田
B35: =ROW()-ROW($B$3) -> 32 | D35: 事前申請タブ | E35: 表示項目設定 | I35: 任意の項目で表示項目設定する | J35: 設定どおりに一覧が最新化されること | L35: OK | M35: - | N35: - | O35: - | P35: 金田
B36: =ROW()-ROW($B$3) -> 33 | E36: ソートボタン | F36: 申請ID | I36: 申請IDカラムのソートボタンを押下 | J36: 一覧がID順になること | L36: OK | M36: - | N36: - | O36: - | P36: 金田
B37: =ROW()-ROW($B$3) -> 34 | E37: 申請状況 | F37: 承認待ち(事前申請) | I37: 1.申請者：事前申請する 2.承認者：承認一覧を確認 | J37: 承認待ち(事前申請)になること | L37: OK | M37: - | N37: - | O37: - | P37: 金田
B38: =ROW()-ROW($B$3) -> 35 | F38: 未精算 | I38: 1.申請者：事前申請する 2.承認者：承認する 3.承認者：承認一覧を確認 ※検索条件で"あなたの承認状況"を「承認済み」にする | J38: 申請状況が 未精算 になること | L38: OK | M38: - | N38: - | O38: - | P38: 金田
B39: =ROW()-ROW($B$3) -> 36 | F39: 承認待ち(精算申請) | I39: 1.申請者：事前申請する 2.承認者：承認する 3.申請者：精算申請する 4.承認者：承認一覧を確認 ※検索条件で"あなたの承認状況"を「承認済み」にする | J39: 申請状況が 承認待ち(精算申請) になること | L39: OK | M39: - | N39: - | O39: - | P39: 金子
B40: =ROW()-ROW($B$3) -> 37 | F40: 精算済み | I40: 1.申請者：事前申請する 2.承認者：承認する 3.申請者：精算申請する 4.承認者：承認一覧を確認 ※検索条件で"あなたの承認状況"を「承認済み」にする | J40: 申請状況が 未精算になること になること | L40: OK | M40: - | N40: - | O40: - | P40: 金子
B41: =ROW()-ROW($B$3) -> 38 | E41: 出力ボタン | F41: 事前申請書出力 | J41: 精算申請書をダウンロードできること | L41: OK | M41: - | N41: - | O41: - | P41: 金田
B42: =ROW()-ROW($B$3) -> 39 | F42: 会計データ出力 | G42: 任意のフォーマット | H42: メールで送信 | J42: メールで通知されること | L42: OK | M42: - | N42: - | O42: - | P42: 金田
B43: =ROW()-ROW($B$3) -> 40 | H43: ダウンロード | J43: 会計データが出力されること | L43: OK | M43: - | N43: - | O43: - | P43: 金田
B44: =ROW()-ROW($B$3) -> 41 | E44: 削除ボタン | J44: 削除できること | L44: OK | M44: - | N44: - | O44: - | P44: 金田
B45: =ROW()-ROW($B$3) -> 42 | E45: 表示件数 | J45: 表示件数を変更できること | L45: OK | M45: - | N45: - | O45: - | P45: 金田
B46: =ROW()-ROW($B$3) -> 43 | E46: ページネーション | F46: 数字のボタン | J46: 押下した通りにページ遷移できること | L46: OK | M46: - | N46: - | O46: - | P46: 金田
B47: =ROW()-ROW($B$3) -> 44 | F47: 「>」ボタン | J47: 押下した通りにページ遷移できること | L47: OK | M47: - | N47: - | O47: - | P47: 金田
B48: =ROW()-ROW($B$3) -> 45 | F48: 「<」ボタン | J48: 押下した通りにページ遷移できること | L48: OK | M48: - | N48: - | O48: - | P48: 金田
B49: =ROW()-ROW($B$3) -> 46 | F49: 「>>」ボタン | J49: 押下した通りにページ遷移できること | L49: OK | M49: - | N49: - | O49: - | P49: 金田
B50: =ROW()-ROW($B$3) -> 47 | F50: 「<<」ボタン | J50: 押下した通りにページ遷移できること | L50: OK | M50: - | N50: - | O50: - | P50: 金田
B51: =ROW()-ROW($B$3) -> 48 | D51: 汎用申請タブ | E51: 表示項目設定 | I51: 任意の項目で表示項目設定する | J51: 設定どおりに一覧が最新化されること | L51: OK | M51: - | N51: - | O51: - | P51: 金田
B52: =ROW()-ROW($B$3) -> 49 | E52: ソートボタン | F52: 申請ID | I52: 申請IDカラムのソートボタンを押下 | J52: 一覧がID順になること | L52: OK | M52: - | N52: - | O52: - | P52: 金田
B53: =ROW()-ROW($B$3) -> 50 | E53: 申請状況 | F53: 承認待ち | I53: 1.申請者：汎用申請する 2.承認者：承認一覧を確認 | J53: 承認待ちステータスになること | L53: OK | M53: - | N53: - | O53: - | P53: 金田
B54: =ROW()-ROW($B$3) -> 51 | F54: 承認済み | I54: 1.申請者：汎用申請する 2.承認者：承認する 3.承認者：承認一覧を確認 | J54: 承認済みステータスになること | L54: OK | M54: - | N54: - | O54: - | P54: 金田
B55: =ROW()-ROW($B$3) -> 52 | F55: 承認見込み | I55: 1.申請者：汎用申請する 2.承認者：差し戻す 3.承認者：申請一覧を確認 | J55: 承認見込みステータスになること | L55: OK | M55: - | N55: - | O55: - | P55: 北川 | Q55: 左記手順では承認見込みステータスにならない場合がある。 第２承認で第１承認者に差し戻した際、承認見込みステータスになることを確認
B56: =ROW()-ROW($B$3) -> 53 | E56: 削除ボタン | J56: 削除できること | L56: OK | M56: - | N56: - | O56: - | P56: 金田
B57: =ROW()-ROW($B$3) -> 54 | E57: 表示件数 | J57: 表示件数を変更できること | L57: OK | M57: - | N57: - | O57: - | P57: 金田
B58: =ROW()-ROW($B$3) -> 55 | E58: ページネーション | F58: 数字のボタン | J58: 押下した通りにページ遷移できること | L58: OK | M58: - | N58: - | O58: - | P58: 金田
B59: =ROW()-ROW($B$3) -> 56 | F59: 「>」ボタン | J59: 押下した通りにページ遷移できること | L59: OK | M59: - | N59: - | O59: - | P59: 金田
B60: =ROW()-ROW($B$3) -> 57 | F60: 「<」ボタン | J60: 押下した通りにページ遷移できること | L60: OK | M60: - | N60: - | O60: - | P60: 金田
B61: =ROW()-ROW($B$3) -> 58 | F61: 「>>」ボタン | J61: 押下した通りにページ遷移できること | L61: OK | M61: - | N61: - | O61: - | P61: 金田
B62: =ROW()-ROW($B$3) -> 59 | F62: 「<<」ボタン | J62: 押下した通りにページ遷移できること | L62: OK | M62: - | N62: - | O62: - | P62: 金田
B63: =ROW()-ROW($B$3) -> 60 | D63: 支払依頼申請タブ | E63: 表示項目設定 | I63: 任意の項目で表示項目設定する | J63: 設定どおりに一覧が最新化されること | L63: OK | M63: - | N63: - | O63: - | P63: 金田
B64: =ROW()-ROW($B$3) -> 61 | E64: ソートボタン | F64: 支払期日 | I64: カラムのソートボタンを押下 | J64: 一覧が支払期日順になること | L64: OK | M64: - | N64: - | O64: - | P64: 金田
B65: =ROW()-ROW($B$3) -> 62 | F65: 支払希望日 | I65: 同上 | J65: 一覧が支払希望日順になること | L65: OK | M65: - | N65: - | O65: - | P65: 金田
B66: =ROW()-ROW($B$3) -> 63 | F66: 計上日 | I66: 同上 | J66: 一覧が計上日順になること | L66: OK | M66: - | N66: - | O66: - | P66: 金田
B67: =ROW()-ROW($B$3) -> 64 | F67: 取引先コード | I67: 同上 | J67: 一覧が取引先コード順になること | L67: OK | M67: - | N67: - | O67: - | P67: 金田
B68: =ROW()-ROW($B$3) -> 65 | F68: 取引先名 | I68: 同上 | J68: 一覧が取引先名順になること | L68: OK | M68: - | N68: - | O68: - | P68: 金田
B69: =ROW()-ROW($B$3) -> 66 | E69: 申請状況 | F69: 承認待ち | I69: 1.申請者：支払依頼申請する 2.承認者：承認一覧を確認 | J69: 承認待ちステータスになること | L69: OK | M69: - | N69: - | O69: - | P69: 金田
B70: =ROW()-ROW($B$3) -> 67 | F70: 承認済み | I70: 1.申請者：支払依頼申請する 2.承認者：承認する 3.承認者：承認一覧を確認 | J70: 承認済みステータスになること | L70: OK | M70: - | N70: - | O70: - | P70: 金田
B71: =ROW()-ROW($B$3) -> 68 | F71: 承認見込み | I71: 1.申請者：支払依頼申請する 2.承認者：差し戻す 3.承認者：申請一覧を確認 | J71: 承認見込みステータスになること | L71: OK | M71: - | N71: - | O71: - | P71: 北川 | Q71: 左記手順では承認見込みステータスにならない場合がある。 第２承認で第１承認者に差し戻した際、承認見込みステータスになることを確認
B72: =ROW()-ROW($B$3) -> 69 | E72: 削除ボタン | J72: 削除できること | L72: OK | M72: - | N72: - | O72: - | P72: 金田
B73: =ROW()-ROW($B$3) -> 70 | E73: 表示件数 | J73: 表示件数を変更できること | L73: OK | M73: - | N73: - | O73: - | P73: 金田
B74: =ROW()-ROW($B$3) -> 71 | E74: ページネーション | F74: 数字のボタン | J74: 押下した通りにページ遷移できること | L74: OK | M74: - | N74: - | O74: - | P74: 金田
B75: =ROW()-ROW($B$3) -> 72 | F75: 「>」ボタン | J75: 押下した通りにページ遷移できること | L75: OK | M75: - | N75: - | O75: - | P75: 金田
B76: =ROW()-ROW($B$3) -> 73 | F76: 「<」ボタン | J76: 押下した通りにページ遷移できること | L76: OK | M76: - | N76: - | O76: - | P76: 金田
B77: =ROW()-ROW($B$3) -> 74 | F77: 「>>」ボタン | J77: 押下した通りにページ遷移できること | L77: OK | M77: - | N77: - | O77: - | P77: 金田
B78: =ROW()-ROW($B$3) -> 75 | F78: 「<<」ボタン | J78: 押下した通りにページ遷移できること | L78: OK | M78: - | N78: - | O78: - | P78: 金田
B79: =ROW()-ROW($B$3) -> 76 | D79: 稟議申請タブ | E79: 表示項目設定 | I79: 任意の項目で表示項目設定する | J79: 設定どおりに一覧が最新化されること | L79: OK | M79: - | N79: - | O79: - | P79: 金田
B80: =ROW()-ROW($B$3) -> 77 | E80: ソートボタン | F80: 申請ID | I80: カラムのソートボタンを押下 | J80: 一覧が支払期日順になること | L80: OK | M80: - | N80: - | O80: - | P80: 金田
B81: =ROW()-ROW($B$3) -> 78 | E81: 申請状況 | F81: 承認待ち | I81: 1.申請者：稟議申請する 2.承認者：承認一覧を確認 | J81: 承認待ちステータスになること | L81: OK | M81: - | N81: - | O81: - | P81: 金田
B82: =ROW()-ROW($B$3) -> 79 | F82: 承認済み | I82: 1.申請者：稟議申請する 2.承認者：承認する 3.承認者：承認一覧を確認 | J82: 承認済みステータスになること | L82: OK | M82: - | N82: - | O82: - | P82: 金田
B83: =ROW()-ROW($B$3) -> 80 | F83: 承認見込み | I83: 1.申請者：稟議申請する 2.承認者：差し戻す 3.承認者：申請一覧を確認 | J83: 承認見込みステータスになること | L83: OK | M83: - | N83: - | O83: - | P83: 金田
B84: =ROW()-ROW($B$3) -> 81 | E84: 削除ボタン | J84: 削除できること | L84: OK | M84: - | N84: - | O84: - | P84: 金田
B85: =ROW()-ROW($B$3) -> 82 | E85: 表示件数 | J85: 表示件数を変更できること | L85: OK | M85: - | N85: - | O85: - | P85: 金田
B86: =ROW()-ROW($B$3) -> 83 | E86: ページネーション | F86: 数字のボタン | J86: 押下した通りにページ遷移できること | L86: OK | M86: - | N86: - | O86: - | P86: 金田
B87: =ROW()-ROW($B$3) -> 84 | F87: 「>」ボタン | J87: 押下した通りにページ遷移できること | L87: OK | M87: - | N87: - | O87: - | P87: 金田
B88: =ROW()-ROW($B$3) -> 85 | F88: 「<」ボタン | J88: 押下した通りにページ遷移できること | L88: OK | M88: - | N88: - | O88: - | P88: 金田
B89: =ROW()-ROW($B$3) -> 86 | F89: 「>>」ボタン | J89: 押下した通りにページ遷移できること | L89: OK | M89: - | N89: - | O89: - | P89: 金田
B90: =ROW()-ROW($B$3) -> 87 | F90: 「<<」ボタン | J90: 押下した通りにページ遷移できること | L90: OK | M90: - | N90: - | O90: - | P90: 金田
B91: =ROW()-ROW($B$3) -> 88 | D91: 一括支払依頼申請タブ | E91: 表示項目設定 | I91: 任意の項目で表示項目設定する | J91: 設定どおりに一覧が最新化されること | L91: OK | M91: - | N91: - | O91: - | P91: 金田
B92: =ROW()-ROW($B$3) -> 89 | E92: ソートボタン | F92: 申請ID | I92: カラムのソートボタンを押下 | J92: 一覧が支払期日順になること | L92: OK | M92: - | N92: - | O92: - | P92: 金田
B93: =ROW()-ROW($B$3) -> 90 | E93: 申請状況 | F93: 承認待ち | I93: 1.申請者：一括支払依頼申請する 2.承認者：承認一覧を確認 | J93: 承認待ちステータスになること | L93: OK | M93: - | N93: - | O93: - | P93: 金田
B94: =ROW()-ROW($B$3) -> 91 | F94: 承認済み | I94: 1.申請者：一括支払依頼申請する 2.承認者：承認する 3.承認者：承認一覧を確認 | J94: 承認済みステータスになること | L94: OK | M94: - | N94: - | O94: - | P94: 金田
B95: =ROW()-ROW($B$3) -> 92 | F95: 承認見込み | I95: 1.申請者：一括支払依頼申請する 2.承認者：差し戻す 3.承認者：申請一覧を確認 | J95: 承認見込みステータスになること | L95: OK | M95: - | N95: - | O95: - | P95: 北川 | Q95: 左記手順では承認見込みステータスにならない場合がある。 第２承認で第１承認者に差し戻した際、承認見込みステータスになることを確認
B96: =ROW()-ROW($B$3) -> 93 | E96: 削除ボタン | J96: 削除できること | L96: OK | M96: - | N96: - | O96: - | P96: 金田
B97: =ROW()-ROW($B$3) -> 94 | E97: 表示件数 | J97: 表示件数を変更できること | L97: OK | M97: - | N97: - | O97: - | P97: 金田
B98: =ROW()-ROW($B$3) -> 95 | E98: ページネーション | F98: 数字のボタン | J98: 押下した通りにページ遷移できること | L98: OK | M98: - | N98: - | O98: - | P98: 金田
B99: =ROW()-ROW($B$3) -> 96 | F99: 「>」ボタン | J99: 押下した通りにページ遷移できること | L99: OK | M99: - | N99: - | O99: - | P99: 金田
B100: =ROW()-ROW($B$3) -> 97 | F100: 「<」ボタン | J100: 押下した通りにページ遷移できること | L100: OK | M100: - | N100: - | O100: - | P100: 金田
B101: =ROW()-ROW($B$3) -> 98 | F101: 「>>」ボタン | J101: 押下した通りにページ遷移できること | L101: OK | M101: - | N101: - | O101: - | P101: 金田
...

Sheet 経費
N2: Win11/ Chrome | O2: Win11/ Edge | P2: Win11/ Firefox | Q2: MacOS/ Safari
B3: No | C3: 画面 | D3: 確認対象 | E3: 詳細 | K3: テスト実行手順 | L3: 期待値 | M3: 備考 | N3: TK+TI+TD | O3: TK+TI+TD | P3: TK単体 | Q3: TK単体 | R3: 実行者 | S3: 実行備考 | T3: 起票JIRA No
B4: =ROW()-ROW($B$3) -> 1 | C4: 経費一覧 | D4: 経費を登録する | E4: 手入力 | K4: 経費を登録する＞手入力を押下する 任意の設定で経費を登録する | L4: 指定した経費が作成できること 保存した経費に入力した内容が反映されていること | M4: 新規ボタンと共通なので項目は省略 | N4: OK | O4: - | P4: - | Q4: - | R4: 金田
B5: =ROW()-ROW($B$3) -> 2 | C5: 経費一覧 | E5: 交通費入力 | K5: 経費を登録する＞交通費入力を押下する 任意の設定で経費を登録する | L5: - | M5: 新規ボタンと共通なので項目は省略 | N5: OK | O5: - | P5: - | Q5: - | R5: 金田
B6: =ROW()-ROW($B$3) -> 3 | C6: 経費一覧 | E6: 日当 | K6: 経費を登録する＞日当を押下する 任意の設定で経費を登録する | L6: - | M6: 新規ボタンと共通なので項目は省略 | N6: OK | O6: - | P6: - | Q6: - | R6: 金田
B7: =ROW()-ROW($B$3) -> 4 | C7: 経費一覧 | E7: 自動入力 | K7: 経費を登録する＞自動入力を押下する | L7: 自動入力新規登録画面に遷移すること | M7: 新規ボタンと共通なので項目は省略 | N7: OK | O7: - | P7: - | Q7: - | R7: 金田
B8: =ROW()-ROW($B$3) -> 5 | C8: 経費一覧 | D8: 検索条件 | E8: 会社全体 | K8: 左記の検索条件を設定して検索 | L8: 条件に基づいた検索結果が表示されること | N8: OK | O8: - | P8: - | Q8: - | R8: 金田
B9: =ROW()-ROW($B$3) -> 6 | C9: 経費一覧 | E9: 削除済み | G9: - | H9: - | K9: 同上 | L9: 同上 | N9: OK | O9: - | P9: - | Q9: - | R9: 金田
B10: =ROW()-ROW($B$3) -> 7 | C10: 経費一覧 | E10: 従業員 | G10: - | H10: - | K10: 同上 | L10: 同上 | N10: OK | O10: - | P10: - | Q10: - | R10: 金田
B11: =ROW()-ROW($B$3) -> 8 | C11: 経費一覧 | E11: 申請ID | G11: - | H11: - | K11: 同上 | L11: 同上 | N11: OK | O11: - | P11: - | Q11: - | R11: 金田
B12: =ROW()-ROW($B$3) -> 9 | C12: 経費一覧 | E12: 利用日 | F12: 〇〇から | G12: - | H12: - | K12: 同上 | L12: 同上 | N12: OK | O12: - | P12: - | Q12: - | R12: 金田
B13: =ROW()-ROW($B$3) -> 10 | C13: 経費一覧 | F13: 〇〇まで | G13: - | H13: - | K13: 同上 | L13: 同上 | N13: OK | O13: - | P13: - | Q13: - | R13: 金田
B14: =ROW()-ROW($B$3) -> 11 | C14: 経費一覧 | F14: 空白検索 | G14: - | H14: - | K14: 同上 | L14: 同上 | N14: OK | O14: - | P14: - | Q14: - | R14: 金田
B15: =ROW()-ROW($B$3) -> 12 | C15: 経費一覧 | E15: 支払先 | G15: - | H15: - | K15: 同上 | L15: 同上 | N15: OK | O15: - | P15: - | Q15: - | R15: 金田
B16: =ROW()-ROW($B$3) -> 13 | C16: 経費一覧 | F16: 空白検索 | G16: - | H16: - | K16: 同上 | L16: 同上 | N16: OK | O16: - | P16: - | Q16: - | R16: 金田
B17: =ROW()-ROW($B$3) -> 14 | C17: 経費一覧 | E17: 金額 | F17: 〇〇から | G17: - | H17: - | K17: 同上 | L17: 同上 | N17: OK | O17: - | P17: - | Q17: - | R17: 金田
B18: =ROW()-ROW($B$3) -> 15 | C18: 経費一覧 | F18: 〇〇まで | G18: - | H18: - | K18: 同上 | L18: 同上 | N18: OK | O18: - | P18: - | Q18: - | R18: 金田
B19: =ROW()-ROW($B$3) -> 16 | C19: 経費一覧 | F19: 空白検索 | G19: - | H19: - | K19: 同上 | L19: 同上 | N19: OK | O19: - | P19: - | Q19: - | R19: 金田
B20: =ROW()-ROW($B$3) -> 17 | C20: 経費一覧 | E20: 経費科目 | G20: - | H20: - | K20: 同上 | L20: 同上 | N20: OK | O20: - | P20: - | Q20: - | R20: 金田
B21: =ROW()-ROW($B$3) -> 18 | C21: 経費一覧 | E21: 所属部署 | G21: - | H21: - | K21: 同上 | L21: 同上 | N21: OK | O21: - | P21: - | Q21: - | R21: 金田
B22: =ROW()-ROW($B$3) -> 19 | C22: 経費一覧 | F22: 下位部署を含む | G22: - | H22: - | K22: 同上 | L22: 同上 | N22: OK | O22: - | P22: - | Q22: - | R22: 金田
B23: =ROW()-ROW($B$3) -> 20 | C23: 経費一覧 | E23: 精算区分 | F23: 精算対象 | G23: - | H23: - | K23: 同上 | L23: 同上 | N23: OK | O23: - | P23: - | Q23: - | R23: 金田
B24: =ROW()-ROW($B$3) -> 21 | C24: 経費一覧 | F24: 精算対象外 | G24: - | H24: - | K24: 同上 | L24: 同上 | N24: OK | O24: - | P24: - | Q24: - | R24: 金田
B25: =ROW()-ROW($B$3) -> 22 | C25: 経費一覧 | E25: コーポレートカード利用 | F25: あり | G25: - | H25: - | K25: 同上 | L25: 同上 | M25: dev環境で行う | N25: OK | O25: - | P25: - | Q25: - | R25: 本橋
B26: =ROW()-ROW($B$3) -> 23 | C26: 経費一覧 | F26: なし | G26: - | H26: - | K26: 同上 | L26: 同上 | N26: OK | O26: - | P26: - | Q26: - | R26: 本橋
B27: =ROW()-ROW($B$3) -> 24 | C27: 経費一覧 | E27: 原本確認 | F27: 確認済み | K27: 同上 | L27: 同上 | M27: PLP契約がないと表示されない | N27: OK | O27: - | P27: - | Q27: - | R27: 行田 | S27: 同上
B28: =ROW()-ROW($B$3) -> 25 | C28: 経費一覧 | F28: 確認済みステータス更新 | K28: 同上 | L28: 同上 | N28: OK | O28: - | P28: - | Q28: - | R28: 行田 | S28: 同上
B29: =ROW()-ROW($B$3) -> 26 | C29: 経費一覧 | F29: 未確認 | K29: 同上 | L29: 同上 | N29: OK | O29: - | P29: - | Q29: - | R29: 行田 | S29: 同上
B30: =ROW()-ROW($B$3) -> 27 | C30: 経費一覧 | F30: 不要 | K30: 同上 | L30: 同上 | N30: OK | O30: - | P30: - | Q30: - | R30: 行田 | S30: 同上
B31: =ROW()-ROW($B$3) -> 28 | C31: 経費一覧 | E31: 出力ID | G31: - | H31: - | K31: 同上 | L31: 同上 | M31: 適当なIDで検索して検索結果が出なければOK | N31: OK | O31: - | P31: - | Q31: - | R31: 金田
B32: =ROW()-ROW($B$3) -> 29 | C32: 経費一覧 | E32: 電子領収書区分 | F32: 電子領収書 | G32: - | H32: - | K32: 同上 | L32: 同上 | N32: OK | O32: - | P32: - | Q32: - | R32: 金田
B33: =ROW()-ROW($B$3) -> 30 | C33: 経費一覧 | F33: 電子領収書以外 | K33: 同上 | L33: 同上 | N33: OK | O33: - | P33: - | Q33: - | R33: 金田
B34: =ROW()-ROW($B$3) -> 31 | C34: 経費一覧 | E34: 汎用マスタ | F34: コード | G34: - | H34: - | K34: 同上 | L34: 同上 | N34: OK | O34: - | P34: - | Q34: - | R34: 金田
B35: =ROW()-ROW($B$3) -> 32 | C35: 経費一覧 | F35: 名称 | K35: 同上 | L35: 同上 | N35: OK | O35: - | P35: - | Q35: - | R35: 金田
B36: =ROW()-ROW($B$3) -> 33 | C36: 経費一覧 | E36: 登録番号 | G36: - | H36: - | K36: 同上 | L36: 同上 | N36: OK | O36: - | P36: - | Q36: - | R36: 金田
B37: =ROW()-ROW($B$3) -> 34 | C37: 経費一覧 | F37: 空白検索 | G37: - | H37: - | K37: 同上 | L37: 同上 | N37: OK | O37: - | P37: - | Q37: - | R37: 金田
B38: =ROW()-ROW($B$3) -> 35 | C38: 経費一覧 | E38: 適格請求書の取り扱い | F38: あり | G38: - | H38: - | K38: 同上 | L38: 同上 | N38: OK | O38: - | P38: - | Q38: - | R38: 金田
B39: =ROW()-ROW($B$3) -> 36 | C39: 経費一覧 | F39: なし | G39: - | H39: - | K39: 同上 | L39: 同上 | N39: OK | O39: - | P39: - | Q39: - | R39: 金田
B40: =ROW()-ROW($B$3) -> 37 | C40: 経費一覧 | E40: ステータス | F40: 未申請 | G40: - | H40: - | K40: 同上 | L40: 同上 | N40: OK | O40: - | P40: - | Q40: - | R40: 金田
B41: =ROW()-ROW($B$3) -> 38 | C41: 経費一覧 | F41: 下書き保存中の申請を含める | G41: - | H41: - | K41: 同上 | L41: 同上 | N41: OK | O41: - | P41: - | Q41: - | R41: 金田
B42: =ROW()-ROW($B$3) -> 39 | C42: 経費一覧 | F42: データ化中 | G42: - | H42: - | K42: 同上 | L42: 同上 | N42: OK | O42: - | P42: - | Q42: - | R42: 金田
B43: =ROW()-ROW($B$3) -> 40 | C43: 経費一覧 | F43: データ化失敗 | G43: - | H43: - | K43: 同上 | L43: 同上 | N43: OK | O43: - | P43: - | Q43: - | R43: 本橋
B44: =ROW()-ROW($B$3) -> 41 | C44: 経費一覧 | F44: 承認待ち | G44: - | H44: - | K44: 同上 | L44: 同上 | N44: OK | O44: - | P44: - | Q44: - | R44: 金田
B45: =ROW()-ROW($B$3) -> 42 | C45: 経費一覧 | F45: 承認済み | G45: - | H45: - | K45: 同上 | L45: 同上 | N45: OK | O45: - | P45: - | Q45: - | R45: 金田
B46: =ROW()-ROW($B$3) -> 43 | C46: 経費一覧 | E46: 検索条件をリセット | K46: 検索条件をリセットを押下 | L46: 検索条件がリセットされること | N46: OK | O46: - | P46: - | Q46: - | R46: 金田
B47: =ROW()-ROW($B$3) -> 44 | C47: 経費一覧 | E47: この条件で検索 | K47: 任意の検索条件を設定してこの条件で検索を押下 | L47: 条件に基づいた検索結果が表示されること | N47: OK | O47: - | P47: - | Q47: - | R47: 金田
B48: =ROW()-ROW($B$3) -> 45 | C48: 経費一覧 | D48: 申請 | E48: 申請する | K48: 任意の経費を選択する 申請>申請するを押下する 承認フローを通して申請を送る | L48: 申請が送れること | N48: OK | O48: OK | P48: OK | Q48: OK | R48: 金田
B49: =ROW()-ROW($B$3) -> 46 | C49: 経費一覧 | E49: 申請書を下書き保存する | K49: 任意の経費を選択する 申請>申請を下書き保存するを押下 | L49: 未申請の申請が作成されること 未申請の申請詳細画面に遷移すること | N49: OK | O49: OK | P49: OK | Q49: OK | R49: 金田
B50: =ROW()-ROW($B$3) -> 47 | C50: 経費一覧 | D50: タイムスタンプ検証 | K50: タイムスタンプ検証を押下 検証を開始する 検証結果をダウンロードする | L50: 一連の動作がエラーなく動作すること タイムスタンプ検証結果の列が追加されること ファイル内容が経費と一致していること | M50: dev環境で行う | N50: OK | O50: - | P50: - | Q50: - | R50: 行田
B51: =ROW()-ROW($B$3) -> 48 | C51: 経費一覧 | D51: 表示項目設定 | E51: 表示 | K51: 表示項目設定を押下 任意の表示項目を設定する 保存を行う | L51: 設定した表示項目が経費一覧に表示されていること | M51: 表示項目の設定モーダル | N51: OK | O51: OK | P51: OK | Q51: OK | R51: 金田
B52: =ROW()-ROW($B$3) -> 49 | E52: 非表示 | K52: 表示項目設定を押下 任意の表示項目を非表示に設定する 保存を行う | L52: 設定した表示項目が経費一覧に表示されないこと | N52: OK | O52: - | P52: - | Q52: - | R52: 金田
B53: =ROW()-ROW($B$3) -> 50 | E53: 並び替え | K53: 表示項目設定を押下 任意の表示項目の順番を入れ替える 保存を行う | L53: 設定した表示項目が設定した順番で経費一覧に表示されていること | N53: OK | O53: - | P53: - | Q53: - | R53: 金田
B54: =ROW()-ROW($B$3) -> 51 | E54: 汎用マスタ | K54: 汎用マスタを新規に設定する 任意の表示項目を設定する 保存を行う | L54: 設定した汎用マスタが経費一覧に表示されていること | N54: OK | O54: - | P54: - | Q54: - | R54: 金田
B55: =ROW()-ROW($B$3) -> 52 | E55: 初期設定に戻す | K55: 表示項目設定を押下 初期設定に戻すボタンを押下する | L55: 初期設定に戻ること | N55: OK | O55: - | P55: - | Q55: - | R55: 金田
B56: =ROW()-ROW($B$3) -> 53 | C56: 経費一覧 | D56: ソート | E56: 利用日 | K56: 左記の表示項目を設定する 表示項目横の▲▼アイコンを押下する | L56: 昇順降順が切り替わること 設定に応じて表示順が変わること | N56: OK | O56: - | P56: - | Q56: - | R56: 金田
B57: =ROW()-ROW($B$3) -> 54 | C57: 経費一覧 | E57: 支払先/訪問先 | K57: 同上 | L57: 同上 | N57: OK | O57: - | P57: - | Q57: - | R57: 金田
B58: =ROW()-ROW($B$3) -> 55 | C58: 経費一覧 | E58: 金額 | K58: 同上 | L58: 同上 | N58: OK | O58: - | P58: - | Q58: - | R58: 金田
B59: =ROW()-ROW($B$3) -> 56 | C59: 経費一覧 | E59: 経費科目 | K59: 同上 | L59: 同上 | N59: OK | O59: - | P59: - | Q59: - | R59: 金田
B60: =ROW()-ROW($B$3) -> 57 | C60: 経費一覧 | E60: 所属部署 | K60: 同上 | L60: 同上 | N60: OK | O60: - | P60: - | Q60: - | R60: 金田
B61: =ROW()-ROW($B$3) -> 58 | C61: 経費一覧 | E61: 経費申請書名 | K61: 同上 | L61: 同上 | N61: OK | O61: - | P61: - | Q61: - | R61: 金田
B62: =ROW()-ROW($B$3) -> 59 | C62: 経費一覧 | E62: ステータス | K62: 同上 | L62: 同上 | N62: OK | O62: - | P62: - | Q62: - | R62: 金田
B63: =ROW()-ROW($B$3) -> 60 | C63: 経費一覧 | E63: 登録日 | K63: 同上 | L63: 同上 | N63: OK | O63: - | P63: - | Q63: - | R63: 金田
B64: =ROW()-ROW($B$3) -> 61 | C64: 経費一覧 | E64: プロジェクト | K64: 同上 | L64: 同上 | N64: OK | O64: - | P64: - | Q64: - | R64: 金田
B65: =ROW()-ROW($B$3) -> 62 | C65: 経費一覧 | D65: 表示件数 | K65: 表示件数を押下する 任意の件数に変更する | L65: 表示件数が切り替わること | N65: OK | O65: - | P65: - | Q65: - | R65: 金田
B66: =ROW()-ROW($B$3) -> 63 | C66: 経費一覧 | D66: ページネーション | E66: ページ指定 | K66: 任意のページを押下する | L66: 指定したページに移動すること | N66: OK | O66: - | P66: - | Q66: - | R66: 金田
B67: =ROW()-ROW($B$3) -> 64 | C67: 経費一覧 | E67: > | K67: >を押下する | L67: 指定したページに移動すること | N67: OK | O67: - | P67: - | Q67: - | R67: 金田
B68: =ROW()-ROW($B$3) -> 65 | C68: 経費一覧 | E68: >> | K68: >>を押下する | L68: 最後尾のページに移動すること | N68: OK | O68: - | P68: - | Q68: - | R68: 金田
B69: =ROW()-ROW($B$3) -> 66 | C69: 経費一覧 | E69: < | K69: <を押下する | L69: 指定したページに移動すること | N69: OK | O69: - | P69: - | Q69: - | R69: 金田
B70: =ROW()-ROW($B$3) -> 67 | C70: 経費一覧 | E70: << | K70: <<を押下する | L70: 先頭のページに移動すること | N70: OK | O70: - | P70: - | Q70: - | R70: 金田
B71: =ROW()-ROW($B$3) -> 68 | C71: 経費一覧 | D71: 経費一覧の表示項目 | E71: アラート | F71: タイムスタンプ | K71: 左記の表示項目を設定する タイムスタンプが押された経費の表示項目を確認する アイコンをマウスオーバーする | L71: タイムスタンプのアイコンが表示されること マウスオーバーすると設定に応じて以下が表示されること 「表面/裏面,ver.日付.日時」 | M71: dev環境で行う | N71: OK | O71: - | P71: - | Q71: - | R71: 行田 | S71: タイムスタンプが付与中のまま動かない
B72: =ROW()-ROW($B$3) -> 69 | C72: 経費一覧 | F72: 警告アラート | K72: 左記の表示項目を設定する 警告アラートの条件を満たした経費の表示項目を確認する アイコンをマウスオーバーする | L72: 警告アラートのアイコンが表示されること マウスオーバーすると警告の内容が表示されること | N72: OK | O72: OK | P72: OK | Q72: OK | R72: 金田
B73: =ROW()-ROW($B$3) -> 70 | C73: 経費一覧 | F73: 申請不可アラート | K73: 左記の表示項目を設定する 申請不可アラートの条件を満たした経費の表示項目を確認する アイコンをマウスオーバーする | L73: 申請不可アラートのアイコンが表示されること マウスオーバーすると申請不可である理由が表示されること | N73: OK | O73: OK | P73: OK | Q73: OK | R73: 金田
B74: =ROW()-ROW($B$3) -> 71 | C74: 経費一覧 | F74: なし | K74: 左記の表示項目を設定する アラートの条件を満たさない経費を設定して確認する | L74: アラートアイコンが何も表示されていないこと | N74: OK | O74: OK | P74: OK | Q74: OK | R74: 金田
B75: =ROW()-ROW($B$3) -> 72 | C75: 経費一覧 | E75: 利用日 | F75: 任意の日付 | K75: 左記の表示項目を設定する 経費に任意の日付を設定する 経費一覧の表示項目を確認する | L75: 任意の日付が表示されること | N75: OK | O75: - | P75: - | Q75: - | R75: 金田
B76: =ROW()-ROW($B$3) -> 73 | C76: 経費一覧 | E76: ラベル | F76: サムネイル画像 | K76: 左記の表示項目を設定する 左記の条件を満たす経費を作成する 経費一覧の表示項目を確認する アイコンをマウスオーバーする | L76: 該当のアイコンが表示されること マウスオーバーすると経費に設定した領収書画像のサムネイル画像が表示されること | N76: OK | O76: OK | P76: OK | Q76: OK | R76: 金田
B77: =ROW()-ROW($B$3) -> 74 | C77: 経費一覧 | F77: 自動入力された経費 | K77: 同上 | L77: 該当のアイコンが表示されること マウスオーバーした時内容がわかる文言が表示されること | N77: OK | O77: - | P77: - | Q77: - | R77: 金田
B78: =ROW()-ROW($B$3) -> 75 | C78: 経費一覧 | F78: 外貨を利用した経費 | K78: 同上 | L78: 同上 | N78: OK | O78: - | P78: - | Q78: - | R78: 金田
B79: =ROW()-ROW($B$3) -> 76 | C79: 経費一覧 | F79: 電子領収書 | K79: 同上 | L79: 同上 | N79: OK | O79: - | P79: - | Q79: - | R79: 金田
B80: =ROW()-ROW($B$3) -> 77 | C80: 経費一覧 | F80: 精算対象外 | K80: 同上 | L80: 同上 | N80: OK | O80: - | P80: - | Q80: - | R80: 金田
B81: =ROW()-ROW($B$3) -> 78 | C81: 経費一覧 | F81: カード連携 | K81: 同上 | L81: 同上 | M81: dev環境で行う | N81: OK | O81: - | P81: - | Q81: - | R81: 行田 | S81: 自分がカードを使えないのでどなたかお願い致します
B82: =ROW()-ROW($B$3) -> 79 | C82: 経費一覧 | F82: 参加者 | K82: 同上 | L82: 同上 | N82: OK | O82: - | P82: - | Q82: - | R82: 金田
B83: =ROW()-ROW($B$3) -> 80 | C83: 経費一覧 | F83: メモ | K83: 同上 | L83: 同上 | N83: OK | O83: - | P83: - | Q83: - | R83: 金田
B84: =ROW()-ROW($B$3) -> 81 | C84: 経費一覧 | F84: タイムスタンプ付与失敗 | K84: 領収書画像でタイムスタンプの付与に失敗した経費を用意する 経費一覧の表示項目を確認する アイコンをマウスオーバーする | L84: 同上 | M84: dev環境で行う | N84: OK | O84: - | P84: - | Q84: - | R84: 行田 | S84: タイムスタンプが付与中のまま動かない
B85: =ROW()-ROW($B$3) -> 82 | C85: 経費一覧 | E85: 電子領収書 | F85: チェック | K85: 左記の表示項目を設定する 経費に左記の設定を行う 経費一覧で該当の経費の表示項目を確認する | L85: 左記の表示項目が一覧に表示されること | N85: OK | O85: - | P85: - | Q85: - | R85: 金田
B86: =ROW()-ROW($B$3) -> 83 | C86: 経費一覧 | E86: 支払先/訪問先 | F86: 任意の設定 | K86: 同上 | L86: 同上 | N86: OK | O86: - | P86: - | Q86: - | R86: 金田
B87: =ROW()-ROW($B$3) -> 84 | C87: 経費一覧 | E87: 金額 | F87: 任意の設定 | K87: 同上 | L87: 同上 | N87: OK | O87: - | P87: - | Q87: - | R87: 金田
B88: =ROW()-ROW($B$3) -> 85 | C88: 経費一覧 | E88: 経費科目 | F88: 任意の設定 | K88: 同上 | L88: 同上 | N88: OK | O88: - | P88: - | Q88: - | R88: 金田
B89: =ROW()-ROW($B$3) -> 86 | C89: 経費一覧 | E89: 税区分 | F89: 任意の設定 | K89: 同上 | L89: 同上 | N89: OK | O89: - | P89: - | Q89: - | R89: 金田
B90: =ROW()-ROW($B$3) -> 87 | C90: 経費一覧 | E90: 所属部署 | F90: 任意の設定 | K90: 同上 | L90: 同上 | N90: OK | O90: - | P90: - | Q90: - | R90: 金田
B91: =ROW()-ROW($B$3) -> 88 | C91: 経費一覧 | E91: 費用負担部署 | F91: 任意の設定 | K91: 同上 | L91: 同上 | N91: OK | O91: - | P91: - | Q91: - | R91: 金田
B92: =ROW()-ROW($B$3) -> 89 | C92: 経費一覧 | E92: 経費申請書名 | F92: 任意の設定 | K92: 同上 | L92: 同上 | N92: OK | O92: - | P92: - | Q92: - | R92: 金田
B93: =ROW()-ROW($B$3) -> 90 | C93: 経費一覧 | E93: ステータス | F93: 未申請 | K93: 同上 | L93: 同上 | N93: OK | O93: - | P93: - | Q93: - | R93: 金田
B94: =ROW()-ROW($B$3) -> 91 | C94: 経費一覧 | F94: データ化中 | K94: 同上 | L94: 同上 | N94: OK | O94: - | P94: - | Q94: - | R94: 金田
B95: =ROW()-ROW($B$3) -> 92 | C95: 経費一覧 | F95: データ化失敗 | K95: 同上 | L95: 同上 | N95: OK | O95: - | P95: - | Q95: - | R95: 本橋 | S95: ESに画像が出て来ない
B96: =ROW()-ROW($B$3) -> 93 | C96: 経費一覧 | F96: 承認待ち | K96: 同上 | L96: 同上 | N96: OK | O96: - | P96: - | Q96: - | R96: 金田 | S96: 「申請済み」で表示される（本番も）
B97: =ROW()-ROW($B$3) -> 94 | C97: 経費一覧 | F97: 承認済み | K97: 同上 | L97: 同上 | N97: OK | O97: - | P97: - | Q97: - | R97: 金田 | S97: 「申請済み」で表示される（本番も）
B98: =ROW()-ROW($B$3) -> 95 | C98: 経費一覧 | E98: 登録日 | K98: 同上 | L98: 同上 | N98: OK | O98: - | P98: - | Q98: - | R98: 金田
B99: =ROW()-ROW($B$3) -> 96 | C99: 経費一覧 | E99: 登録番号 | F99: 任意の設定 | K99: 同上 | L99: 同上 | N99: OK | O99: - | P99: - | Q99: - | R99: 金田
B100: =ROW()-ROW($B$3) -> 97 | C100: 経費一覧 | E100: 適格請求書 | F100: チェック | K100: 同上 | L100: 同上 | N100: OK | O100: - | P100: - | Q100: - | R100: 金田
B101: =ROW()-ROW($B$3) -> 98 | C101: 経費一覧 | E101: 交通費支払先 | F101: 任意の設定 | K101: 同上 | L101: 同上 | N101: OK | O101: - | P101: - | Q101: - | R101: 金田
...

Sheet カード明細
N2: Chrome | O2: Win11/ Edge | P2: Win11/ Firefox | Q2: Win11/ Safari
B3: No | C3: 画面 | D3: 確認対象 | E3: 詳細 | K3: テスト実行手順 | L3: 期待値 | M3: 備考 | N3: TK+TI+TD | O3: TK+TI+TD | P3: TK単体 | Q3: TK単体 | R3: 実行者 | S3: 実行備考 | T3: 起票JIRA No
B4: =ROW()-ROW($B$3) -> 1 | C4: カード明細 | D4: 連携カード・サービス一覧 | E4: 表示件数 | K4: 1.連携口座・カード一覧を開く 2.カード一覧の表示件数を変更する | L4: 任意の表示件数に変更できること | N4: OK | O4: OK | P4: - | Q4: - | R4: 北川
B5: =ROW()-ROW($B$3) -> 2 | C5: カード明細 | D5: 連携カード・サービス一覧 | E5: ページネーション | F5: ページ指定 | K5: 任意のページを押下する | L5: 指定したページに移動すること | N5: OK | O5: - | P5: - | Q5: - | R5: 北川
B6: =ROW()-ROW($B$3) -> 3 | C6: カード明細 | D6: 連携カード・サービス一覧 | F6: > | K6: >を押下する | L6: 指定したページに移動すること | N6: OK | O6: - | P6: - | Q6: - | R6: 北川
B7: =ROW()-ROW($B$3) -> 4 | C7: カード明細 | D7: 連携カード・サービス一覧 | F7: >> | K7: >>を押下する | L7: 最後尾のページに移動すること | N7: OK | O7: - | P7: - | Q7: - | R7: 北川
B8: =ROW()-ROW($B$3) -> 5 | C8: カード明細 | D8: 連携カード・サービス一覧 | F8: < | K8: <を押下する | L8: 指定したページに移動すること | N8: OK | O8: - | P8: - | Q8: - | R8: 北川
B9: =ROW()-ROW($B$3) -> 6 | C9: カード明細 | D9: 連携カード・サービス一覧 | F9: << | K9: <<を押下する | L9: 先頭のページに移動すること | N9: OK | O9: - | P9: - | Q9: - | R9: 北川
B10: =ROW()-ROW($B$3) -> 7 | C10: カード明細 | D10: 連携カード・サービス一覧 | E10: 名前 | K10: 任意のカードの名前を押下する 編集する | L10: 編集できることを確認 | N10: OK | O10: - | P10: - | Q10: - | R10: 北川
B11: =ROW()-ROW($B$3) -> 8 | C11: カード明細 | D11: 連携カード・サービス一覧 | E11: 保存 | K11: 任意のカードの名前を押下する 保存する | L11: 任意のカードの名称が変更できること | N11: OK | O11: - | P11: - | Q11: - | R11: 北川
B12: =ROW()-ROW($B$3) -> 9 | C12: カード明細 | D12: 連携カード・サービス一覧 | E12: 編集 | K12: 任意のカードの編集アイコンを押下する | L12: 任意のカードの編集画面に遷移すること | N12: OK | O12: - | P12: - | Q12: - | R12: 北川
B13: =ROW()-ROW($B$3) -> 10 | C13: カード明細 | D13: 連携カード・サービス一覧 | E13: 削除 | K13: 任意のカードの削除アイコンを押下する | L13: 任意のカードが削除されること | N13: OK | O13: - | P13: - | Q13: - | R13: 北川
B14: =ROW()-ROW($B$3) -> 11 | C14: カード明細 | D14: 連携カード・サービス一覧 | E14: 再取得 | K14: 任意のカードの再取得アイコンを押下する | L14: カードの情報が再取得されること 最終更新の横の日付時間が更新されること | N14: OK | O14: - | P14: - | Q14: - | R14: 北川 | S14: 要カードアカウント 交通系IC（物理）では不可
B15: =ROW()-ROW($B$3) -> 12 | C15: カード明細 | D15: 連携カード・サービス一覧 | E15: 最終更新日 | K15: 利用履歴の取得に成功したカードの最終更新日を確認する | L15: 最終更新日が記載されていること | N15: OK | O15: - | P15: - | Q15: - | R15: 北川
B16: =ROW()-ROW($B$3) -> 13 | C16: カード明細 | D16: 連携カード・サービス一覧 | E16: アラート | F16: 警告アイコン | K16: 連携口座・カードのログインに失敗する アラートアイコンを確認する アイコンにマウスオーバーする | L16: 該当のアラートアイコンが表示されること 「ログインに失敗しました」の文字が表示されること ログインに成功するとアイコンが消えること | N16: OK | O16: OK | P16: - | Q16: - | R16: 北川 | S16: 要カードアカウント
B17: =ROW()-ROW($B$3) -> 14 | C17: カード明細 | D17: 連携カード・サービス一覧 | F17: お知らせアイコン | K17: 連携口座・カードの画像認証に失敗する アラートアイコンを確認する アイコンにマウスオーバーする | L17: 該当のアラートアイコンが表示されること 「一定時間内に画像認証に完了しませんでした。再取得するともう一度画像認証を行うことができます」の文字が表示されること 画像認証に成功するとアイコンが消えること | N17: OK | O17: OK | P17: - | Q17: - | R17: 北川
B18: =ROW()-ROW($B$3) -> 15 | C18: カード明細 | D18: 連携カード・サービス一覧 | F18: 取得中アイコン | K18: 連携口座・カードを登録して利用履歴を取得するまでにアイコンを確認する アイコンにマウスオーバーする | L18: 該当のアイコンが表示されること 「ただいま取得中です」が表示されること | N18: OK | O18: OK | P18: - | Q18: - | R18: 北川
B19: =ROW()-ROW($B$3) -> 16 | C19: カード明細 | D19: 利用履歴 | E19: 経費を登録（上画面） | F19: 経費 | G19: 経費科目 | K19: 1.任意の経費履歴を選択し、経費登録モーダルを開く 2.左記の項目を編集する 3.経費を作成する 4.左記の項目を確認する | L19: カードの利用履歴を反映した経費が作成されること 左記の編集した編集した項目が反映されていること | M19: 経費登録すると、登録に使用した内容は利用履歴から削除される | N19: OK | O19: - | P19: - | Q19: - | R19: 北川 | S19: 利用履歴を用意できる実アカウントが必要 今回はVEC実施時のテナントとダミーデータを使用
B20: =ROW()-ROW($B$3) -> 17 | C20: カード明細 | D20: 利用履歴 | F20: 経費 | G20: 事前申請名 | K20: 同上 | L20: 同上 | N20: OK | O20: - | P20: - | Q20: - | R20: 北川
B21: =ROW()-ROW($B$3) -> 18 | C21: カード明細 | D21: 利用履歴 | F21: 経費 | G21: プロジェクト | K21: 同上 | L21: 同上 | N21: OK | O21: - | P21: - | Q21: - | R21: 北川
B22: =ROW()-ROW($B$3) -> 19 | C22: カード明細 | D22: 利用履歴 | F22: 経費 | G22: 所属部署 | K22: 同上 | L22: 同上 | N22: OK | O22: - | P22: - | Q22: - | R22: 北川
B23: =ROW()-ROW($B$3) -> 20 | C23: カード明細 | D23: 利用履歴 | F23: 経費 | G23: 費用負担部署 | K23: 同上 | L23: 同上 | N23: OK | O23: - | P23: - | Q23: - | R23: 北川
B24: =ROW()-ROW($B$3) -> 21 | C24: カード明細 | D24: 利用履歴 | F24: 経費 | G24: メモ | K24: 同上 | L24: 同上 | N24: OK | O24: - | P24: - | Q24: - | R24: 北川
B25: =ROW()-ROW($B$3) -> 22 | C25: カード明細 | D25: 利用履歴 | F25: 交通費 | G25: 経費科目 | K25: 同上 | L25: 同上 | N25: OK | O25: - | P25: - | Q25: - | R25: 北川
B26: =ROW()-ROW($B$3) -> 23 | C26: カード明細 | D26: 利用履歴 | F26: 交通費 | G26: 事前申請名 | K26: 同上 | L26: 同上 | N26: OK | O26: - | P26: - | Q26: - | R26: 北川
B27: =ROW()-ROW($B$3) -> 24 | C27: カード明細 | D27: 利用履歴 | F27: 交通費 | G27: プロジェクト | K27: 同上 | L27: 同上 | N27: OK | O27: - | P27: - | Q27: - | R27: 北川
B28: =ROW()-ROW($B$3) -> 25 | C28: カード明細 | D28: 利用履歴 | F28: 交通費 | G28: 所属部署 | K28: 同上 | L28: 同上 | N28: OK | O28: - | P28: - | Q28: - | R28: 北川
B29: =ROW()-ROW($B$3) -> 26 | C29: カード明細 | D29: 利用履歴 | F29: 交通費 | G29: 費用負担部署 | K29: 同上 | L29: 同上 | N29: OK | O29: - | P29: - | Q29: - | R29: 北川
B30: =ROW()-ROW($B$3) -> 27 | C30: カード明細 | D30: 利用履歴 | F30: 交通費 | G30: メモ | K30: 同上 | L30: 同上 | N30: OK | O30: - | P30: - | Q30: - | R30: 北川
B31: =ROW()-ROW($B$3) -> 28 | C31: カード明細 | D31: 利用履歴 | E31: 履歴を削除（上画面） | K31: 選択した履歴を削除する | L31: 選択した履歴が削除されること | N31: OK | O31: - | P31: - | Q31: - | R31: 北川
B32: =ROW()-ROW($B$3) -> 29 | C32: カード明細 | D32: 利用履歴 | E32: 経費を登録（画面右） | F32: 経費 | G32: 経費科目 | K32: 1.任意の交通費履歴を選択し、経費登録モーダルを開く 2.左記の項目を編集する 3.経費を作成する 4.左記の項目を確認する | L32: カードの利用履歴を反映した経費が作成されること 左記の編集した編集した項目が反映されていること | N32: OK | O32: - | P32: - | Q32: - | R32: 北川
B33: =ROW()-ROW($B$3) -> 30 | C33: カード明細 | D33: 利用履歴 | F33: 経費 | G33: 事前申請名 | K33: 同上 | L33: 同上 | N33: OK | O33: - | P33: - | Q33: - | R33: 北川
B34: =ROW()-ROW($B$3) -> 31 | C34: カード明細 | D34: 利用履歴 | F34: 経費 | G34: プロジェクト | K34: 同上 | L34: 同上 | N34: OK | O34: - | P34: - | Q34: - | R34: 北川
B35: =ROW()-ROW($B$3) -> 32 | C35: カード明細 | D35: 利用履歴 | F35: 経費 | G35: 所属部署 | K35: 同上 | L35: 同上 | N35: OK | O35: - | P35: - | Q35: - | R35: 北川
B36: =ROW()-ROW($B$3) -> 33 | C36: カード明細 | D36: 利用履歴 | F36: 経費 | G36: 費用負担部署 | K36: 同上 | L36: 同上 | N36: OK | O36: - | P36: - | Q36: - | R36: 北川
B37: =ROW()-ROW($B$3) -> 34 | C37: カード明細 | D37: 利用履歴 | F37: 経費 | G37: メモ | K37: 同上 | L37: 同上 | N37: OK | O37: - | P37: - | Q37: - | R37: 北川
B38: =ROW()-ROW($B$3) -> 35 | C38: カード明細 | D38: 利用履歴 | F38: 交通費 | G38: 経費科目 | K38: 同上 | L38: 同上 | N38: OK | O38: - | P38: - | Q38: - | R38: 北川
B39: =ROW()-ROW($B$3) -> 36 | C39: カード明細 | D39: 利用履歴 | F39: 交通費 | G39: 事前申請名 | K39: 同上 | L39: 同上 | N39: OK | O39: - | P39: - | Q39: - | R39: 北川
B40: =ROW()-ROW($B$3) -> 37 | C40: カード明細 | D40: 利用履歴 | F40: 交通費 | G40: プロジェクト | K40: 同上 | L40: 同上 | N40: OK | O40: - | P40: - | Q40: - | R40: 北川
B41: =ROW()-ROW($B$3) -> 38 | C41: カード明細 | D41: 利用履歴 | F41: 交通費 | G41: 所属部署 | K41: 同上 | L41: 同上 | N41: OK | O41: - | P41: - | Q41: - | R41: 北川
B42: =ROW()-ROW($B$3) -> 39 | C42: カード明細 | D42: 利用履歴 | F42: 交通費 | G42: 費用負担部署 | K42: 同上 | L42: 同上 | N42: OK | O42: - | P42: - | Q42: - | R42: 北川
B43: =ROW()-ROW($B$3) -> 40 | C43: カード明細 | D43: 利用履歴 | F43: 交通費 | G43: メモ | K43: 同上 | L43: 同上 | N43: OK | O43: - | P43: - | Q43: - | R43: 北川
B44: =ROW()-ROW($B$3) -> 41 | C44: カード明細 | D44: 利用履歴 | E44: 一覧から削除（画面右） | K44: 一覧から削除されるボタンを押下 削除確認モーダルで削除 | L44: 経費履歴から削除されること | N44: OK | O44: - | P44: - | Q44: - | R44: 北川
B45: =ROW()-ROW($B$3) -> 42 | C45: カード明細 | D45: 利用履歴 | E45: ソート | F45: 利用日 | K45: ▲▼アイコンを押下 | L45: 設定した順序に並び変わること | N45: OK | O45: - | P45: - | Q45: - | R45: 北川
B46: =ROW()-ROW($B$3) -> 43 | C46: カード明細 | D46: 利用履歴 | F46: ご利用先 | K46: 同上 | L46: 同上 | N46: OK | O46: - | P46: - | Q46: - | R46: 北川
B47: =ROW()-ROW($B$3) -> 44 | C47: カード明細 | D47: 利用履歴 | F47: 経費科目 | K47: 同上 | L47: 同上 | N47: OK | O47: - | P47: - | Q47: - | R47: 北川 | S47: 経費科目のあるデータが必要となる。要請中
B48: =ROW()-ROW($B$3) -> 45 | C48: カード明細 | D48: 利用履歴 | F48: 金額 | K48: 同上 | L48: 同上 | N48: OK | O48: - | P48: - | Q48: - | R48: 北川
B49: =ROW()-ROW($B$3) -> 46 | C49: カード明細 | D49: 利用履歴 | E49: 任意のタブ | K49: 任意のタブを押下 | L49: 任意の表示に切り替わること | N49: OK | O49: - | P49: - | Q49: - | R49: 北川
B50: =ROW()-ROW($B$3) -> 47 | C50: カード明細 | D50: 利用履歴 | E50: ページネーション | F50: ページ指定 | K50: 任意のページを押下する | L50: 指定したページに移動すること | N50: OK | O50: - | P50: - | Q50: - | R50: 北川
B51: =ROW()-ROW($B$3) -> 48 | C51: カード明細 | D51: 利用履歴 | F51: > | K51: >を押下する | L51: 指定したページに移動すること | N51: OK | O51: - | P51: - | Q51: - | R51: 北川
B52: =ROW()-ROW($B$3) -> 49 | C52: カード明細 | D52: 利用履歴 | F52: >> | K52: >>を押下する | L52: 最後尾のページに移動すること | N52: OK | O52: - | P52: - | Q52: - | R52: 北川 | S52: 合計51件以上必要となる。要請中
B53: =ROW()-ROW($B$3) -> 50 | C53: カード明細 | D53: 利用履歴 | F53: < | K53: <を押下する | L53: 指定したページに移動すること | N53: OK | O53: - | P53: - | Q53: - | R53: 北川
B54: =ROW()-ROW($B$3) -> 51 | C54: カード明細 | D54: 利用履歴 | F54: << | K54: <<を押下する | L54: 先頭のページに移動すること | N54: OK | O54: - | P54: - | Q54: - | R54: 北川 | S54: 合計51件以上必要となる。要請中
B55: =ROW()-ROW($B$3) -> 52 | C55: カード明細 | D55: 連携カード・サービスを登録する一覧画面 | E55: すべて | K55: 1.カード明細>連携口座・カードを追加する>連携口座・カードを登録する画面を開く 2.左記のタブを押下する | L55: タブが切り替わること | N55: OK | O55: - | P55: - | Q55: - | R55: 北川
B56: =ROW()-ROW($B$3) -> 53 | C56: カード明細 | D56: 連携カード・サービスを登録する画面 | E56: カード | K56: 同上 | L56: タブが切り替わること | N56: OK | O56: - | P56: - | Q56: - | R56: 北川
B57: =ROW()-ROW($B$3) -> 54 | C57: カード明細 | D57: 連携カード・サービスを登録する画面 | E57: 電子マネー | K57: 同上 | L57: タブが切り替わること | N57: OK | O57: - | P57: - | Q57: - | R57: 北川
B58: =ROW()-ROW($B$3) -> 55 | C58: カード明細 | D58: 連携カード・サービスを登録する画面 | E58: レンタル | K58: 同上 | L58: タブが切り替わること | N58: OK | O58: - | P58: - | Q58: - | R58: 北川
B59: =ROW()-ROW($B$3) -> 56 | C59: カード明細 | D59: 連携カード・サービスを登録する画面 | E59: カードサービス | K59: 同上 | L59: タブが切り替わること | N59: OK | O59: - | P59: - | Q59: - | R59: 北川
B60: =ROW()-ROW($B$3) -> 57 | C60: カード明細 | D60: 連携カード・サービスを登録する画面 | E60: 任意のカード | K60: 2.任意のカードを押下する | L60: 任意のカードの登録画面に遷移すること | N60: OK | O60: - | P60: - | Q60: - | R60: 北川
B61: =ROW()-ROW($B$3) -> 58 | C61: カード明細 | D61: 連携カード・サービスを登録する画面 | E61: 新規登録画面 | F61: メールアドレス | K61: 1.カード明細>連携口座・カードを追加する>連携口座・カードを登録する>カード登録する画面(モバイルsuica)を開く 2.左記の項目を編集する | L61: 編集できることを確認 | N61: OK | O61: - | P61: - | Q61: - | R61: 北川
B62: =ROW()-ROW($B$3) -> 59 | C62: カード明細 | D62: 連携カード・サービスを登録する画面 | F62: パスワード | K62: 同上 | L62: 編集できることを確認 | N62: OK | O62: - | P62: - | Q62: - | R62: 北川
B63: =ROW()-ROW($B$3) -> 60 | C63: カード明細 | D63: 連携カード・サービスを登録する画面 | F63: suica番号 | K63: 同上 | L63: 編集できることを確認 | N63: OK | O63: - | P63: - | Q63: - | R63: 北川
B64: =ROW()-ROW($B$3) -> 61 | C64: カード明細 | D64: 連携カード・サービスを登録する画面 | F64: 精算対象外として登録 | K64: 同上 | L64: 編集できることを確認 | N64: OK | O64: - | P64: - | Q64: - | R64: 北川
B65: =ROW()-ROW($B$3) -> 62 | C65: カード明細 | D65: 連携カード・サービスを登録する画面 | F65: 経費登録した明細を自動入力経費に統合する | K65: 同上 | L65: 編集できることを確認 | N65: OK | O65: - | P65: - | Q65: - | R65: 北川
B66: =ROW()-ROW($B$3) -> 63 | C66: カード明細 | D66: 連携カード・サービスを登録する画面 | F66: 明細の経費登録を自動で行う | K66: 同上 | L66: 編集できることを確認 | N66: OK | O66: - | P66: - | Q66: - | R66: 北川
B67: =ROW()-ROW($B$3) -> 64 | C67: カード明細 | D67: 連携カード・サービスを登録する画面 | F67: 物販の明細を登録しない | K67: 同上 | L67: 編集できることを確認 | N67: OK | O67: - | P67: - | Q67: - | R67: 北川
B68: =ROW()-ROW($B$3) -> 65 | C68: カード明細 | D68: 連携カード・サービスを登録する画面 | F68: 経費登録時の経費科目 | K68: 同上 | L68: 編集できることを確認 | N68: OK | O68: - | P68: - | Q68: - | R68: 北川
B69: =ROW()-ROW($B$3) -> 66 | C69: カード明細 | D69: 連携カード・サービスを登録する画面 | F69: 経費登録時の費用負担部署 | K69: 同上 | L69: 編集できることを確認 | N69: OK | O69: - | P69: - | Q69: - | R69: 北川
B70: =ROW()-ROW($B$3) -> 67 | C70: カード明細 | D70: 連携カード・サービスを登録する画面 | F70: 経費登録時のプロジェクト | K70: 同上 | L70: 編集できることを確認 | N70: OK | O70: - | P70: - | Q70: - | R70: 北川
B71: =ROW()-ROW($B$3) -> 68 | C71: カード明細 | D71: 連携カード・サービスを登録する画面 | F71: 経費登録時のメモ欄テンプレート | K71: 同上 | L71: 編集できることを確認 | N71: OK | O71: - | P71: - | Q71: - | R71: 北川
B72: =ROW()-ROW($B$3) -> 69 | C72: カード明細 | D72: 連携カード・サービスを登録する画面 | F72: 明細の経費登録を自動で行う | K72: 同上 | L72: 編集できることを確認 | N72: OK | O72: - | P72: - | Q72: - | R72: 北川
B73: =ROW()-ROW($B$3) -> 70 | C73: カード明細 | D73: 連携カード・サービスを登録する画面 | F73: 物販の明細を登録しない | K73: 同上 | L73: 編集できることを確認 | N73: OK | O73: - | P73: - | Q73: - | R73: 北川
B74: =ROW()-ROW($B$3) -> 71 | C74: カード明細 | D74: 連携カード・サービスを登録する画面 | F74: 登録する | K74: 登録ボタンを押下する | L74: 任意の設定でカードを登録できること 登録後、編集画面に設定が反映されていること | N74: OK | O74: - | P74: - | Q74: - | R74: 北川
B75: =ROW()-ROW($B$3) -> 72 | C75: カード明細 | D75: 連携カード・サービス / 認証情報編集画面 | E75: メールアドレス | K75: 1.カード明細>連携口座・カード / 認証情報編集を開く 2.左記の項目を編集する | L75: 編集できることを確認 | M75: カードの種類ごとに画面が異なる 任意のカードで確認すること | N75: OK | O75: - | P75: - | Q75: - | R75: 北川
B76: =ROW()-ROW($B$3) -> 73 | C76: カード明細 | D76: 連携カード・サービス / 認証情報編集画面 | E76: パスワード | K76: 同上 | L76: 編集できることを確認 | N76: OK | O76: - | P76: - | Q76: - | R76: 北川
B77: =ROW()-ROW($B$3) -> 74 | C77: カード明細 | D77: 連携カード・サービス / 認証情報編集画面 | E77: 更新する | F77: 成功 | K77: 該当のカードにログインできる正しいメールアドレスとパスワードを入力する 更新するボタンを押下する | L77: ログインしなおし、再度カードの利用履歴が取得されること | N77: OK | O77: - | P77: - | Q77: - | R77: 本橋 | S77: 実アカウントが必要
B78: =ROW()-ROW($B$3) -> 75 | C78: カード明細 | D78: 連携カード・サービス / 認証情報編集画面 | F78: 失敗 | K78: 該当のカードにログインできない間違ったメールアドレスとパスワードを入力する 更新するボタンを押下する | L78: ログインに失敗し、一覧にアラートアイコンが表示されること | N78: OK | O78: - | P78: - | Q78: - | R78: 北川
B79: =ROW()-ROW($B$3) -> 76 | C79: カード明細 | D79: 連携カード・サービス / 認証情報編集画面 | E79: 精算対象外として登録 | F79: チェック | K79: 1.カード明細>連携口座・カード / 認証情報編集を開く 2.左記の項目を編集する 3.該当のカードで経費を登録する | L79: 編集できることを確認 精算対象外として登録されること | N79: OK | O79: - | P79: - | Q79: - | R79: 北川
B80: =ROW()-ROW($B$3) -> 77 | C80: カード明細 | D80: 連携カード・サービス / 認証情報編集画面 | F80: オフ | K80: 同上 | L80: 編集できることを確認 精算対象外として登録されないこと | N80: OK | O80: - | P80: - | Q80: - | R80: 北川
B81: =ROW()-ROW($B$3) -> 78 | C81: カード明細 | D81: 連携カード・サービス / 認証情報編集画面 | E81: 経費登録した明細を自動入力経費に統合する | F81: チェック | K81: 同上 | L81: 編集できることを確認 経費登録した明細が自動入力経費と統合されること | N81: OK | O81: - | P81: - | Q81: - | R81: 北川
B82: =ROW()-ROW($B$3) -> 79 | C82: カード明細 | D82: 連携カード・サービス / 認証情報編集画面 | F82: オフ | K82: 同上 | L82: 編集できることを確認 経費登録した明細が自動入力経費と統合されないこと | N82: OK | O82: - | P82: - | Q82: - | R82: 北川
B83: =ROW()-ROW($B$3) -> 80 | C83: カード明細 | D83: 連携カード・サービス / 認証情報編集画面 | E83: 明細の経費登録を自動で行う | F83: チェック | K83: 同上 | L83: 編集できることを確認 利用履歴を取得した際、自動で経費登録されること | N83: OK | O83: - | P83: - | Q83: - | R83: 北川
B84: =ROW()-ROW($B$3) -> 81 | C84: カード明細 | D84: 連携カード・サービス / 認証情報編集画面 | F84: オフ | K84: 同上 | L84: 編集できることを確認 利用履歴を取得した際、自動で経費登録されないこと | N84: OK | O84: - | P84: - | Q84: - | R84: 北川
B85: =ROW()-ROW($B$3) -> 82 | C85: カード明細 | D85: 連携カード・サービス / 認証情報編集画面 | E85: 物販の明細を登録しない | F85: チェック | K85: 同上 | L85: 編集できることを確認 物販の明細が登録されること | N85: OK | O85: - | P85: - | Q85: - | R85: 北川
B86: =ROW()-ROW($B$3) -> 83 | C86: カード明細 | D86: 連携カード・サービス / 認証情報編集画面 | F86: オフ | K86: 同上 | L86: 編集できることを確認 物販の明細が登録されないこと（交通費のみ登録されること） | N86: OK | O86: - | P86: - | Q86: - | R86: 北川
B87: =ROW()-ROW($B$3) -> 84 | C87: カード明細 | D87: 連携カード・サービス / 認証情報編集画面 | E87: 経費登録時の経費科目 | K87: 同上 | L87: 編集できることを確認 設定した項目が経費に反映されること | N87: OK | O87: - | P87: - | Q87: - | R87: 北川
B88: =ROW()-ROW($B$3) -> 85 | C88: カード明細 | D88: 連携カード・サービス / 認証情報編集画面 | E88: 経費登録時の費用負担部署 | K88: 同上 | L88: 同上 | N88: OK | O88: - | P88: - | Q88: - | R88: 北川
B89: =ROW()-ROW($B$3) -> 86 | C89: カード明細 | D89: 連携カード・サービス / 認証情報編集画面 | E89: 経費登録時のプロジェクト | K89: 同上 | L89: 同上 | N89: OK | O89: - | P89: - | Q89: - | R89: 北川
B90: =ROW()-ROW($B$3) -> 87 | C90: カード明細 | D90: 連携カード・サービス / 認証情報編集画面 | E90: 経費登録時のメモ欄テンプレート | K90: 同上 | L90: 同上 | N90: OK | O90: - | P90: - | Q90: - | R90: 北川
B91: =ROW()-ROW($B$3) -> 88 | C91: カード明細 | D91: 連携カード・サービス / 認証情報編集画面 | E91: 設定を更新する | K91: 設定を更新するボタンを押下する | L91: 設定が反映されることを確認 | N91: OK | O91: - | P91: - | Q91: - | R91: 北川
B92: =ROW()-ROW($B$3) -> 89 | C92: カード明細 | D92: 連携カード・サービス / 認証情報編集画面 | E92: 自動経費科目設定 | F92: 科目設定追加 | K92: 自動経費科目設定を開く 任意の条件で自動経費科目設定を追加する | L92: 自動経費科目設定モーダルが表示されること 任意の設定を追加できること | N92: 外 | O92: - | P92: - | Q92: - | R92: 北川 | S92: 追加直後に表示が反映されない →本番環境でも発生 富田(秀)：本番でも起きている事象のため、本ケースは対象外 | T92: KH-4260
B93: =ROW()-ROW($B$3) -> 90 | C93: カード明細 | D93: 連携カード・サービス / 認証情報編集画面 | F93: 設定の有効化 | G93: オン | K93: 自動経費科目設定を確認する 設定の有効化をオンにする カード明細から経費を登録する | L93: 振り分け条件を満たす利用先だったときに指定の経費科目が設定されること | N93: OK | O93: - | P93: - | Q93: - | R93: 北川
B94: =ROW()-ROW($B$3) -> 91 | C94: カード明細 | D94: 連携カード・サービス / 認証情報編集画面 | G94: オフ | K94: 自動経費科目設定を確認する 設定の有効化をオフにする カード明細から経費を登録する | L94: 振り分け条件を満たす利用先だったときに指定の経費科目が設定されないこと | N94: OK | O94: - | P94: - | Q94: - | R94: 北川
B95: =ROW()-ROW($B$3) -> 92 | C95: カード明細 | D95: 連携カード・サービス / 認証情報編集画面 | F95: 編集 | K95: 自動経費科目設定を開く 任意の条件で自動経費科目設定を編集する | L95: 自動経費科目設定モーダルが表示されること 任意の設定を編集できること | N95: OK | O95: - | P95: - | Q95: - | R95: 北川
B96: =ROW()-ROW($B$3) -> 93 | C96: カード明細 | D96: 連携カード・サービス / 認証情報編集画面 | F96: 削除 | K96: 削除ボタンを押下する | L96: 自動経費科目設定を削除できること | N96: 外 | O96: - | P96: - | Q96: - | R96: 北川 | S96: 追加直後に表示が反映されない →本番環境でも発生 富田(秀)：本番でも起きている事象のため、本ケースは対象外 | T96: KH-4260
B97: =ROW()-ROW($B$3) -> 94 | C97: カード明細 | D97: 連携カード・サービス / 認証情報編集画面 | F97: 自動経費科目設定追加画面 | G97: 振り分け条件 | K97: 科目設定追加＞自動経費科目設定を開く 振り分け条件を設定する | L97: 任意の設定が追加できること | N97: OK | O97: - | P97: - | Q97: - | R97: 北川
B98: =ROW()-ROW($B$3) -> 95 | C98: カード明細 | D98: 連携カード・サービス / 認証情報編集画面 | F98: 自動経費科目設定追加画面 | G98: 経費科目 | K98: 科目設定追加＞自動経費科目設定を開く 経費科目を設定する | L98: 任意の設定が追加できること | N98: OK | O98: - | P98: - | Q98: - | R98: 北川
B99: =ROW()-ROW($B$3) -> 96 | C99: カード明細 | D99: 連携カード・サービス / 認証情報編集画面 | F99: 自動経費科目設定編集画面 | G99: 振り分け条件 | K99: 編集ボタン＞自動経費科目設定を開く 振り分け条件を設定する | L99: 任意の設定に編集できること | N99: OK | O99: - | P99: - | Q99: - | R99: 北川
B100: =ROW()-ROW($B$3) -> 97 | C100: カード明細 | D100: 連携カード・サービス / 認証情報編集画面 | F100: 自動経費科目設定編集画面 | G100: 経費科目 | K100: 編集ボタン＞自動経費科目設定を開く 経費科目を設定する | L100: 任意の設定に編集できること | N100: OK | O100: - | P100: - | Q100: - | R100: 北川
B101: =ROW()-ROW($B$3) -> 98 | C101: カード明細 | D101: 連携カード・サービス / 認証情報編集画面（追加情報確認画面） | E101: 画像の文字 | K101: 1.カード明細でモバイルsuicaの再取得を行う 2.画像認証が求められた際に追加認証情報入力画面を開く 3.画像の文字を確認し、入力する | L101: 画像認証用の画像が表示されていること 画像の文字を編集できること | M101: ログイン時の処理として画像認証が求められる場合この画面に飛ぶ。テストでは例としてモバイルsuicaを挙げている。 | N101: OK | O101: - | P101: - | Q101: - | R101: 北川
...

Sheet 仮払
N2: Win11/ Chrome | O2: Win11/ edge | P2: Win11/ Firefox | Q2: Win11/ Safari
B3: No | C3: 画面 | D3: 確認対象 | E3: 詳細 | K3: テスト実行手順 | L3: 期待値 | M3: 備考 | N3: TK+TI+TD | O3: TK+TI+TD | P3: TK単体 | Q3: TK単体 | R3: 実行者 | S3: 実行備考 | T3: 起票JIRA No
B4: =ROW()-ROW($B$3) -> 1 | C4: 仮払一覧画面 | D4: タブ | E4: 仮払待ち | K4: 左記のタブを確認する タブを押下する | L4: タブの横に表示件数が表示されること 表示される事前申請の種類が変更されること | N4: OK | O4: OK | P4: OK | Q4: OK | R4: 行田 北川(Mac)
B5: =ROW()-ROW($B$3) -> 2 | C5: 仮払一覧画面 | E5: 未精算 | K5: 同上 | L5: 同上 | N5: OK | O5: OK | P5: OK | Q5: OK | R5: 行田 北川(Mac)
B6: =ROW()-ROW($B$3) -> 3 | C6: 仮払一覧画面 | E6: 仮払差額返金待ち | K6: 同上 | L6: 同上 | N6: OK | O6: OK | P6: OK | Q6: OK | R6: 行田 北川(Mac)
B7: =ROW()-ROW($B$3) -> 4 | C7: 仮払一覧画面 | D7: 表示件数 | K7: 表示件数を押下する 任意の件数に変更する | L7: 表示件数が切り替わること | N7: OK | O7: OK | P7: OK | Q7: OK | R7: 行田 北川(Mac)
B8: =ROW()-ROW($B$3) -> 5 | C8: 仮払一覧画面 | D8: ページネーション | E8: ページ指定 | K8: 任意のページを押下する | L8: 指定したページに移動すること | N8: OK | O8: OK | P8: OK | Q8: OK | R8: 行田 北川(Mac)
B9: =ROW()-ROW($B$3) -> 6 | C9: 仮払一覧画面 | E9: > | K9: >を押下する | L9: 指定したページに移動すること | N9: OK | O9: OK | P9: OK | Q9: OK | R9: 行田 北川(Mac)
B10: =ROW()-ROW($B$3) -> 7 | C10: 仮払一覧画面 | E10: >> | K10: >>を押下する | L10: 最後尾のページに移動すること | M10: 51件以上必要 | N10: OK | O10: OK | P10: OK | Q10: OK | R10: 行田 北川(Mac)
B11: =ROW()-ROW($B$3) -> 8 | C11: 仮払一覧画面 | E11: < | K11: <を押下する | L11: 指定したページに移動すること | N11: OK | O11: OK | P11: OK | Q11: OK | R11: 行田 北川(Mac)
B12: =ROW()-ROW($B$3) -> 9 | C12: 仮払一覧画面 | E12: << | K12: <<を押下する | L12: 先頭のページに移動すること | M12: 51件以上必要 | N12: OK | O12: OK | P12: OK | Q12: OK | R12: 行田 北川(Mac)
B13: =ROW()-ROW($B$3) -> 10 | C13: 仮払一覧画面 | D13: 表示項目 | E13: 仮払待ち | F13: 事前申請名 | K13: 左記のタブを選択する 表示される項目を確認する 任意の表示を押下し、遷移先の事前申請を確認する | L13: 左記の表示項目が表示されていること 内容が正しいこと | N13: OK | O13: OK | P13: OK | Q13: OK | R13: 行田 北川(Mac)
B14: =ROW()-ROW($B$3) -> 11 | C14: 仮払一覧画面 | F14: 申請ID | K14: 同上 | L14: 同上 | N14: OK | O14: OK | P14: OK | Q14: OK | R14: 行田 北川(Mac)
B15: =ROW()-ROW($B$3) -> 12 | C15: 仮払一覧画面 | F15: 申請者名 | K15: 同上 | L15: 同上 | N15: OK | O15: OK | P15: OK | Q15: OK | R15: 行田 北川(Mac)
B16: =ROW()-ROW($B$3) -> 13 | C16: 仮払一覧画面 | F16: 所属部署 | K16: 同上 | L16: 同上 | N16: OK | O16: OK | P16: OK | Q16: OK | R16: 行田 北川(Mac)
B17: =ROW()-ROW($B$3) -> 14 | C17: 仮払一覧画面 | F17: 仮払希望日 | K17: 同上 | L17: 同上 | N17: OK | O17: OK | P17: OK | Q17: OK | R17: 行田 北川(Mac)
B18: =ROW()-ROW($B$3) -> 15 | C18: 仮払一覧画面 | F18: 事前申請額 | K18: 同上 | L18: 同上 | N18: OK | O18: OK | P18: OK | Q18: OK | R18: 行田 北川(Mac)
B19: =ROW()-ROW($B$3) -> 16 | C19: 仮払一覧画面 | E19: 未精算 | F19: 事前申請名 | K19: 同上 | L19: 同上 | N19: OK | O19: OK | P19: OK | Q19: OK | R19: 行田 北川(Mac)
B20: =ROW()-ROW($B$3) -> 17 | C20: 仮払一覧画面 | F20: 申請ID | K20: 同上 | L20: 同上 | N20: OK | O20: OK | P20: OK | Q20: OK | R20: 行田 北川(Mac)
B21: =ROW()-ROW($B$3) -> 18 | C21: 仮払一覧画面 | F21: 申請者名 | K21: 同上 | L21: 同上 | N21: OK | O21: OK | P21: OK | Q21: OK | R21: 行田 北川(Mac)
B22: =ROW()-ROW($B$3) -> 19 | C22: 仮払一覧画面 | F22: 所属部署 | K22: 同上 | L22: 同上 | N22: OK | O22: OK | P22: OK | Q22: OK | R22: 行田 北川(Mac)
B23: =ROW()-ROW($B$3) -> 20 | C23: 仮払一覧画面 | F23: 仮払支払日 | K23: 同上 | L23: 同上 | N23: OK | O23: OK | P23: OK | Q23: OK | R23: 行田 北川(Mac)
B24: =ROW()-ROW($B$3) -> 21 | C24: 仮払一覧画面 | F24: 仮払額 | K24: 同上 | N24: OK | O24: OK | P24: OK | Q24: OK | R24: 行田 北川(Mac)
B25: =ROW()-ROW($B$3) -> 22 | C25: 仮払一覧画面 | F25: 申請状況 | K25: 同上 | L25: 同上 | N25: OK | O25: OK | P25: OK | Q25: OK | R25: 行田 北川(Mac)
B26: =ROW()-ROW($B$3) -> 23 | C26: 仮払一覧画面 | E26: 仮払差額返金待ち | F26: 事前申請名 | K26: 同上 | L26: 同上 | N26: OK | O26: OK | P26: OK | Q26: OK | R26: 行田 北川(Mac)
B27: =ROW()-ROW($B$3) -> 24 | C27: 仮払一覧画面 | F27: 申請ID | K27: 同上 | L27: 同上 | N27: OK | O27: OK | P27: OK | Q27: OK | R27: 行田 北川(Mac)
B28: =ROW()-ROW($B$3) -> 25 | C28: 仮払一覧画面 | F28: 申請者名 | K28: 同上 | L28: 同上 | N28: OK | O28: OK | P28: OK | Q28: OK | R28: 行田 北川(Mac)
B29: =ROW()-ROW($B$3) -> 26 | C29: 仮払一覧画面 | F29: 所属部署 | K29: 同上 | L29: 同上 | N29: OK | O29: OK | P29: OK | Q29: OK | R29: 行田 北川(Mac)
B30: =ROW()-ROW($B$3) -> 27 | C30: 仮払一覧画面 | F30: 最終承認日 | K30: 同上 | L30: 同上 | N30: OK | O30: OK | P30: OK | Q30: OK | R30: 行田 北川(Mac)
B31: =ROW()-ROW($B$3) -> 28 | C31: 仮払一覧画面 | F31: 返金額 | K31: 同上 | L31: 同上 | N31: OK | O31: OK | P31: OK | Q31: OK | R31: 行田 北川(Mac)
B32: =ROW()-ROW($B$3) -> 29 | C32: 仮払一覧画面 | F32: 仮払い額 | K32: 同上 | L32: 同上 | N32: OK | O32: OK | P32: OK | Q32: OK | R32: 行田 北川(Mac)
B33: =ROW()-ROW($B$3) -> 30 | C33: 仮払一覧画面 | F33: 利用額 | K33: 同上 | L33: 同上 | N33: OK | O33: OK | P33: OK | Q33: OK | R33: 行田 北川(Mac)
B34: =ROW()-ROW($B$3) -> 31 | C34: 仮払一覧画面 | F34: 源泉徴収額 | K34: 同上 | L34: 同上 | N34: OK | O34: OK | P34: OK | Q34: OK | R34: 行田 北川(Mac)

Sheet 稟議
C2: dev-td環境で実施 | N2: Win11/ Chrome | O2: Win11/ Edge | P2: Win11/ Firefox | Q2: Mac/ Safari
B3: No | C3: 画面 | D3: 確認対象 | E3: 詳細 | K3: テスト実行手順 | L3: 期待値 | M3: 備考 | N3: TK+TI+TD | O3: TI+TD | P3: TK+TI+TD | Q3: TK+TI+TD | R3: 実行者 | S3: 実行備考 | T3: 起票JIRA No
B4: =ROW()-ROW($B$3) -> 1 | C4: 稟議一覧 | D4: 発注稟議を作成する | E4: 画像なし | K4: 1.「発注稟議を作成」を押下する。 2.任意の内容を入力し「保存」を押下する。 | L4: 稟議が作成できること | N4: OK | O4: OK | P4: OK | Q4: OK | R4: 金田
B5: =ROW()-ROW($B$3) -> 2 | E5: png | K5: 1.「発注稟議を作成」を押下する。 2.左記のファイルを追加する。 3.任意の内容を入力し「保存」を押下する。 | L5: 稟議が作成できること | N5: OK | O5: OK | P5: OK | Q5: OK | R5: 金田
B6: =ROW()-ROW($B$3) -> 3 | E6: jpeg（jpg） | K6: 1.「発注稟議を作成」を押下する。 2.左記のファイルを追加する。 3.任意の内容を入力し「保存」を押下する。 | L6: 稟議が作成できること | N6: OK | O6: OK | P6: OK | Q6: OK | R6: 金田
B7: =ROW()-ROW($B$3) -> 4 | E7: pdf | K7: 1.「発注稟議を作成」を押下する。 2.左記のファイルを追加する。 3.任意の内容を入力し「保存」を押下する。 | L7: 稟議が作成できること | N7: OK | O7: OK | P7: OK | Q7: OK | R7: 金田
B8: =ROW()-ROW($B$3) -> 5 | E8: pdf（パスワード付） | K8: 1.「発注稟議を作成」を押下する。 2.左記のファイルを追加する。 3.任意の内容を入力し「保存」を押下する。 | L8: 稟議が作成できること | N8: OK | O8: OK | P8: OK | Q8: OK | R8: 金田
B9: =ROW()-ROW($B$3) -> 6 | E9: xls | K9: 1.「発注稟議を作成」を押下する。 2.左記のファイルを追加する。 3.任意の内容を入力し「保存」を押下する。 | L9: 稟議が作成できること | N9: OK | O9: OK | P9: OK | Q9: OK | R9: 金田
B10: =ROW()-ROW($B$3) -> 7 | E10: xlsx | K10: 1.「発注稟議を作成」を押下する。 2.左記のファイルを追加する。 3.任意の内容を入力し「保存」を押下する。 | L10: 稟議が作成できること | N10: OK | O10: OK | P10: OK | Q10: OK | R10: 金田
B11: =ROW()-ROW($B$3) -> 8 | E11: doc | K11: 1.「発注稟議を作成」を押下する。 2.左記のファイルを追加する。 3.任意の内容を入力し「保存」を押下する。 | L11: 稟議が作成できること | N11: OK | O11: OK | P11: OK | Q11: OK | R11: 金田
B12: =ROW()-ROW($B$3) -> 9 | E12: docx | K12: 1.「発注稟議を作成」を押下する。 2.左記のファイルを追加する。 3.任意の内容を入力し「保存」を押下する。 | L12: 稟議が作成できること | N12: OK | O12: OK | P12: OK | Q12: OK | R12: 金田
B13: =ROW()-ROW($B$3) -> 10 | E13: txt | K13: 1.「発注稟議を作成」を押下する。 2.左記のファイルを追加する。 3.任意の内容を入力し「保存」を押下する。 | L13: 稟議が作成できること | N13: OK | O13: OK | P13: OK | Q13: OK | R13: 金田
B14: =ROW()-ROW($B$3) -> 11 | E14: csv | K14: 1.「発注稟議を作成」を押下する。 2.左記のファイルを追加する。 3.任意の内容を入力し「保存」を押下する。 | L14: 稟議が作成できること | N14: OK | O14: OK | P14: OK | Q14: OK | R14: 金田
B15: =ROW()-ROW($B$3) -> 12 | E15: 100MBのファイル | K15: 1.「発注稟議を作成」を押下する。 2.左記のファイルを追加する。 3.任意の内容を入力し「保存」を押下する。 | L15: 稟議が作成できること | N15: OK | O15: OK | P15: OK | Q15: OK | R15: 金田
B16: =ROW()-ROW($B$3) -> 13 | E16: 1~10ページにファイル追加 | K16: 1.「発注稟議を作成」を押下する。 2.左記の状態にする。 3.任意の内容を入力し「保存」を押下する。 | L16: 稟議が作成できること | N16: OK | O16: OK | P16: OK | Q16: OK | R16: 金田
B17: =ROW()-ROW($B$3) -> 14 | D17: 検索条件 | E17: 稟議名 | K17: 1.左記の検索条件を設定する。 2.「指定した条件で検索」を押下する。 | L17: 条件に基づいた検索結果が表示されること | N17: OK | O17: OK | P17: OK | Q17: OK | R17: 金田
B18: =ROW()-ROW($B$3) -> 15 | E18: 取引先 | K18: 1.左記の検索条件を設定する。 2.「指定した条件で検索」を押下する。 | L18: 条件に基づいた検索結果が表示されること | N18: OK | O18: OK | P18: OK | Q18: OK | R18: 金田
B19: =ROW()-ROW($B$3) -> 16 | E19: 取引先コード | K19: 1.左記の検索条件を設定する。 2.「指定した条件で検索」を押下する。 | L19: 条件に基づいた検索結果が表示されること | N19: OK | O19: OK | P19: OK | Q19: OK | R19: 金田
B20: =ROW()-ROW($B$3) -> 17 | E20: 費用負担部署 | K20: 1.左記の検索条件を設定する。 2.「指定した条件で検索」を押下する。 | L20: 条件に基づいた検索結果が表示されること | N20: OK | O20: OK | P20: OK | Q20: OK | R20: 金田
B21: =ROW()-ROW($B$3) -> 18 | E21: プロジェクトID | K21: 1.左記の検索条件を設定する。 2.「指定した条件で検索」を押下する。 | L21: 条件に基づいた検索結果が表示されること | N21: OK | O21: OK | P21: OK | Q21: OK | R21: 金田
B22: =ROW()-ROW($B$3) -> 19 | E22: プロジェクト名 | K22: 1.左記の検索条件を設定する。 2.「指定した条件で検索」を押下する。 | L22: 条件に基づいた検索結果が表示されること | N22: OK | O22: OK | P22: OK | Q22: OK | R22: 金田
B23: =ROW()-ROW($B$3) -> 20 | E23: メモ | K23: 1.左記の検索条件を設定する。 2.「指定した条件で検索」を押下する。 | L23: 条件に基づいた検索結果が表示されること | N23: OK | O23: OK | P23: OK | Q23: OK | R23: 金田
B24: =ROW()-ROW($B$3) -> 21 | E24: 有効状態 | F24: 有効 | K24: 1.左記の検索条件を設定する。 2.「指定した条件で検索」を押下する。 | L24: 条件に基づいた検索結果が表示されること | N24: OK | O24: OK | P24: OK | Q24: OK | R24: 金田
B25: =ROW()-ROW($B$3) -> 22 | F25: 無効 | K25: 1.左記の検索条件を設定する。 2.「指定した条件で検索」を押下する。 | L25: 条件に基づいた検索結果が表示されること | N25: OK | O25: OK | P25: OK | Q25: OK | R25: 金田
B26: =ROW()-ROW($B$3) -> 23 | E26: 消化状況 | F26: 未使用 | K26: 1.左記の検索条件を設定する。 2.「指定した条件で検索」を押下する。 | L26: 条件に基づいた検索結果が表示されること | N26: OK | O26: OK | P26: OK | Q26: OK | R26: 金田
B27: =ROW()-ROW($B$3) -> 24 | E27: ステータス | F27: 承認待ち | K27: 1.左記の検索条件を設定する。 2.「指定した条件で検索」を押下する。 | L27: 条件に基づいた検索結果が表示されること | N27: OK | O27: OK | P27: OK | Q27: OK | R27: 金田
B28: =ROW()-ROW($B$3) -> 25 | F28: 未申請 | K28: 1.左記の検索条件を設定する。 2.「指定した条件で検索」を押下する。 | L28: 条件に基づいた検索結果が表示されること | N28: OK | O28: OK | P28: OK | Q28: OK | R28: 金田
B29: =ROW()-ROW($B$3) -> 26 | F29: フロー変更待ち | K29: 1.左記の検索条件を設定する。 2.「指定した条件で検索」を押下する。 | L29: 条件に基づいた検索結果が表示されること | N29: OK | O29: OK | P29: OK | Q29: OK | R29: 金田
B30: =ROW()-ROW($B$3) -> 27 | F30: 取下げ | K30: 1.左記の検索条件を設定する。 2.「指定した条件で検索」を押下する。 | L30: 条件に基づいた検索結果が表示されること | N30: OK | O30: OK | P30: OK | Q30: OK | R30: 金田
B31: =ROW()-ROW($B$3) -> 28 | F31: 差し戻し | K31: 1.左記の検索条件を設定する。 2.「指定した条件で検索」を押下する。 | L31: 条件に基づいた検索結果が表示されること | N31: OK | O31: OK | P31: OK | Q31: OK | R31: 金田
B32: =ROW()-ROW($B$3) -> 29 | F32: 承認済み | K32: 1.左記の検索条件を設定する。 2.「指定した条件で検索」を押下する。 | L32: 条件に基づいた検索結果が表示されること | N32: OK | O32: OK | P32: OK | Q32: OK | R32: 金田
B33: =ROW()-ROW($B$3) -> 30 | E33: 検索条件をリセット | K33: 検索条件をリセットを押下する。 | L33: 検索条件がリセットされること | N33: OK | O33: OK | P33: OK | Q33: OK | R33: 金田
B34: =ROW()-ROW($B$3) -> 31 | D34: 表示項目設定 | E34: 非表示 | K34: 1.任意の表示項目のチェックボックスを外す。 2.「保存」を押下する。 3.稟議一覧の表示項目を確認する。 | L34: 該当の項目が表示されていないこと | N34: OK | O34: OK | P34: OK | Q34: OK | R34: 金田
B35: =ROW()-ROW($B$3) -> 32 | E35: 表示 | K35: 1.任意の表示項目のチェックボックスを入れる。 2.「保存」を押下する。 3.稟議一覧の表示項目を確認する。 | L35: 該当の項目が表示されていること | N35: OK | O35: OK | P35: OK | Q35: OK | R35: 金田
B36: =ROW()-ROW($B$3) -> 33 | E36: 並び替え | K36: 1.モーダル右側の「^」「v」ボタンを押下し、項目の順番を変更する。 2.「保存」を押下する。 3.稟議一覧の表示項目を確認する。 | L36: 項目の順番が変更内容と一致していること | N36: OK | O36: OK | P36: OK | Q36: OK | R36: 金田
B37: =ROW()-ROW($B$3) -> 34 | E37: 初期設定に戻す | K37: 1.任意の項目表示・並び替えを行う。 2.「初期設定に戻す」を押下する。 3.「保存」を押下する。 4.稟議一覧の表示項目を確認する。 | L37: 表示項目が初期状態になっていること | N37: OK | O37: OK | P37: OK | Q37: OK | R37: 金田
B38: =ROW()-ROW($B$3) -> 35 | D38: 表示件数 | K38: 1.表示件数を押下する。 2.任意の件数を選択する。 | L38: 表示件数が変更できること | N38: OK | O38: OK | P38: OK | Q38: OK | R38: 金田
B39: =ROW()-ROW($B$3) -> 36 | D39: ページネーション | E39: ページボタン | K39: ページボタンを押下する。 | L39: 該当のページへ遷移すること | N39: OK | O39: OK | P39: OK | Q39: OK | R39: 金田
B40: =ROW()-ROW($B$3) -> 37 | E40: 「>」ボタン | K40: 「>」ボタンを押下する。 | L40: 1つ後ろのページへ遷移すること | N40: OK | O40: OK | P40: OK | Q40: OK | R40: 金田
B41: =ROW()-ROW($B$3) -> 38 | E41: 「<」ボタン | K41: 「<」ボタンを押下する。 | L41: 1つ前のページへ遷移すること | N41: OK | O41: OK | P41: OK | Q41: OK | R41: 金田
B42: =ROW()-ROW($B$3) -> 39 | E42: 「>>」ボタン | K42: 「>>」ボタンを押下する。 | L42: 1番最後のページへ遷移すること | N42: OK | O42: OK | P42: OK | Q42: OK | R42: 金田
B43: =ROW()-ROW($B$3) -> 40 | E43: 「<<」ボタン | K43: 「<<」ボタンを押下する。 | L43: 1番最初のページへ遷移すること | N43: OK | O43: OK | P43: OK | Q43: OK | R43: 金田
B44: =ROW()-ROW($B$3) -> 41 | D44: この条件でファイル出力する | K44: 1.「この条件でファイル出力する」を押下する。 2.任意の内容を入力し、ダウンロードを行う。 | L44: ファイルが作成できること | N44: 外 | O44: - | P44: - | Q44: - | R44: 中里 | S44: ファイルが作成されない（本番は問題なし） →富田(秀)：今回のビルド改善の影響ではないため、対象外とする | T44: FA-99
B45: =ROW()-ROW($B$3) -> 42 | D45: 削除 | K45: 「削除」を押下する。 | L45: 稟議が削除できること | N45: OK | O45: - | P45: - | Q45: - | R45: 中里
B46: =ROW()-ROW($B$3) -> 43 | D46: 無効 | K46: 「無効」を押下する。 | L46: 稟議を無効にできること | N46: OK | O46: - | P46: - | Q46: - | R46: 中里
B47: =ROW()-ROW($B$3) -> 44 | D47: 有効 | K47: 「有効」を押下する。 | L47: 稟議を有効できること | N47: OK | O47: - | P47: - | Q47: - | R47: 中里
B48: =ROW()-ROW($B$3) -> 45 | C48: 稟議一覧＞稟議編集 | D48: 稟議名 | K48: 1.該当項目を任意の内容へ変更する。 2.「保存」を押下する。 | L48: 入力した内容で保存されること | N48: OK | O48: OK | P48: OK | Q48: OK | R48: 金田
B49: =ROW()-ROW($B$3) -> 46 | D49: 金額 | E49: JPY | F49: プラス | K49: 1.JPYで該当の金額を入力する。 2.「保存」を押下する。 | L49: 入力した内容で保存されること | N49: OK | O49: OK | P49: OK | Q49: OK | R49: 金田
B50: =ROW()-ROW($B$3) -> 47 | F50: マイナス | K50: 1.JPYで該当の金額を入力する。 2.「保存」を押下する。 | L50: 入力した内容で保存されること | N50: OK | O50: OK | P50: OK | Q50: OK | R50: 金田
B51: =ROW()-ROW($B$3) -> 48 | F51: ゼロ | K51: 1.JPYで該当の金額を入力する。 2.「保存」を押下する。 | L51: 入力した内容で保存されること | N51: OK | O51: OK | P51: OK | Q51: OK | R51: 金田
B52: =ROW()-ROW($B$3) -> 49 | F52: 小数点 | K52: 1.JPYで該当の金額を入力する。 2.「保存」を押下する。 | L52: 小数点以下が切り捨てられて保存されること | N52: OK | O52: OK | P52: OK | Q52: OK | R52: 金田 | S52: 小数点以下は、切り捨てられることを確認
B53: =ROW()-ROW($B$3) -> 50 | D53: 詳細 | K53: 1.該当項目を任意の内容へ変更する。 2.「保存」を押下する。 | L53: 入力した内容で保存されること | N53: OK | O53: OK | P53: OK | Q53: OK | R53: 金田
B54: =ROW()-ROW($B$3) -> 51 | D54: 取引先名 | K54: 1.該当項目を任意の内容へ変更する。 2.「保存」を押下する。 | L54: 入力した内容で保存されること | N54: OK | O54: OK | P54: OK | Q54: OK | R54: 金田
B55: =ROW()-ROW($B$3) -> 52 | D55: 取引先担当者 | K55: 1.該当項目を任意の内容へ変更する。 2.「保存」を押下する。 | L55: 入力した内容で保存されること | N55: OK | O55: OK | P55: OK | Q55: OK | R55: 金田
B56: =ROW()-ROW($B$3) -> 53 | D56: 借方請求明細科目 | K56: 1.該当項目を任意の内容へ変更する。 2.「保存」を押下する。 | L56: 入力した内容で保存されること | N56: OK | O56: OK | P56: OK | Q56: OK | R56: 金田
B57: =ROW()-ROW($B$3) -> 54 | D57: 費用負担部署 | K57: 1.該当項目を任意の内容へ変更する。 2.「保存」を押下する。 | L57: 入力した内容で保存されること | N57: OK | O57: OK | P57: OK | Q57: OK | R57: 金田
B58: =ROW()-ROW($B$3) -> 55 | D58: プロジェクト | K58: 1.該当項目を任意の内容へ変更する。 2.「保存」を押下する。 | L58: 入力した内容で保存されること | N58: OK | O58: OK | P58: OK | Q58: OK | R58: 金田
B59: =ROW()-ROW($B$3) -> 56 | D59: 明細メモ | K59: 1.該当項目を任意の内容へ変更する。 2.「保存」を押下する。 | L59: 入力した内容で保存されること | N59: OK | O59: OK | P59: OK | Q59: OK | R59: 金田
B60: =ROW()-ROW($B$3) -> 57 | D60: PDFビューア | E60: TOKIUMビューア | K60: 1.pdfをアップロードする。 2.ビューアの切り替えを行う。 | L60: ビューアが切り替えられること 画像の回転、拡大、ページ送りといった操作ができること | N60: OK | O60: OK | P60: OK | Q60: OK | R60: 金田
B61: =ROW()-ROW($B$3) -> 58 | E61: ブラウザ標準ビューア | K61: 1.pdfをアップロードする。 2.ビューアの切り替えを行う。 | L61: ビューアが切り替えられること 画像の回転、拡大、ページ送りといった操作ができること | N61: OK | O61: OK | P61: OK | Q61: OK | R61: 金田
B62: =ROW()-ROW($B$3) -> 59 | D62: 稟議詳細 | K62: 1.任意の請求書に発注稟議を紐付ける。 2.稟議詳細を押下する。 | L62: 別タブが開き、該当の稟議詳細が表示されること | N62: OK | O62: - | P62: - | Q62: - | R62: 中里
B63: =ROW()-ROW($B$3) -> 60 | D63: 変更履歴 | K63: 1.任意の内容を変更する。 2.変更履歴を確認する。 | L63: 変更履歴が表示されていること | N63: OK | O63: OK | P63: OK | Q63: OK | R63: 金田
B64: =ROW()-ROW($B$3) -> 61 | D64: 申請 | K64: 1.「申請する」を押下する。 2.任意の申請フローを設定し、申請を行う。 | L64: 申請できること | N64: OK | O64: OK | P64: OK | Q64: OK | R64: 金田
B65: =ROW()-ROW($B$3) -> 62 | C65: 稟議詳細（承認済み） | D65: 取引先名 | E65: 送付先を確認 | K65: 「送付先を確認」を押下する。 | L65: 送付先情報が表示され、内容が一致していること | N65: OK | O65: - | P65: - | Q65: - | R65: 中里
B66: =ROW()-ROW($B$3) -> 63 | D66: ビューア | E66: 画像の追加 | K66: 1.任意の稟議を画像なしで作成する。 2.稟議を承認する。 3.稟議詳細にて、任意の画像を追加する。 | L66: 画像の追加ができないこと | M66: アップロード導線が表示されている件は対象外 IP-3839 | N66: OK | O66: - | P66: - | Q66: - | R66: 中里
B67: =ROW()-ROW($B$3) -> 64 | E67: 入れ替え | K67: 1.任意の稟議を画像ありで作成する。 2.稟議を承認する。 3.稟議詳細にて、任意の画像を入れ替える。 | L67: 画像の入れ替えができないこと | M67: 入れ替えアイコンが表示されている件は対象外 IP-3839 | N67: OK | O67: - | P67: - | Q67: - | R67: 中里
B68: =ROW()-ROW($B$3) -> 65 | E68: 削除 | K68: 1.任意の稟議を画像ありで作成する。 2.稟議を承認する。 3.稟議詳細にて、任意の画像を削除する。 | L68: 画像の削除ができないこと | M68: 削除ボタンが表示されている件は対象外 IP-3839 | N68: OK | O68: - | P68: - | Q68: - | R68: 中里

Sheet 領収書原本PLPサイト
N2: Win11/ Chrome | O2: Win11/ Edge | P2: Win11/ Firefox | Q2: Mac/ Safari
B3: No | C3: 画面 | D3: 確認対象 | E3: 詳細 | K3: テスト実行手順 | L3: 期待値 | M3: 備考 | N3: TK+TI+TD | O3: TK+TI+TD | P3: TK単体 | Q3: TK単体 | R3: 実行者 | S3: 実行備考 | T3: 起票JIRA No
B4: =ROW()-ROW($B$3) -> 1 | C4: 領収書原本 | D4: 領収書原本一覧 | E4: 検索条件を設定 | F4: 検索条件 | G4: 登録日～から | K4: 左記の検索条件を設定して検索 | L4: 条件に基づいた検索結果が表示されること | M4: PLP契約をしていないと出てこない https://beartail.slack.com/archives/C053S26MFRA/p1725596902639739?thread_ts=1725596490.164689&cid=C053S26MFRA | N4: OK | O4: - | P4: - | Q4: - | R4: 金田
B5: =ROW()-ROW($B$3) -> 2 | C5: 領収書原本 | G5: 登録日～まで | K5: 同上 | L5: 同上 | N5: OK | O5: - | P5: - | Q5: - | R5: 金田
B6: =ROW()-ROW($B$3) -> 3 | C6: 領収書原本 | G6: 利用日～から | K6: 同上 | L6: 同上 | N6: OK | O6: - | P6: - | Q6: - | R6: 金田
B7: =ROW()-ROW($B$3) -> 4 | C7: 領収書原本 | G7: 利用日～まで | K7: 同上 | L7: 同上 | N7: OK | O7: - | P7: - | Q7: - | R7: 金田
B8: =ROW()-ROW($B$3) -> 5 | C8: 領収書原本 | G8: 金額～から | K8: 同上 | L8: 同上 | N8: OK | O8: - | P8: - | Q8: - | R8: 金田
B9: =ROW()-ROW($B$3) -> 6 | C9: 領収書原本 | G9: 金額～まで | K9: 同上 | L9: 同上 | N9: OK | O9: - | P9: - | Q9: - | R9: 金田
B10: =ROW()-ROW($B$3) -> 7 | C10: 領収書原本 | G10: ポスト名 | K10: 同上 | L10: 同上 | N10: OK | O10: - | P10: - | Q10: - | R10: 金田
B11: =ROW()-ROW($B$3) -> 8 | C11: 領収書原本 | G11: 支払先 | K11: 同上 | L11: 同上 | N11: OK | O11: - | P11: - | Q11: - | R11: 金田
B12: =ROW()-ROW($B$3) -> 9 | C12: 領収書原本 | G12: 申請ステータス:未申請 | K12: 同上 | L12: 同上 | N12: OK | O12: - | P12: - | Q12: - | R12: 行田 | S12: 通信エラーになる確率が高い、普段なりやすいのか分からない
B13: =ROW()-ROW($B$3) -> 10 | C13: 領収書原本 | G13: 申請ステータス:申請中 | K13: 同上 | L13: 同上 | N13: OK | O13: - | P13: - | Q13: - | R13: 行田 | S13: 同上
B14: =ROW()-ROW($B$3) -> 11 | C14: 領収書原本 | G14: 申請ステータス:最終承認待ち | K14: 同上 | L14: 同上 | N14: OK | O14: - | P14: - | Q14: - | R14: 行田 | S14: 同上
B15: =ROW()-ROW($B$3) -> 12 | C15: 領収書原本 | G15: 申請ステータス:最終承認済み | K15: 同上 | L15: 同上 | N15: OK | O15: - | P15: - | Q15: - | R15: 行田 | S15: 同上
B16: =ROW()-ROW($B$3) -> 13 | C16: 領収書原本 | G16: 追加ステータス:通知済み | K16: 同上 | L16: 同上 | N16: OK | O16: - | P16: - | Q16: - | R16: 金田
B17: =ROW()-ROW($B$3) -> 14 | C17: 領収書原本 | G17: 追加ステータス:未通知 | K17: 同上 | L17: 同上 | N17: OK | O17: - | P17: - | Q17: - | R17: 金田
B18: =ROW()-ROW($B$3) -> 15 | C18: 領収書原本 | G18: 原本ステータス:突合待ち | K18: 同上 | L18: 同上 | N18: OK | O18: - | P18: - | Q18: - | R18: 金田
B19: =ROW()-ROW($B$3) -> 16 | C19: 領収書原本 | G19: 原本ステータス:該当経費画像なし | K19: 同上 | L19: 同上 | M19: 突合画面で、対応する経費が見つからず「該当経費画像なし」が選択され、ダブルエントリー完了した | N19: OK | O19: - | P19: - | Q19: - | R19: 行田
B20: =ROW()-ROW($B$3) -> 17 | C20: 領収書原本 | G20: 原本ステータス:キャンセル突合解除 | K20: 同上 | L20: 同上 | M20: 一度突合されたが、 ・手動で突合解除 ・経費の削除 が行われた | N20: OK | O20: - | P20: - | Q20: - | R20: 金田
B21: =ROW()-ROW($B$3) -> 18 | C21: 領収書原本 | G21: 原本ステータス:私用の原本 | K21: 同上 | L21: 同上 | M21: 該当経費画像なし、の原本を一覧から開くと、私用の原本と設定できる。 | N21: OK | O21: - | P21: - | Q21: - | R21: 金田
B22: =ROW()-ROW($B$3) -> 19 | C22: 領収書原本 | G22: 契約期間:任意 | K22: 同上 | L22: 同上 | N22: OK | O22: - | P22: - | Q22: - | R22: 金田
B23: =ROW()-ROW($B$3) -> 20 | C23: 領収書原本 | F23: 検索結果でレポートを出力 | K23: 任意の検索条件で検索 検索結果でレポートを出力を押下 最新のレポート作成を開始 ダウンロードを押下 | L23: 一連の動作がエラーなくできること 作成開始日時、作成完了日時、出力形式が正しいこと ダウンロードできること 出力されたファイルが検索内容と一致すること | N23: OK | O23: - | P23: - | Q23: - | R23: 金田
B24: =ROW()-ROW($B$3) -> 21 | C24: 領収書原本 | E24: 選択した原本を通知する | K24: 突合ステータス「突合経費画像なし」「キャンセル」の突合を選択する 選択した原本を通知するを押下する 任意のユーザーを選択して通知を送信する 任意のユーザーで通知画面を確認する | L24: ・管理者:通知を送信しましたというメッセージが表示されること ・任意のユーザー:通知画面に管理者の送った通知が届くこと | M24: 管理者権限のあるユーザーで行う https://www.notion.so/cbc19e22cfd044509a25b3a1b5b57a59 | N24: OK | O24: - | P24: - | Q24: - | R24: 行田 | S24: キャンセルのみ確認出来ている
B25: =ROW()-ROW($B$3) -> 22 | C25: 領収書原本 | E25: 表示件数 | K25: 表示件数を押下する 任意の件数に変更する | L25: 表示件数が切り替わること | N25: OK | O25: - | P25: - | Q25: - | R25: 金田
B26: =ROW()-ROW($B$3) -> 23 | C26: 領収書原本 | E26: ページネーション | F26: ページ指定 | K26: 任意のページを押下する | L26: 指定したページに移動すること | N26: OK | O26: - | P26: - | Q26: - | R26: 金田
B27: =ROW()-ROW($B$3) -> 24 | C27: 領収書原本 | F27: > | K27: >を押下する | L27: 指定したページに移動すること | N27: OK | O27: - | P27: - | Q27: - | R27: 金田
B28: =ROW()-ROW($B$3) -> 25 | C28: 領収書原本 | F28: >> | K28: >>を押下する | L28: 最後尾のページに移動すること | N28: OK | O28: - | P28: - | Q28: - | R28: 金田
B29: =ROW()-ROW($B$3) -> 26 | C29: 領収書原本 | F29: < | K29: <を押下する | L29: 指定したページに移動すること | N29: OK | O29: - | P29: - | Q29: - | R29: 金田
B30: =ROW()-ROW($B$3) -> 27 | C30: 領収書原本 | F30: << | K30: <<を押下する | L30: 先頭のページに移動すること | N30: OK | O30: - | P30: - | Q30: - | R30: 金田
B31: =ROW()-ROW($B$3) -> 28 | C31: 領収書原本 | E31: クリックで関連経費を見る | K31: クリックで関連経費を見るを押下 | L31: 関連経費が展開して確認できること | M31: 突合した経費を経費分割すると表示される | N31: OK | O31: - | P31: - | Q31: - | R31: 本橋 | S31: 場所がよく分からない
B32: =ROW()-ROW($B$3) -> 29 | C32: 領収書原本 | E32: 原本詳細 | F32: この原本を通知する | G32: 「突合経費画像なし」「キャンセル」 | K32: 突合ステータス「突合経費画像なし」「キャンセル」の突合を選択する 選択した原本を通知するを押下する 任意のユーザーを選択して通知を送信する 任意のユーザーで通知画面を確認する | L32: ・管理者:通知を送信しましたというメッセージが表示されること ・任意のユーザー:通知画面に管理者の送った通知が届くこと | N32: OK | O32: - | P32: - | Q32: - | R32: 行田
B33: =ROW()-ROW($B$3) -> 30 | C33: 領収書原本 | G33: 「突合待ち」「私用の原本」 | K33: 突合ステータス「突合待ち」「私用の原本」を選択する ボタンを確認する | L33: グレーアウトで押下しても反応がないこと | N33: OK | O33: - | P33: - | Q33: - | R33: 金田
G34: 通知先を検索モーダル | H34: 高度な検索 | K34: 高度な検索を押下 | L34: 部署が表示されること | N34: OK | O34: - | P34: - | Q34: -
H35: 従業員名 | K35: 従業員名を入力する 検索を行う | L35: 条件に基づいた検索結果が表示されること | N35: OK | O35: - | P35: - | Q35: - | R35: 金田
H36: 部署 | K36: 部署選択モーダルで部署を選択する 検索を行う | L36: 同上 | N36: OK | O36: - | P36: - | Q36: - | R36: 金田 | S36: 起票したいけど、起票場所など確認中 | T36: FA-102 ⇒修正確認済
H37: 検索ボタン | K37: 任意の条件で入力して検索ボタンを押下 | L37: 同上 | N37: OK | O37: - | P37: - | Q37: - | R37: 金田
H38: すべて外す | K38: 押下する | L38: 検索結果のチェックがすべて外れること | N38: 外 | O38: - | P38: - | Q38: - | R38: 本橋 | S38: チェックが全て選択される状態になっている →富田(秀)：今回のビルド改善の影響ではないので、対象外とする | T38: https://beartail.atlassian.net/browse/FA-108
H39: 表示している内容をすべて選択する | K39: 押下する | L39: 検索結果に全てチェックがつくこと | N39: OK | O39: - | P39: - | Q39: - | R39: 金田
I40: 検索結果タブ | K40: 検索結果タブを押下する | L40: 検索結果が表示されること | N40: OK | O40: - | P40: - | Q40: - | R40: 金田
I41: 選択結果 | K41: 選択結果タブを押下する | L41: 選択結果タブが表示される 検索結果で選択した従業員のみ表示されること | N41: OK | O41: - | P41: - | Q41: - | R41: 金田
I42: キャンセル | K42: 押下する | L42: モーダルが閉じること | N42: OK | O42: - | P42: - | Q42: - | R42: 金田
I43: 対象ユーザーに通知を送信する | K43: 任意の従業員を選択する 対象ユーザーに通知を送信するを押下 | L43: 対象の従業員に通知が送られること | N43: OK | O43: - | P43: - | Q43: - | R43: 金田
G44: 突合する経費を選択モーダル | H44: 検索条件を設定 | K44: ボタンを押下 | L44: 検索条件が展開すること | N44: OK | O44: - | P44: - | Q44: - | R44: 金田
I45: 利用日～から | K45: 左記の検索条件を設定して検索 | L45: 条件に基づいた検索結果が表示されること | N45: OK | O45: - | P45: - | Q45: - | R45: 金田
I46: 利用日～まで | K46: 同上 | L46: 同上 | N46: OK | O46: - | P46: - | Q46: - | R46: 金田
I47: 金額～から | K47: 同上 | L47: 同上 | N47: OK | O47: - | P47: - | Q47: - | R47: 金田
I48: 金額～まで | K48: 同上 | L48: 同上 | N48: OK | O48: - | P48: - | Q48: - | R48: 金田
I49: 支払先 | K49: 同上 | L49: 同上 | N49: OK | O49: - | P49: - | Q49: - | R49: 金田
I50: 従業員 | K50: 同上 | L50: 同上 | N50: OK | O50: - | P50: - | Q50: - | R50: 金田
I51: 所属部署 | K51: 同上 | L51: 同上 | N51: OK | O51: - | P51: - | Q51: - | R51: 金田
I52: 下位部署を含む | K52: 同上 | L52: 同上 | N52: OK | O52: - | P52: - | Q52: - | R52: 金田
I53: 検索 | K53: 任意の検索条件を設定 検索ボタンを押下 | L53: 同上 | N53: OK | O53: - | P53: - | Q53: - | R53: 金田
H54: 表示 | I54: 画像等 | K54: 左記の表示項目が表示されていること マウスオーバーをする | L54: サムネイル画像が表示されること | N54: OK | O54: - | P54: - | Q54: - | R54: 金田
I55: 経費作成者 | K55: 左記の表示項目が表示されていること | L55: 内容が正しいこと | N55: OK | O55: - | P55: - | Q55: - | R55: 金田
I56: 利用日 | K56: 同上 | L56: 同上 | N56: OK | O56: - | P56: - | Q56: - | R56: 金田
I57: 支払先/訪問先 | K57: 同上 | L57: 同上 | N57: OK | O57: - | P57: - | Q57: - | R57: 金田
I58: 金額 | K58: 同上 | L58: 同上 | N58: OK | O58: - | P58: - | Q58: - | R58: 金田
I59: 経費科目 | K59: 同上 | L59: 同上 | N59: OK | O59: - | P59: - | Q59: - | R59: 金田
I60: メモ | K60: 同上 | L60: 同上 | N60: OK | O60: - | P60: - | Q60: - | R60: 金田
I61: 所属部署 | K61: 同上 | L61: 同上 | N61: OK | O61: - | P61: - | Q61: - | R61: 金田
I62: ステータス | K62: 同上 | L62: 同上 | N62: OK | O62: - | P62: - | Q62: - | R62: 金田
H63: 原本確認済み | K63: 原本確認済みの経費を検索する | L63: 検索結果に表示されないこと | N63: OK | O63: - | P63: - | Q63: - | R63: 行田
H64: ソート | I64: 利用日 | K64: 左記の表示項目を設定する 表示項目横の▲▼アイコンを押下する | L64: 昇順降順が切り替わること 設定に応じて表示順が変わること | N64: OK | O64: - | P64: - | Q64: - | R64: 金田
I65: 支払先/訪問先 | K65: 同上 | L65: 同上 | N65: OK | O65: - | P65: - | Q65: - | R65: 金田
I66: 金額 | K66: 同上 | L66: 同上 | N66: OK | O66: - | P66: - | Q66: - | R66: 金田
I67: 経費科目 | K67: 同上 | L67: 同上 | N67: OK | O67: - | P67: - | Q67: - | R67: 金田
I68: 所属部署 | K68: 同上 | L68: 同上 | N68: OK | O68: - | P68: - | Q68: - | R68: 金田
I69: ステータス | K69: 同上 | L69: 同上 | N69: OK | O69: - | P69: - | Q69: - | R69: 金田
H70: ページネーション | I70: ページ指定 | K70: 任意のページを押下する | L70: 指定したページに移動すること | N70: OK | O70: - | P70: - | Q70: - | R70: 金田
I71: > | K71: >を押下する | L71: 指定したページに移動すること | N71: OK | O71: - | P71: - | Q71: - | R71: 金田
I72: >> | K72: >>を押下する | L72: 最後尾のページに移動すること | N72: OK | O72: - | P72: - | Q72: - | R72: 金田
I73: < | K73: <を押下する | L73: 指定したページに移動すること | N73: OK | O73: - | P73: - | Q73: - | R73: 金田
I74: << | K74: <<を押下する | L74: 先頭のページに移動すること | N74: OK | O74: - | P74: - | Q74: - | R74: 金田
H75: 対象の経費を突合 | K75: 対象の経費を突合を押下する | L75: 経費突合すること | N75: OK | O75: - | P75: - | Q75: - | R75: 金田
B76: =ROW()-ROW($B$3) -> 73 | C76: 領収書原本 | F76: 突合経費を選択 | G76: 「突合経費画像なし」「キャンセル」 | K76: 突合ステータス「突合経費画像なし」「キャンセル」の突合を選択して 選択した原本を通知するを押下する 突合する経費の選択を押下する 任意の経費を検索し、突合を行う | L76: 経費突合ができること | N76: OK | O76: - | P76: - | Q76: - | R76: 行田 | S76: キャンセルのみ確認出来ている
B77: =ROW()-ROW($B$3) -> 74 | C77: 領収書原本 | G77: 「突合待ち」「私用の原本」 | K77: 突合ステータス「突合待ち」「私用の原本」を選択する ボタンを確認する | L77: グレーアウトで押下しても反応がないこと | N77: OK | O77: - | P77: - | Q77: - | R77: 金田
B78: =ROW()-ROW($B$3) -> 75 | C78: 領収書原本 | E78: 表示項目 | F78: 原本画像 | K78: 左記の項目を確認する 任意の原本画像にマウスオーバーする | L78: 左記の項目が表示されていること サムネイル画像が表示されること 内容が正しいこと | N78: OK | O78: - | P78: - | Q78: - | R78: 金田
B79: =ROW()-ROW($B$3) -> 76 | C79: 領収書原本 | F79: ポスト名 | K79: 左記の項目を確認する 任意の原本を確認する | L79: 左記の項目が表示されていること 内容が正しいこと | N79: OK | O79: - | P79: - | Q79: - | R79: 金田
B80: =ROW()-ROW($B$3) -> 77 | C80: 領収書原本 | F80: 登録日 | K80: 同上 | L80: 同上 | N80: OK | O80: - | P80: - | Q80: - | R80: 金田
B81: =ROW()-ROW($B$3) -> 78 | C81: 領収書原本 | F81: 突合ステータス | K81: 同上 | L81: 同上 | N81: OK | O81: - | P81: - | Q81: - | R81: 金田
B82: =ROW()-ROW($B$3) -> 79 | C82: 領収書原本 | F82: 利用日 | K82: 同上 | L82: 同上 | N82: OK | O82: - | P82: - | Q82: - | R82: 金田
B83: =ROW()-ROW($B$3) -> 80 | C83: 領収書原本 | F83: 金額 | K83: 同上 | L83: 同上 | N83: OK | O83: - | P83: - | Q83: - | R83: 金田
B84: =ROW()-ROW($B$3) -> 81 | C84: 領収書原本 | F84: 支払先 | K84: 同上 | L84: 同上 | N84: OK | O84: - | P84: - | Q84: - | R84: 金田
B85: =ROW()-ROW($B$3) -> 82 | C85: 領収書原本 | F85: 経費作成者名 | K85: 同上 | L85: 同上 | N85: OK | O85: - | P85: - | Q85: - | R85: 金田
B86: =ROW()-ROW($B$3) -> 83 | C86: 領収書原本 | F86: 所属部署 | K86: 同上 | L86: 同上 | N86: OK | O86: - | P86: - | Q86: - | R86: 金田
B87: =ROW()-ROW($B$3) -> 84 | C87: 領収書原本 | F87: 申請ID | K87: 同上 | L87: 同上 | N87: OK | O87: - | P87: - | Q87: - | R87: 金田
B88: =ROW()-ROW($B$3) -> 85 | C88: 領収書原本 | F88: 管理ID | K88: 同上 | L88: 同上 | N88: OK | O88: - | P88: - | Q88: - | R88: 金田
B89: =ROW()-ROW($B$3) -> 86 | C89: 領収書原本 | F89: ポスト設置場所 | K89: 同上 | L89: 同上 | N89: OK | O89: - | P89: - | Q89: - | R89: 金田
B90: =ROW()-ROW($B$3) -> 87 | C90: 領収書原本 | F90: 契約期間 | K90: 同上 | L90: 同上 | N90: OK | O90: - | P90: - | Q90: - | R90: 金田
B91: =ROW()-ROW($B$3) -> 88 | C91: PLPサイト | D91: 原本回収サイクル一覧 | E91: 原本回収サイクルを検索 | K91: 原本回収サイクルを検索を押下 | L91: 検索画面が展開すること | N91: OK | O91: - | P91: - | Q91: - | R91: 金田
B92: =ROW()-ROW($B$3) -> 89 | C92: PLPサイト | F92: 事業所名 | K92: 押下する 任意の事業所名を入力する | L92: 事業所候補が表示されること 入力に一致する事業所が候補として表示されること | N92: OK | O92: - | P92: - | Q92: - | R92: 金田
B93: =ROW()-ROW($B$3) -> 90 | C93: PLPサイト | F93: 検索条件をリセット | K93: 検索条件をリセットを押下 | L93: 検索条件がクリアされること | N93: OK | O93: - | P93: - | Q93: - | R93: 金田
B94: =ROW()-ROW($B$3) -> 91 | C94: PLPサイト | F94: 指定した条件で検索 | K94: 任意の検索条件を設定する 検索ボタンを押下する | L94: 任意の条件にを満たす事業所のみ検索結果に表示されること | N94: OK | O94: - | P94: - | Q94: - | R94: 金田
B95: =ROW()-ROW($B$3) -> 92 | C95: PLPサイト | E95: 表示件数 | K95: 表示件数を押下する 任意の件数に変更する | L95: 表示件数が切り替わること | N95: OK | O95: - | P95: - | Q95: - | R95: 金田
B96: =ROW()-ROW($B$3) -> 93 | C96: PLPサイト | E96: ページネーション | F96: ページ指定 | K96: 任意のページを押下する | L96: 指定したページに移動すること | N96: OK | O96: - | P96: - | Q96: - | R96: 金田
B97: =ROW()-ROW($B$3) -> 94 | C97: PLPサイト | F97: > | K97: >を押下する | L97: 指定したページに移動すること | N97: OK | O97: - | P97: - | Q97: - | R97: 金田
B98: =ROW()-ROW($B$3) -> 95 | C98: PLPサイト | F98: >> | K98: >>を押下する | L98: 最後尾のページに移動すること | N98: OK | O98: - | P98: - | Q98: - | R98: 金田
B99: =ROW()-ROW($B$3) -> 96 | C99: PLPサイト | F99: < | K99: <を押下する | L99: 指定したページに移動すること | N99: OK | O99: - | P99: - | Q99: - | R99: 金田
B100: =ROW()-ROW($B$3) -> 97 | C100: PLPサイト | F100: << | K100: <<を押下する | L100: 先頭のページに移動すること | N100: OK | O100: - | P100: - | Q100: - | R100: 金田
B101: =ROW()-ROW($B$3) -> 98 | C101: PLPサイト | E101: 表示項目 | F101: 事業所名 | K101: 表示を確認する 任意の事業所を確認する | L101: 表示項目が表示されていること 内容が正しいこと | N101: OK | O101: - | P101: - | Q101: - | R101: 金田
...

Sheet 請求書
C2: 新UIで作成（必要であれば旧も作成する） | M2: Win11/ Chrome | N2: Win11/ Edge | O2: Win11/ Firefox | P2: Mac/ Safari
B3: No | C3: 画面 | D3: 確認対象 | E3: 詳細 | J3: テスト実行手順 | K3: 期待値 | L3: 備考 | M3: TK+TI+TD | N3: TI+TD | O3: TI+TD | P3: TI+TD | Q3: 実行者 | R3: 実行備考 | S3: 起票JIRA No
B4: =ROW()-ROW($B$3) -> 1 | C4: 請求書＞請求書を登録する | D4: 請求書（新規画面） | E4: 画像 | F4: 画像なし | J4: 1.「請求書を登録する」を押下する。 2.概要タブで任意の内容を入力する。 3.「保存」を押下する。 | K4: 請求書が作成できること | M4: OK | N4: - | O4: - | P4: - | Q4: 北川 | R4: 新UI
B5: =ROW()-ROW($B$3) -> 2 | F5: png | J5: 1.「請求書を登録する」を押下する。 2.左記のファイルを追加する。 3.概要タブで任意の内容を入力する。 4.「保存」を押下する。 | K5: 請求書が作成できること | M5: OK | N5: - | O5: - | P5: - | Q5: 北川
B6: =ROW()-ROW($B$3) -> 3 | F6: jpeg（jpg） | J6: 1.「請求書を登録する」を押下する。 2.左記のファイルを追加する。 3.概要タブで任意の内容を入力する。 4.「保存」を押下する。 | K6: 請求書が作成できること | M6: OK | N6: - | O6: - | P6: - | Q6: 北川
B7: =ROW()-ROW($B$3) -> 4 | F7: pdf | J7: 1.「請求書を登録する」を押下する。 2.左記のファイルを追加する。 3.概要タブで任意の内容を入力する。 4.「保存」を押下する。 | K7: 請求書が作成できること | M7: OK | N7: OK | O7: OK | P7: - | Q7: 北川 金田
B8: =ROW()-ROW($B$3) -> 5 | F8: pdf（パスワード付） | J8: 1.「請求書を登録する」を押下する。 2.左記のファイルを追加する。 3.概要タブで任意の内容を入力する。 4.「保存」を押下する。 | K8: 請求書が作成できること | M8: OK | N8: - | O8: - | P8: - | Q8: 北川
B9: =ROW()-ROW($B$3) -> 6 | F9: xls | J9: 1.「請求書を登録する」を押下する。 2.左記のファイルを追加する。 3.概要タブで任意の内容を入力する。 4.「保存」を押下する。 | K9: 請求書が作成できること | M9: OK | N9: - | O9: - | P9: - | Q9: 北川
B10: =ROW()-ROW($B$3) -> 7 | F10: xlsx | J10: 1.「請求書を登録する」を押下する。 2.左記のファイルを追加する。 3.概要タブで任意の内容を入力する。 4.「保存」を押下する。 | K10: 請求書が作成できること | M10: OK | N10: - | O10: - | P10: - | Q10: 北川
B11: =ROW()-ROW($B$3) -> 8 | F11: doc | J11: 1.「請求書を登録する」を押下する。 2.左記のファイルを追加する。 3.概要タブで任意の内容を入力する。 4.「保存」を押下する。 | K11: 請求書が作成できること | M11: OK | N11: - | O11: - | P11: - | Q11: 北川
B12: =ROW()-ROW($B$3) -> 9 | F12: docx | J12: 1.「請求書を登録する」を押下する。 2.左記のファイルを追加する。 3.概要タブで任意の内容を入力する。 4.「保存」を押下する。 | K12: 請求書が作成できること | M12: OK | N12: - | O12: - | P12: - | Q12: 北川
B13: =ROW()-ROW($B$3) -> 10 | F13: txt | J13: 1.「請求書を登録する」を押下する。 2.左記のファイルを追加する。 3.概要タブで任意の内容を入力する。 4.「保存」を押下する。 | K13: 請求書が作成できること | M13: OK | N13: - | O13: - | P13: - | Q13: 北川
B14: =ROW()-ROW($B$3) -> 11 | F14: csv | J14: 1.「請求書を登録する」を押下する。 2.左記のファイルを追加する。 3.概要タブで任意の内容を入力する。 4.「保存」を押下する。 | K14: 請求書が作成できること | M14: OK | N14: - | O14: - | P14: - | Q14: 北川
B15: =ROW()-ROW($B$3) -> 12 | F15: 100MBのファイル | J15: 1.「請求書を登録する」を押下する。 2.左記のファイルを追加する。 3.概要タブで任意の内容を入力する。 4.「保存」を押下する。 | K15: 請求書が作成できること | M15: OK | N15: - | O15: - | P15: - | Q15: 北川
B16: =ROW()-ROW($B$3) -> 13 | F16: 1~10ページにファイル追加 | J16: 1.「請求書を登録する」を押下する。 2.左記のファイル状態にする。 3.概要タブで任意の内容を入力する。 4.「保存」を押下する。 | K16: 請求書が作成できること | M16: OK | N16: - | O16: - | P16: - | Q16: 北川
B17: =ROW()-ROW($B$3) -> 14 | E17: PDFビューア | F17: TOKIUMビューア | J17: ビューアで画像の入れ替えや拡縮など各種操作を行う | K17: 表示崩れしないこと | M17: OK | N17: - | O17: - | P17: - | Q17: 北川
B18: =ROW()-ROW($B$3) -> 15 | F18: ブラウザ標準ビューア | J18: ブラウザ標準ビューアを開き画像の入れ替えや拡縮など各種操作を行う | K18: 表示崩れしないこと | M18: OK | N18: - | O18: - | P18: - | Q18: 北川
B19: =ROW()-ROW($B$3) -> 16 | E19: PNG,JPEGのビューア | J19: ビューアで画像の入れ替えや拡縮など各種操作を行う | K19: 表示崩れしないこと | M19: OK | N19: - | O19: - | P19: - | Q19: 北川
B20: =ROW()-ROW($B$3) -> 17 | E20: その他の拡張子のビューア | J20: ビューアで画像の入れ替えとダウンロードを行う | K20: ビューアの機能が使えること | M20: OK | N20: - | O20: - | P20: - | Q20: 北川
B21: =ROW()-ROW($B$3) -> 18 | E21: 明細作成 | F21: 手動で作成 | J21: 1.「請求書を登録する」を押下する。 2.概要タブで任意の内容を入力する。 3.明細タブ＞明細の追加＞手動で作成を選択する。 4.「保存」を押下する。 | K21: 請求書が作成できること | M21: OK | N21: OK | O21: OK | P21: - | Q21: 金田
B22: =ROW()-ROW($B$3) -> 19 | F22: 過去明細から作成 | G22: 明細ドロワー | J22: 1.「請求書を登録する」を押下する。 2.明細タブ＞明細の追加＞過去明細から作成を押下する。 3.請求書から探す＞明細ドロワーで明細を選択する。 4.「保存」を押下する。 | K22: 請求書が作成できること | M22: OK | N22: - | O22: - | P22: - | Q22: 北川 | R22: 過去明細モーダルのタブ機能が未実装→実装済み
B23: =ROW()-ROW($B$3) -> 20 | G23: お気に入りタブ | J23: 1.「請求書を登録する」を押下する。 2.明細タブ＞明細の追加＞過去明細から作成を押下する。 3.明細ドロワーから明細のお気に入り登録を行う。 4.お気に入りタブを開き、明細を選択する。 5.「保存」を押下する。 | K23: 請求書が作成できること | M23: OK | N23: - | O23: - | P23: - | Q23: 北川
B24: =ROW()-ROW($B$3) -> 21 | F24: インポートから作成 | J24: 1.「請求書を登録する」を押下する。 2.明細タブ＞明細の追加＞インポートから作成を押下する。 3.明細をインポートする。 4.「保存」を押下する。 | K24: 請求書が作成できること | M24: OK | N24: - | O24: - | P24: - | Q24: 北川
B25: =ROW()-ROW($B$3) -> 22 | F25: 表示項目（税込） | G25: 明細名 | J25: 1.任意の明細名を入力する。 2.「保存する」を押下する。 3.明細一覧を確認する。 | K25: 入力した明細名が表示されていること | M25: OK | N25: - | O25: - | P25: - | Q25: 中里
B26: =ROW()-ROW($B$3) -> 23 | G26: 税抜金額 | H26: 通貨 | J26: 任意の通貨を選択する。 | K26: 通貨が変更できること | M26: OK | N26: - | O26: - | P26: - | Q26: 中里
B27: =ROW()-ROW($B$3) -> 24 | I27: 金額 | J27: 1.任意の金額を入力する。 2.「保存する」を押下する。 | K27: 入力した金額が請求書詳細に反映されること | M27: OK | N27: - | O27: - | P27: - | Q27: 中里
B28: =ROW()-ROW($B$3) -> 25 | I28: レート | J28: 1.任意の値を入力する。 2.入力値を変更する。 | K28: レートに合わせ、以下の金額が変動すること ・金額の「JPY換算」 ・消費税額 | M28: OK | N28: - | O28: - | P28: - | Q28: 中里
B29: =ROW()-ROW($B$3) -> 26 | J29: 「保存する」を押下する。 | K29: 入力した金額が請求書詳細に反映されること | M29: OK | N29: - | O29: - | P29: - | Q29: 中里
B30: =ROW()-ROW($B$3) -> 27 | H30: ヘルプ | J30: 「？」アイコンへマウスオーバーする。 | K30: ヘルプが表示され、表示崩れがないこと | M30: OK | N30: - | O30: - | P30: - | Q30: 中里
B31: =ROW()-ROW($B$3) -> 28 | G31: 消費税額 | J31: 金額を入力する。 | K31: 入力できること | M31: OK | N31: - | O31: - | P31: - | Q31: 中里
B32: =ROW()-ROW($B$3) -> 29 | H32: ヘルプ | J32: 「？」アイコンへマウスオーバーする。 | K32: ヘルプが表示され、表示崩れがないこと | M32: OK | N32: - | O32: - | P32: - | Q32: 中里
B33: =ROW()-ROW($B$3) -> 30 | G33: 源泉徴収税額 | J33: 金額を入力する。 | K33: 入力できること | M33: OK | N33: - | O33: - | P33: - | Q33: 中里
B34: =ROW()-ROW($B$3) -> 31 | G34: 発注稟議 | J34: 1.セレクトボックス内を押下する。 2.候補に表示された稟議を選択する。 | K34: 同一の取引先の稟議が表示され、選択できること | M34: OK | N34: - | O34: - | P34: - | Q34: 中里
B35: =ROW()-ROW($B$3) -> 32 | H35: ヘルプ | J35: 「？」アイコンへマウスオーバーする。 | K35: ヘルプが表示され、表示崩れがないこと | M35: OK | N35: - | O35: - | P35: - | Q35: 中里
B36: =ROW()-ROW($B$3) -> 33 | G36: 発注書番号 | J36: 任意の数値を入力する。 | K36: 入力できること | M36: OK | N36: - | O36: - | P36: - | Q36: 中里
B37: =ROW()-ROW($B$3) -> 34 | G37: 借方請求明細科目 | J37: 1.セレクトボックス内を押下する。 2.候補に表示された科目を選択する。 | K37: 選択した科目が反映されること | M37: OK | N37: - | O37: - | P37: - | Q37: 中里
B38: =ROW()-ROW($B$3) -> 35 | G38: 参加者 | H38: 自社の参加者を追加 | J38: 1.参加者が必須の借方請求明細科目が設定された明細を用意する。 2.参加者＞自社を押下する。 | K38: 「自社の参加者を追加」モーダルが表示されること | M38: OK | N38: - | O38: - | P38: - | Q38: 金子
B39: =ROW()-ROW($B$3) -> 36 | I39: 社員を追加 | J39: 1.任意の氏名を入力する。 2.「追加」を押下する。 | K39: 参加者が追加でき、モーダル上部に以下の内容が表示されること ・参加者名：◯◯ ・詳細：空欄 ・「除外する」ボタン | M39: OK | N39: - | O39: - | P39: - | Q39: 金子
B40: =ROW()-ROW($B$3) -> 37 | J40: 「除外する」ボタンを押下する。 | K40: 追加した参加者が一覧に表示されており、以下が表示されていること ・参加者の氏名 ・ゴミ箱アイコン ・チェックボックス | M40: OK | N40: - | O40: - | P40: - | Q40: 金子
B41: =ROW()-ROW($B$3) -> 38 | J41: 参加者一覧を確認する。 | K41: 追加した参加者が表示されていること | M41: OK | N41: - | O41: - | P41: - | Q41: 金子
B42: =ROW()-ROW($B$3) -> 39 | J42: 「氏名」のプルダウンを押下する。 | K42: 切り替えの候補に「氏名」「人数」が表示されること | M42: OK | N42: - | O42: - | P42: - | Q42: 金子
B43: =ROW()-ROW($B$3) -> 40 | J43: 「人数」を押下する。 | K43: 内容が切り替わること | M43: OK | N43: - | O43: - | P43: - | Q43: 金子
B44: =ROW()-ROW($B$3) -> 41 | J44: 1.任意の数字を入力する。 2.「追加」を押下する。 | K44: 参加者が追加でき、モーダル上部に以下の内容が表示されること ・参加者名：その他 ・詳細：◯人 ・「除外する」ボタン | M44: OK | N44: - | O44: - | P44: - | Q44: 金子
B45: =ROW()-ROW($B$3) -> 42 | J45: 詳細のセレクトボックスにて、任意の値を入力する。 | K45: 参加者の人数が変更できること | M45: OK | N45: - | O45: - | P45: - | Q45: 金子
B46: =ROW()-ROW($B$3) -> 43 | J46: 詳細のセレクトボックスにて、「▲▼」を押下する。 | K46: 参加者の人数が変更できること | M46: OK | N46: - | O46: - | P46: - | Q46: 金子
B47: =ROW()-ROW($B$3) -> 44 | J47: 「除外する」ボタンを押下する。 | K47: 参加者が全て除外されること | M47: OK | N47: - | O47: - | P47: - | Q47: 金子
B48: =ROW()-ROW($B$3) -> 45 | I48: 検索 | J48: 任意の氏名（完全一致）で検索を行う。 | K48: 条件に基づいた検索結果が表示されること | M48: OK | N48: - | O48: - | P48: - | Q48: 金子
B49: =ROW()-ROW($B$3) -> 46 | J49: 任意の氏名（部分一致）で検索を行う。 | K49: 条件に基づいた検索結果が表示されること | M49: OK | N49: - | O49: - | P49: - | Q49: 金子
B50: =ROW()-ROW($B$3) -> 47 | J50: 任意の部署名（完全一致）で検索を行う。 | K50: 条件に基づいた検索結果が表示されること | M50: OK | N50: - | O50: - | P50: - | Q50: 金子
B51: =ROW()-ROW($B$3) -> 48 | J51: 任意の部署名（部分一致）で検索を行う。 | K51: 条件に基づいた検索結果が表示されること | M51: OK | N51: - | O51: - | P51: - | Q51: 金子
B52: =ROW()-ROW($B$3) -> 49 | J52: 存在しない値で検索を行う。 | K52: 条件に基づいた検索結果が表示されること | M52: OK | N52: - | O52: - | P52: - | Q52: 金子
B53: =ROW()-ROW($B$3) -> 50 | J53: 「検索条件をリセット」を押下する。 | K53: 検索条件がリセットされ、全ての参加者が表示されること | M53: OK | N53: - | O53: - | P53: - | Q53: 金子
B54: =ROW()-ROW($B$3) -> 51 | I54: 参加者一覧 | J54: 表示されている参加者を確認する。 | K54: 以下が表示されていること ・参加者の氏名 ・所属部署（設定済みの場合） ・チェックボックス | M54: OK | N54: - | O54: - | P54: - | Q54: 金子
B55: =ROW()-ROW($B$3) -> 52 | J55: 任意の参加者にチェックを入れる。 | K55: モーダル名横の人数と選択人数が一致すること | M55: OK | N55: - | O55: - | P55: - | Q55: 金子
B56: =ROW()-ROW($B$3) -> 53 | I56: 保存 | J56: 「保存」を押下する。 | K56: 選択した参加者を追加できること | M56: OK | N56: - | O56: - | P56: - | Q56: 金子
B57: =ROW()-ROW($B$3) -> 54 | I57: 「×」 | J57: 1.任意の参加者にチェックを入れる。 2.「×」を押下する。 | K57: 選択した参加者が追加されないこと | M57: OK | N57: - | O57: - | P57: - | Q57: 金子
B58: =ROW()-ROW($B$3) -> 55 | I58: 表示件数 | J58: 表示件数を押下する。 | K58: 件数に「5」「10」「25」が表示されること | M58: OK | N58: - | O58: - | P58: - | Q58: 金子
B59: =ROW()-ROW($B$3) -> 56 | J59: 任意の表示件数を選択する。 | K59: 変更できること | M59: OK | N59: - | O59: - | P59: - | Q59: 金子
B60: =ROW()-ROW($B$3) -> 57 | H60: 取引先の参加者を追加 | J60: 1.参加者が必須の借方請求明細科目が設定された明細を用意する。 2.参加者＞取引先を押下する。 | K60: 「取引先の参加者を追加」モーダルが表示されること | M60: OK | N60: - | O60: - | P60: - | Q60: 金子
B61: =ROW()-ROW($B$3) -> 58 | I61: 会社名のみ | J61: 1.任意の内容を入力する。 2.「追加」を押下する。 | K61: 参加者の追加ができないこと | M61: OK | N61: - | O61: - | P61: - | Q61: 金子
B62: =ROW()-ROW($B$3) -> 59 | J62: 「社員を追加」のセレクトボックスを確認する。 | K62: 「社員を追加」のセレクトボックスを確認する。 | M62: OK | N62: - | O62: - | P62: - | Q62: 金子
B63: =ROW()-ROW($B$3) -> 60 | J63: 1.「社員を追加」のプルダウン＞人数を選択する。 2.任意の会社名を入力する。 3.「追加」を押下する。 | K63: 参加者の追加ができないこと | M63: OK | N63: - | O63: - | P63: - | Q63: 金子
B64: =ROW()-ROW($B$3) -> 61 | J64: 「社員を追加」のセレクトボックスを確認する。 | K64: エラーが表示され、表示崩れがないこと | M64: OK | N64: - | O64: - | P64: - | Q64: 金子
B65: =ROW()-ROW($B$3) -> 62 | I65: 会社名＋社員を追加（氏名） | J65: 1.任意の会社名・氏名を入力する。 2.「追加」を押下する。 | K65: 参加者が追加でき、モーダル上部に以下の内容が表示されること ・（会社名）参加者一覧 ・参加者名：◯◯ ・詳細：空欄 ・「除外する」ボタン | M65: OK | N65: - | O65: - | P65: - | Q65: 金子
B66: =ROW()-ROW($B$3) -> 63 | J66: 「除外する」ボタンを押下する。 | K66: 参加者が全て除外されること | M66: OK | N66: - | O66: - | P66: - | Q66: 金子
B67: =ROW()-ROW($B$3) -> 64 | J67: 参加者一覧を確認する。 | K67: 追加した参加者が一覧に表示されており、以下が表示されていること ・参加者の氏名 ・会社名 ・ゴミ箱アイコン ・チェックボックス | M67: OK | N67: - | O67: - | P67: - | Q67: 金子
B68: =ROW()-ROW($B$3) -> 65 | I68: 社員を追加 | J68: 1.任意の氏名を入力する。 2.「追加」を押下する。 | K68: 参加者が追加でき、モーダル上部に以下の内容が表示されること ・参加者名：◯◯ ・詳細：空欄 ・「除外する」ボタン | M68: OK | N68: - | O68: - | P68: - | Q68: 金子
B69: =ROW()-ROW($B$3) -> 66 | J69: 「除外する」ボタンを押下する。 | K69: 追加した参加者が一覧に表示されており、以下が表示されていること ・参加者の氏名 ・ゴミ箱アイコン ・チェックボックス | M69: OK | N69: - | O69: - | P69: - | Q69: 金子
B70: =ROW()-ROW($B$3) -> 67 | J70: 参加者一覧を確認する。 | K70: 追加した参加者が表示されていること | M70: OK | N70: - | O70: - | P70: - | Q70: 金子
B71: =ROW()-ROW($B$3) -> 68 | J71: 「氏名」のプルダウンを押下する。 | K71: 切り替えの候補に「氏名」「人数」が表示されること | M71: OK | N71: - | O71: - | P71: - | Q71: 金子
B72: =ROW()-ROW($B$3) -> 69 | J72: 「人数」を押下する。 | K72: 内容が切り替わること | M72: OK | N72: - | O72: - | P72: - | Q72: 金子
B73: =ROW()-ROW($B$3) -> 70 | J73: 1.任意の数字を入力する。 2.「追加」を押下する。 | K73: 参加者が追加でき、モーダル上部に以下の内容が表示されること ・参加者名：その他 ・詳細：◯人 ・「除外する」ボタン | M73: OK | N73: - | O73: - | P73: - | Q73: 金子
B74: =ROW()-ROW($B$3) -> 71 | J74: 詳細のセレクトボックスにて、任意の値を入力する。 | K74: 参加者の人数が変更できること | M74: OK | N74: - | O74: - | P74: - | Q74: 金子
B75: =ROW()-ROW($B$3) -> 72 | J75: 詳細のセレクトボックスにて、「▲▼」を押下する。 | K75: 参加者の人数が変更できること | M75: OK | N75: - | O75: - | P75: - | Q75: 金子
B76: =ROW()-ROW($B$3) -> 73 | J76: 「除外する」ボタンを押下する。 | K76: 参加者が全て除外されること | M76: OK | N76: - | O76: - | P76: - | Q76: 金子
B77: =ROW()-ROW($B$3) -> 74 | I77: 検索 | J77: 任意の氏名（完全一致）で検索を行う。 | K77: 条件に基づいた検索結果が表示されること | M77: OK | N77: - | O77: - | P77: - | Q77: 金子
B78: =ROW()-ROW($B$3) -> 75 | J78: 任意の氏名（部分一致）で検索を行う。 | K78: 条件に基づいた検索結果が表示されること | M78: OK | N78: - | O78: - | P78: - | Q78: 金子
B79: =ROW()-ROW($B$3) -> 76 | J79: 任意の部署名（完全一致）で検索を行う。 | K79: 条件に基づいた検索結果が表示されること | M79: OK | N79: - | O79: - | P79: - | Q79: 金子
B80: =ROW()-ROW($B$3) -> 77 | J80: 任意の部署名（部分一致）で検索を行う。 | K80: 条件に基づいた検索結果が表示されること | M80: OK | N80: - | O80: - | P80: - | Q80: 金子
B81: =ROW()-ROW($B$3) -> 78 | J81: 存在しない値で検索を行う。 | K81: 条件に基づいた検索結果が表示されること | M81: OK | N81: - | O81: - | P81: - | Q81: 金子
B82: =ROW()-ROW($B$3) -> 79 | J82: 「検索条件をリセット」を押下する。 | K82: 検索条件がリセットされ、全ての参加者が表示されること | M82: OK | N82: - | O82: - | P82: - | Q82: 金子
B83: =ROW()-ROW($B$3) -> 80 | I83: 参加者一覧 | J83: 表示されている参加者を確認する。 | K83: 以下が表示されていること ・参加者の氏名 ・所属部署（設定済みの場合） ・チェックボックス | M83: OK | N83: - | O83: - | P83: - | Q83: 金子
B84: =ROW()-ROW($B$3) -> 81 | J84: 任意の参加者にチェックを入れる。 | K84: モーダル名横の人数と選択人数が一致すること | M84: OK | N84: - | O84: - | P84: - | Q84: 金子
B85: =ROW()-ROW($B$3) -> 82 | I85: 保存 | J85: 「保存」を押下する。 | K85: 選択した参加者を追加できること | M85: OK | N85: - | O85: - | P85: - | Q85: 金子
B86: =ROW()-ROW($B$3) -> 83 | I86: 「×」 | J86: 1.任意の参加者にチェックを入れる。 2.「×」を押下する。 | K86: 選択した参加者が追加されないこと | M86: OK | N86: - | O86: - | P86: - | Q86: 金子
B87: =ROW()-ROW($B$3) -> 84 | I87: 表示件数 | J87: 表示件数を押下する。 | K87: 件数に「5」「10」「25」が表示されること | M87: OK | N87: - | O87: - | P87: - | Q87: 金子
B88: =ROW()-ROW($B$3) -> 85 | J88: 任意の表示件数を選択する。 | K88: 変更できること | M88: OK | N88: - | O88: - | P88: - | Q88: 金子
B89: =ROW()-ROW($B$3) -> 86 | G89: 税区分 | J89: 任意の税区分を選択する。 | K89: 選択できること | M89: OK | N89: - | O89: - | P89: - | Q89: 中里
B90: =ROW()-ROW($B$3) -> 87 | G90: 貸方請求明細科目 | J90: 1.セレクトボックス内を押下する。 2.候補に表示された科目を選択する。 | K90: 選択した内容が反映されること | M90: OK | N90: - | O90: - | P90: - | Q90: 中里
B91: =ROW()-ROW($B$3) -> 88 | G91: プロジェクト | J91: 1.セレクトボックス内を押下する。 2.候補に表示されたプロジェクトを選択する。 | K91: 選択した内容が反映されること | M91: OK | N91: - | O91: - | P91: - | Q91: 中里
B92: =ROW()-ROW($B$3) -> 89 | G92: 費用負担部署 | J92: 1.「＋」を押下し、費用負担部署モーダルを表示する。 2.任意の部署で按分を行う。 3.「キャンセル」を押下する。 | K92: 費用負担部署が追加されないこと | M92: OK | N92: - | O92: - | P92: - | Q92: 中里
B93: =ROW()-ROW($B$3) -> 90 | J93: 1.「＋」を押下し、費用負担部署モーダルを表示する。 2.任意の部署で按分を行う。 3.「設定する」を押下する。 | K93: 費用負担部署が追加されること | M93: OK | N93: - | O93: - | P93: - | Q93: 中里
B94: =ROW()-ROW($B$3) -> 91 | G94: 明細メモ | J94: 1.任意の内容を入力する。 2.「保存する」を押下する。 | K94: 明細に内容が反映されること | M94: OK | N94: - | O94: - | P94: - | Q94: 中里
B95: =ROW()-ROW($B$3) -> 92 | G95: 確認モーダル | H95: はい | J95: 1.明細の任意の項目を入力する。 2.任意の方法で明細の入力キャンセルを行う。 3.確認モーダルの「はい」を押下する。 | K95: 明細の作成がキャンセルされること | M95: OK | N95: - | O95: - | P95: - | Q95: 中里
B96: =ROW()-ROW($B$3) -> 93 | H96: いいえ | J96: 1.明細の任意の項目を入力する。 2.任意の方法で明細の入力キャンセルを行う。 3.確認モーダルの「いいえ」を押下する。 | K96: 明細の作成に戻ること | M96: OK | N96: - | O96: - | P96: - | Q96: 中里
B97: =ROW()-ROW($B$3) -> 94 | H97: × | J97: 1.明細の任意の項目を入力する。 2.任意の方法で明細の入力キャンセルを行う。 3.確認モーダルの「×」を押下する。 | K97: 明細の作成に戻ること | M97: OK | N97: - | O97: - | P97: - | Q97: 中里
B98: =ROW()-ROW($B$3) -> 95 | H98: モーダル外を押下 | J98: 1.明細の任意の項目を入力する。 2.任意の方法で明細の入力キャンセルを行う。 3.確認モーダル外を押下する。 | K98: 明細の作成に戻ること | M98: OK | N98: - | O98: - | P98: - | Q98: 中里
B99: =ROW()-ROW($B$3) -> 96 | G99: 「×」アイコン | H99: 入力あり | J99: 1.明細の任意の項目を入力する。 2.「×」アイコンを押下する。 | K99: 確認モーダルが表示されること | M99: OK | N99: - | O99: - | P99: - | Q99: 中里
B100: =ROW()-ROW($B$3) -> 97 | H100: 入力なし | J100: 明細の項目を入力せずに「×」アイコンを押下する。 | K100: 確認モーダルが表示されず、明細タブに戻ること | M100: OK | N100: - | O100: - | P100: - | Q100: 中里
B101: =ROW()-ROW($B$3) -> 98 | G101: 明細画面の外側をクリック | H101: 入力あり | J101: 1.明細の任意の項目を入力する。 2.明細画面の外側をクリックする。 | K101: 確認モーダルが表示されること | M101: OK | N101: - | O101: - | P101: - | Q101: 中里
...

Sheet 個人設定
M2: mac/ Chrome | N2: Win11/ Edge | O2: mac/ Firefox | P2: Win11/ Safari
B3: No | C3: 画面 | D3: 確認対象 | E3: 詳細 | J3: テスト実行手順 | K3: 期待値 | L3: 備考 | M3: TK+TI+TD | N3: TI+TD | O3: TK単体 | P3: TD単体 | Q3: 実行者 | R3: 実行備考 | S3: 起票JIRA No
B4: =ROW()-ROW($B$3) -> 1 | C4: アカウント設定 | D4: アカウント設定 | E4: アカウント名 | J4: 任意のアカウント名へ変更する。 | K4: 変更後のアカウント名が表示されること | M4: OK | N4: OK | O4: OK | P4: - | Q4: 中里 行田
B5: =ROW()-ROW($B$3) -> 2 | E5: メールアドレス | J5: 任意のメールアドレスへ変更する。 | K5: 変更できること | M5: OK | N5: OK | O5: OK | P5: - | Q5: 中里 行田
B6: =ROW()-ROW($B$3) -> 3 | J6: 1.一度ログアウトを行う。 2.変更後のメールアドレスでログインする。 | K6: ログインできること | M6: OK | N6: OK | O6: OK | P6: - | Q6: 中里 行田
B7: =ROW()-ROW($B$3) -> 4 | E7: 言語設定 | F7: English | J7: 言語を「English」へ変更する。 | K7: 言語変更後、表示崩れが起きないこと | M7: OK | N7: OK | O7: OK | P7: - | Q7: 中里 行田
B8: =ROW()-ROW($B$3) -> 5 | F8: 日本語 | J8: 言語を「日本語」へ変更する。 | K8: 言語変更後、表示崩れが起きないこと | M8: OK | N8: OK | O8: OK | P8: - | Q8: 中里 行田
B9: =ROW()-ROW($B$3) -> 6 | D9: 書類送付先 | E9: メールアドレス | J9: メールアドレスを確認する。 | K9: 書類送付先アドレスが表示されていること | M9: OK | N9: OK | O9: OK | P9: - | Q9: 中里 行田
B10: =ROW()-ROW($B$3) -> 7 | F10: ヘルプ | J10: メールアドレスの左側の「？」アイコンへマウスオーバーする。 | K10: ヘルプに表示崩れがないこと | M10: OK | N10: OK | O10: OK | P10: - | Q10: 中里 行田
B11: =ROW()-ROW($B$3) -> 8 | D11: シングルサインオン設定 | E11: Google | F11: アカウント登録 | J11: 任意のGoogleアカウントを連携する。 | K11: 連携できること | M11: OK | N11: OK | O11: OK | P11: - | Q11: 中里 行田 北川 | R11: 共通stg以外だとSSOできないっぽい？ slack →共通STGで確認
B12: =ROW()-ROW($B$3) -> 9 | J12: 1.一度ログアウトを行う。 2.Googleアカウントでサインインを行う。 | K12: サインインできること | M12: OK | N12: OK | O12: OK | P12: - | Q12: 中里 行田 北川
B13: =ROW()-ROW($B$3) -> 10 | F13: 紐付けを解除 | J13: Googleアカウントの連携を解除する。 | K13: 解除できること | M13: OK | N13: OK | O13: OK | P13: - | Q13: 中里 行田 北川
B14: =ROW()-ROW($B$3) -> 11 | J14: 1.一度ログアウトを行う。 2.Googleアカウントでサインインを行う。 | K14: サインインできないこと | M14: OK | N14: OK | O14: OK | P14: - | Q14: 中里 行田 北川
B15: =ROW()-ROW($B$3) -> 12 | E15: Microsoft 365 | F15: アカウント登録 | J15: 任意のMicrosoft 365アカウントを連携する。 | K15: 連携できること | M15: 外 | N15: 外 | O15: 外 | P15: - | Q15: 中里 行田 | R15: KH-4131が未対応で実施できないため対象外とする slack | S15: KH-4131
B16: =ROW()-ROW($B$3) -> 13 | J16: 1.一度ログアウトを行う。 2.Microsoft 365アカウントでサインインを行う。 | K16: サインインできること | M16: 外 | N16: 外 | O16: 外 | P16: - | Q16: 中里 行田 | R16: KH-4131が未対応で実施できないため対象外とする slack | S16: 同上
B17: =ROW()-ROW($B$3) -> 14 | F17: 紐付けを解除 | J17: Microsoft 365アカウントの連携を解除する。 | K17: 解除できること | M17: 外 | N17: 外 | O17: 外 | P17: - | Q17: 中里 行田 | R17: KH-4131が未対応で実施できないため対象外とする slack
B18: =ROW()-ROW($B$3) -> 15 | J18: 1.一度ログアウトを行う。 2.Microsoft 365アカウントでサインインを行う。 | K18: サインインできないこと | M18: 外 | N18: 外 | O18: 外 | P18: - | Q18: 中里 行田 | R18: KH-4131が未対応で実施できないため対象外とする slack
B19: =ROW()-ROW($B$3) -> 16 | E19: Apple | F19: アカウント登録 | J19: 任意のAppleアカウントを連携する。 | K19: 連携できること | M19: OK | N19: OK | O19: OK | P19: - | Q19: 中里
B20: =ROW()-ROW($B$3) -> 17 | J20: 1.一度ログアウトを行う。 2.Appleアカウントでサインインを行う。 | K20: サインインできること | M20: 外 | N20: OK | O20: 外 | P20: - | Q20: 中里 富田（典） | R20: SSO自体はiOSのTestflight版アプリにて実施 【対象外】項目は、SSOできることの確認はiOSデノミ実施可能なことから、N列で1度は確認しているので十分だと判断したため
B21: =ROW()-ROW($B$3) -> 18 | F21: 紐付けを解除 | J21: Appleアカウントの連携を解除する。 | K21: 解除できること | M21: OK | N21: OK | O21: OK | P21: - | Q21: 中里
B22: =ROW()-ROW($B$3) -> 19 | J22: 1.一度ログアウトを行う。 2.Appleアカウントでサインインを行う。 | K22: サインインできないこと | M22: 外 | N22: OK | O22: 外 | P22: - | Q22: 中里 富田（典） | R22: SSO自体はiOSのTestflight版アプリにて実施 【対象外】項目は、SSOできることの確認はiOSデノミ実施可能なことから、N列で1度は確認しているので十分だと判断したため
B23: =ROW()-ROW($B$3) -> 20 | D23: 経費精算払込口座 | E23: 金融機関名 | J23: 任意の内容を入力して保存する。 | K23: セレクトボックス右側に不足事項がある旨が表示されること | M23: OK | N23: 外 | O23: OK | P23: - | Q23: 中里 行田 | R23: TI/TDは表示されないので対象外
B24: =ROW()-ROW($B$3) -> 21 | E24: 支店名 | J24: 任意の内容を入力して保存する。 | K24: セレクトボックス右側に不足事項がある旨が表示されること | M24: OK | N24: 外 | O24: OK | P24: - | Q24: 中里 行田 | R24: TI/TDは表示されないので対象外
B25: =ROW()-ROW($B$3) -> 22 | E25: 口座種類 | J25: 任意の内容を選択して保存する。 | K25: セレクトボックス右側に不足事項がある旨が表示されること | M25: OK | N25: 外 | O25: OK | P25: - | Q25: 中里 行田 | R25: TI/TDは表示されないので対象外
B26: =ROW()-ROW($B$3) -> 23 | E26: 口座番号 | J26: 任意の内容を入力して保存する。 | K26: セレクトボックス右側に不足事項がある旨が表示されること | M26: OK | N26: 外 | O26: OK | P26: - | Q26: 中里 行田 | R26: TI/TDは表示されないので対象外
B27: =ROW()-ROW($B$3) -> 24 | E27: 名義人 | J27: 任意の内容を入力して保存する。 | K27: セレクトボックス右側に不足事項がある旨が表示されること | M27: OK | N27: 外 | O27: OK | P27: - | Q27: 中里 行田 | R27: TI/TDは表示されないので対象外
E28: 全て入力 | J28: 任意の内容を入力して保存する。 | K28: 内容を保存できること | M28: OK | N28: 外 | O28: OK | P28: - | Q28: 中里 行田 | R28: TI/TDは表示されないので対象外
B29: =ROW()-ROW($B$3) -> 26 | D29: パスワードの変更 | E29: ヘルプ | J29: パスワードの変更の右側の「？」アイコンへマウスオーバーする。 | K29: ヘルプに表示崩れがないこと | M29: OK | N29: OK | O29: OK | P29: - | Q29: 中里 行田
B30: =ROW()-ROW($B$3) -> 27 | E30: 新しいパスワード | J30: 「新しいパスワード」のみを入力して保存する。 | K30: 入力不備のエラーが表示され、保存できないこと | M30: OK | N30: OK | O30: OK | P30: - | Q30: 中里 行田
B31: =ROW()-ROW($B$3) -> 28 | E31: 新しいパスワード（確認） | J31: 「新しいパスワード（確認）」のみを入力して保存する。 | K31: 入力不備のエラーが表示され、保存できないこと | M31: OK | N31: OK | O31: OK | P31: - | Q31: 中里 行田
B32: =ROW()-ROW($B$3) -> 29 | E32: 現在のパスワード | J32: 「現在のパスワード」のみを入力して保存する。 | K32: 入力不備のエラーが表示され、保存できないこと | M32: OK | N32: OK | O32: OK | P32: - | Q32: 中里 行田
B33: =ROW()-ROW($B$3) -> 30 | E33: 上記3つを入力 | J33: 以下の全てに任意の内容を入力して保存する。 ・新しいパスワード ・新しいパスワード（確認） ・現在のパスワード | K33: パスワードの変更ができること | M33: OK | N33: OK | O33: OK | P33: - | Q33: 中里 行田
B34: =ROW()-ROW($B$3) -> 31 | J34: 1.一度ログアウトを行う。 2.変更後のパスワードでログインする。 | K34: ログインできること | M34: OK | N34: OK | O34: OK | P34: - | Q34: 中里 行田
B35: =ROW()-ROW($B$3) -> 32 | C35: 定期区間設定 | D35: 定期区間追加 | J35: 任意の定期区間を登録する。 | K35: 登録できること | M35: OK | N35: - | O35: OK | P35: - | Q35: 中里
B36: =ROW()-ROW($B$3) -> 33 | J36: 登録した定期情報を確認する。 | K36: 登録した内容と一致していること | M36: OK | N36: - | O36: OK | P36: - | Q36: 中里
B37: =ROW()-ROW($B$3) -> 34 | E37: 更新 | J37: 定期の更新を行う。 | K37: 更新できること | M37: OK | N37: - | O37: OK | P37: - | Q37: 中里
B38: =ROW()-ROW($B$3) -> 35 | E38: 削除 | J38: 定期の削除を行う。 | K38: 削除できること | M38: OK | N38: - | O38: OK | P38: - | Q38: 中里
B39: =ROW()-ROW($B$3) -> 36 | C39: 経費科目設定 | D39: 有効 | J39: 1.任意の経費科目を用意しておく。 2.経費科目を「有効」に設定する。 3.任意箇所で経費科目を確認する。 | K39: 該当の経費科目が表示されていること | M39: OK | N39: - | O39: OK | P39: - | Q39: 中里
B40: =ROW()-ROW($B$3) -> 37 | D40: 無効 | J40: 1.任意の経費科目を用意しておく。 2.経費科目を「無効」に設定する。 3.任意箇所で経費科目を確認する。 | K40: 該当の経費科目が表示されていないこと | M40: OK | N40: - | O40: OK | P40: - | Q40: 中里
B41: =ROW()-ROW($B$3) -> 38 | C41: メール通知 | D41: 申請に関する通知 | E41: 承認された時 | F41: 有効 | J41: 「承認された時」のトグルを有効に設定する。 | K41: 設定できること | M41: OK | N41: OK | O41: OK | P41: - | Q41: 中里 行田
B42: =ROW()-ROW($B$3) -> 39 | J42: 1.任意書類の申請を行う。 2.申請された書類を最終承認済みまで進める。 3.申請者のメールボックスを確認する。 | K42: メール通知が受信されること | M42: - | N42: - | O42: - | P42: - | Q42: 中里
B43: =ROW()-ROW($B$3) -> 40 | F43: 無効 | J43: 「承認された時」のトグルを無効に設定する。 | K43: 設定できること | M43: OK | N43: OK | O43: OK | P43: - | Q43: 中里 行田
B44: =ROW()-ROW($B$3) -> 41 | J44: 1.任意書類の申請を行う。 2.申請された書類を最終承認済みまで進める。 3.申請者のメールボックスを確認する。 | K44: メール通知が受信されないこと | M44: - | N44: - | O44: - | P44: - | Q44: 中里
B45: =ROW()-ROW($B$3) -> 42 | E45: 差し戻された時 | F45: 有効 | J45: 「差し戻された時」のトグルを有効に設定する。 | K45: 設定できること | M45: OK | N45: OK | O45: OK | P45: - | Q45: 中里 行田
B46: =ROW()-ROW($B$3) -> 43 | J46: 1.任意書類の申請を行う。 2.申請された書類の差し戻しを行う。 3.申請者のメールボックスを確認する。 | K46: メール通知が受信されること | M46: - | N46: - | O46: - | P46: - | Q46: 中里
B47: =ROW()-ROW($B$3) -> 44 | F47: 無効 | J47: 「差し戻しされた時」のトグルを無効に設定する。 | K47: 設定できること | M47: OK | N47: OK | O47: OK | P47: - | Q47: 中里 行田
B48: =ROW()-ROW($B$3) -> 45 | J48: 1.任意書類の申請を行う。 2.申請された書類の差し戻しを行う。 3.申請者のメールボックスを確認する。 | K48: メール通知が受信されないこと | M48: - | N48: - | O48: - | P48: - | Q48: 中里
B49: =ROW()-ROW($B$3) -> 46 | E49: 承認が取り消された時 | F49: 有効 | J49: 「承認が取り消された時」のトグルを有効に設定する。 | K49: 設定できること | M49: OK | N49: OK | O49: OK | P49: - | Q49: 中里 行田
B50: =ROW()-ROW($B$3) -> 47 | J50: 1.任意書類の申請を行う。 2.申請された書類を承認後、承認の取り消しを行う。 3.申請者のメールボックスを確認する。 | K50: メール通知が受信されること | M50: - | N50: - | O50: - | P50: - | Q50: 中里
B51: =ROW()-ROW($B$3) -> 48 | F51: 無効 | J51: 「承認が取り消された時」のトグルを無効に設定する。 | K51: 設定できること | M51: OK | N51: OK | O51: OK | P51: - | Q51: 中里 行田
B52: =ROW()-ROW($B$3) -> 49 | J52: 1.任意書類の申請を行う。 2.申請された書類を承認後、承認の取り消しを行う。 3.申請者のメールボックスを確認する。 | K52: メール通知が受信されないこと | M52: - | N52: - | O52: - | P52: - | Q52: 中里
B53: =ROW()-ROW($B$3) -> 50 | E53: コメントがあった時 | F53: 有効 | J53: 「コメントがあった時」のトグルを有効に設定する。 | K53: 設定できること | M53: OK | N53: OK | O53: OK | P53: - | Q53: 中里 行田
B54: =ROW()-ROW($B$3) -> 51 | J54: 1.任意書類の申請を行う。 2.申請された書類のタイムラインにコメントを投稿する。 3.申請者のメールボックスを確認する。 | K54: メール通知が受信されること | M54: - | N54: - | O54: - | P54: - | Q54: 中里
B55: =ROW()-ROW($B$3) -> 52 | F55: 無効 | J55: 「コメントがあった時」のトグルを無効に設定する。 | K55: 設定できること | M55: OK | N55: OK | O55: OK | P55: - | Q55: 中里 行田
B56: =ROW()-ROW($B$3) -> 53 | J56: 1.任意書類の申請を行う。 2.申請された書類のタイムラインにコメントを投稿する。 3.申請者のメールボックスを確認する。 | K56: メール通知が受信されないこと | M56: - | N56: - | O56: - | P56: - | Q56: 中里
B57: =ROW()-ROW($B$3) -> 54 | D57: 承認に関する通知 | E57: 新たに承認が必要な申請がある時 | F57: 有効 | J57: 「新たに承認が必要な申請がある時」のトグルを有効に設定する。 | K57: 設定できること | M57: OK | N57: OK | O57: OK | P57: - | Q57: 中里 行田
B58: =ROW()-ROW($B$3) -> 55 | J58: 1.任意の書類の申請を行う。 2.承認者のメールボックスを確認する。 | K58: メール通知が受信されること | M58: - | N58: - | O58: - | P58: - | Q58: 中里
B59: =ROW()-ROW($B$3) -> 56 | F59: 無効 | J59: 「新たに承認が必要な申請がある時」のトグルを無効に設定する。 | K59: 設定できること | M59: OK | N59: OK | O59: OK | P59: - | Q59: 中里 行田
B60: =ROW()-ROW($B$3) -> 57 | J60: 1.任意の書類の申請を行う。 2.承認者のメールボックスを確認する。 | K60: メール通知が受信されないこと | M60: - | N60: - | O60: - | P60: - | Q60: 中里
B61: =ROW()-ROW($B$3) -> 58 | E61: 承認した申請が取り下げられた時 | F61: 有効 | J61: 「承認した申請が取り下げられた時」のトグルを有効に設定する。 | K61: 設定できること | M61: OK | N61: OK | O61: OK | P61: - | Q61: 中里 行田
B62: =ROW()-ROW($B$3) -> 59 | J62: 1.任意の書類の申請を行う。 2.申請の第一承認を行う。 3.最終承認前に申請を取り下げる。 4.承認者のメールボックスを確認する。 | K62: メール通知が受信されること | M62: - | N62: - | O62: - | P62: - | Q62: 中里
B63: =ROW()-ROW($B$3) -> 60 | F63: 無効 | J63: 「承認した申請が取り下げられた時」のトグルを無効に設定する。 | K63: 設定できること | M63: OK | N63: OK | O63: OK | P63: - | Q63: 中里 行田
B64: =ROW()-ROW($B$3) -> 61 | J64: 1.任意の書類の申請を行う。 2.申請の第一承認を行う。 3.最終承認前に申請を取り下げる。 4.承認者のメールボックスを確認する。 | K64: メール通知が受信されないこと | M64: - | N64: - | O64: - | P64: - | Q64: 中里
B65: =ROW()-ROW($B$3) -> 62 | E65: 他の承認者が差し戻した時 | F65: 有効 | J65: 「他の承認者が差し戻した時」のトグルを有効に設定する。 | K65: 設定できること | M65: OK | N65: OK | O65: OK | P65: - | Q65: 中里 行田
B66: =ROW()-ROW($B$3) -> 63 | J66: 1.以下の承認フローで書類の申請を行う。 第1承認フロー：任意 第2承認フロー：承認者A,承認者B 2.第1承認フローで承認を行う。 3.第2承認フローにて、承認者Bで差し戻しを行う。 4.承認者Aのメールボックスを確認する。 | K66: メール通知が受信されること | M66: - | N66: - | O66: - | P66: - | Q66: 中里
B67: =ROW()-ROW($B$3) -> 64 | F67: 無効 | J67: 「他の承認者が差し戻した時」のトグルを無効に設定する。 | K67: 設定できること | M67: OK | N67: OK | O67: OK | P67: - | Q67: 中里 行田
B68: =ROW()-ROW($B$3) -> 65 | J68: 1.以下の承認フローで書類の申請を行う。 第1承認フロー：任意 第2承認フロー：承認者A,承認者B 2.第1承認フローで承認を行う。 3.第2承認フローにて、承認者Bで差し戻しを行う。 4.承認者Aのメールボックスを確認する。 | K68: メール通知が受信されないこと | M68: - | N68: - | O68: - | P68: - | Q68: 中里
B69: =ROW()-ROW($B$3) -> 66 | E69: 承認した申請にコメントがあった時 | F69: 有効 | J69: 「承認した申請にコメントがあった時」のトグルを有効に設定する。 | K69: 設定できること | M69: OK | N69: OK | O69: OK | P69: - | Q69: 中里 行田
B70: =ROW()-ROW($B$3) -> 67 | J70: 1.任意書類の申請を行う。 2.申請を最終承認まで進める。 3.申請者でタイムラインにコメントを投稿を行う。 4.承認者のメールボックスを確認する。 | K70: メール通知が受信されること | M70: - | N70: - | O70: - | P70: - | Q70: 中里
B71: =ROW()-ROW($B$3) -> 68 | F71: 無効 | J71: 「承認した申請にコメントがあった時」のトグルを無効に設定する。 | K71: 設定できること | M71: OK | N71: OK | O71: OK | P71: - | Q71: 中里 行田
B72: =ROW()-ROW($B$3) -> 69 | J72: 1.任意書類の申請を行う。 2.申請を最終承認まで進める。 3.申請者でタイムラインにコメントを投稿を行う。 4.承認者のメールボックスを確認する。 | K72: メール通知が受信されないこと | M72: - | N72: - | O72: - | P72: - | Q72: 中里
B73: =ROW()-ROW($B$3) -> 70 | D73: 代理操作に関する通知 | E73: 代理人が申請・承認をした時 | F73: 有効 | J73: 「代理人が申請・承認をした時」のトグルを有効に設定する。 | K73: 設定できること | M73: OK | N73: OK | O73: OK | P73: - | Q73: 中里 行田
B74: =ROW()-ROW($B$3) -> 71 | J74: 1.代理人で任意書類の申請または承認を行う。 2.従業員のメールボックスを確認する。 | K74: メール通知が受信されること | M74: - | N74: - | O74: - | P74: - | Q74: 中里
B75: =ROW()-ROW($B$3) -> 72 | F75: 無効 | J75: 「代理人が申請・承認をした時」のトグルを無効に設定する。 | K75: 設定できること | M75: OK | N75: OK | O75: OK | P75: - | Q75: 中里 行田
B76: =ROW()-ROW($B$3) -> 73 | J76: 1.代理人で任意書類の申請または承認を行う。 2.従業員のメールボックスを確認する。 | K76: メール通知が受信されないこと | M76: - | N76: - | O76: - | P76: - | Q76: 中里
B77: =ROW()-ROW($B$3) -> 74 | E77: 代理人として申請後、承認された時 | F77: 有効 | J77: 「代理人として申請後、承認された時」のトグルを有効に設定する。 | K77: 設定できること | M77: OK | N77: OK | O77: OK | P77: - | Q77: 中里 行田
B78: =ROW()-ROW($B$3) -> 75 | J78: 1.代理人で任意の書類の申請を行う。 2.承認者で書類の承認を行う。 3.従業員のメールボックスを確認する。 | K78: メール通知が受信されること | M78: - | N78: - | O78: - | P78: - | Q78: 中里
B79: =ROW()-ROW($B$3) -> 76 | F79: 無効 | J79: 「代理人として申請後、承認された時」のトグルを無効に設定する。 | K79: 設定できること | M79: OK | N79: OK | O79: OK | P79: - | Q79: 中里 行田
B80: =ROW()-ROW($B$3) -> 77 | J80: 1.代理人で任意の書類の申請を行う。 2.承認者で書類の承認を行う。 3.従業員のメールボックスを確認する。 | K80: メール通知が受信されないこと | M80: - | N80: - | O80: - | P80: - | Q80: 中里
B81: =ROW()-ROW($B$3) -> 78 | E81: 代理人として申請後、差し戻された時 | F81: 有効 | J81: 「代理人として申請後、差し戻された時」のトグルを有効に設定する。 | K81: 設定できること | M81: OK | N81: OK | O81: OK | P81: - | Q81: 中里 行田
B82: =ROW()-ROW($B$3) -> 79 | J82: 1.代理人で任意の書類の申請を行う。 2.承認者で書類の差し戻しを行う。 3.従業員のメールボックスを確認する。 | K82: メール通知が受信されること | M82: - | N82: - | O82: - | P82: -
B83: =ROW()-ROW($B$3) -> 80 | F83: 無効 | J83: 「代理人として申請後、差し戻された時」のトグルを無効に設定する。 | K83: 設定できること | M83: OK | N83: OK | O83: OK | P83: - | Q83: 中里 行田
B84: =ROW()-ROW($B$3) -> 81 | J84: 1.代理人で任意の書類の申請を行う。 2.承認者で書類の差し戻しを行う。 3.従業員のメールボックスを確認する。 | K84: メール通知が受信されないこと | M84: - | N84: - | O84: - | P84: -
B85: =ROW()-ROW($B$3) -> 82 | E85: 代理人として申請後、承認が取り消された時 | F85: 有効 | J85: 「代理人として申請後、承認が取り消された時」のトグルを有効に設定する。 | K85: 設定できること | M85: OK | N85: OK | O85: OK | P85: - | Q85: 中里 行田
B86: =ROW()-ROW($B$3) -> 83 | J86: 1.代理人で任意の書類の申請を行う。 2.承認者で書類を承認後、承認を取り消す。 3.従業員のメールボックスを確認する。 | K86: メール通知が受信されること | M86: - | N86: - | O86: - | P86: - | Q86: 中里
B87: =ROW()-ROW($B$3) -> 84 | F87: 無効 | J87: 「代理人として申請後、承認が取り消された時」のトグルを無効に設定する。 | K87: 設定できること | M87: OK | N87: OK | O87: OK | P87: - | Q87: 中里 行田
B88: =ROW()-ROW($B$3) -> 85 | J88: 1.代理人で任意の書類の申請を行う。 2.承認者で書類を承認後、承認を取り消す。 3.従業員のメールボックスを確認する。 | K88: メール通知が受信されないこと | M88: - | N88: - | O88: - | P88: - | Q88: 中里
B89: =ROW()-ROW($B$3) -> 86 | E89: 代理人として申請後、コメントがあった時 | F89: 有効 | J89: 「代理人として申請後、コメントがあった時」のトグルを有効に設定する。 | K89: 設定できること | M89: OK | N89: OK | O89: OK | P89: - | Q89: 中里 行田
B90: =ROW()-ROW($B$3) -> 87 | J90: 1.代理人で任意の書類の申請を行う。 2.承認者でタイムラインにコメントを投稿する。 3.従業員のメールボックスを確認する。 | K90: メール通知が受信されること | M90: - | N90: - | O90: - | P90: - | Q90: 中里
B91: =ROW()-ROW($B$3) -> 88 | F91: 無効 | J91: 「代理人として申請後、コメントがあった時」のトグルを無効に設定する。 | K91: 設定できること | M91: OK | N91: OK | O91: OK | P91: - | Q91: 中里 行田
B92: =ROW()-ROW($B$3) -> 89 | J92: 1.代理人で任意の書類の申請を行う。 2.承認者でタイムラインにコメントを投稿する。 3.従業員のメールボックスを確認する。 | K92: メール通知が受信されないこと | M92: - | N92: - | O92: - | P92: - | Q92: 中里
B93: =ROW()-ROW($B$3) -> 90 | D93: 領収書に関する通知 | E93: 領収書の自動入力完了・失敗時 | F93: 有効 | J93: 「領収書の自動入力完了・失敗時」のトグルを有効に設定する。 | K93: 設定できること | M93: OK | N93: - | O93: OK | P93: - | Q93: 中里
B94: =ROW()-ROW($B$3) -> 91 | J94: 1.経費の自動入力を行う。 2.作成者のメールボックスを確認する。 | K94: メール通知が受信されること | M94: - | N94: - | O94: - | P94: - | Q94: 中里
B95: =ROW()-ROW($B$3) -> 92 | F95: 無効 | J95: 「領収書の自動入力完了・失敗時」のトグルを無効に設定する。 | K95: 設定できること | M95: OK | N95: - | O95: OK | P95: - | Q95: 中里
B96: =ROW()-ROW($B$3) -> 93 | J96: 1.経費の自動入力を行う。 2.作成者のメールボックスを確認する。 | K96: メール通知が受信されないこと | M96: - | N96: - | O96: - | P96: - | Q96: 中里
B97: =ROW()-ROW($B$3) -> 94 | E97: 締め日後に未提出経費がある時 | F97: 有効 | J97: 「締め日後に未提出経費がある時」のトグルを有効に設定する。 | K97: 設定できること | M97: OK | N97: - | O97: OK | P97: - | Q97: 中里
B98: =ROW()-ROW($B$3) -> 95 | J98: 1.締め日を過ぎた経費を作成し、未申請の状態にする。 2.作成者のメールボックスを確認する。 | K98: メール通知が受信されること | M98: - | N98: - | O98: - | P98: - | Q98: 中里
B99: =ROW()-ROW($B$3) -> 96 | F99: 無効 | J99: 「締め日後に未提出経費がある時」のトグルを無効に設定する。 | K99: 設定できること | M99: OK | N99: - | O99: OK | P99: - | Q99: 中里
B100: =ROW()-ROW($B$3) -> 97 | F100: 有効 | J100: 1.締め日を過ぎた経費を作成し、未申請の状態にする。 2.作成者のメールボックスを確認する。 | K100: メール通知が受信されないこと | M100: - | N100: - | O100: - | P100: - | Q100: 中里
B101: =ROW()-ROW($B$3) -> 98 | D101: 請求書に関する通知 | E101: 請求書の自動入力完了時 | J101: 「請求書の自動入力完了時」のトグルを有効に設定する。 | K101: 設定できること | M101: OK | N101: OK | O101: - | P101: - | Q101: 中里 行田
...

Sheet 国税関係書類
L2: Win11/ Chrome | M2: Win11/ Firefox | N2: Win11/ Edge | O2: Win11/ Firefox | P2: Mac/ Safari | Q2: iOS/ OSver●● | R2: Android/ OSver●●
B3: No | C3: 画面 | D3: 確認対象 | E3: 詳細 | I3: テスト実行手順 | J3: 期待値 | K3: 備考 | L3: TK+TI+TD | M3: TI+TD | N3: TK+TD | O3: TK+TI+TD | P3: TD単体 | Q3: TK+TI+TD | R3: TK+TI+TD | S3: 実行者 | T3: 実行備考 | U3: 起票JIRA No
B4: 1 | C4: 国税関係書類を登録するボタン | D4: 手入力 | E4: 画像 | F4: PDF | I4: 1.国税関係書類画面右上の「国税関係書類を登録する」ボタンを押下する 2.「手入力」を選択する 3.国税関係書類登録画面が開く 4.PDFの画像を選択する 5.「登録」ボタンを押下する | J4: 登録できること | L4: OK | M4: OK | N4: OK | O4: - | P4: 外 | Q4: - | R4: - | S4: 金子
B5: 2 | C5: =INDIRECT(ADDRESS(ROW()-1, COLUMN())) -> 国税関係書類を登録するボタン | D5: =INDIRECT(ADDRESS(ROW()-1, COLUMN())) -> 手入力 | E5: =INDIRECT(ADDRESS(ROW()-1, COLUMN())) -> 画像 | F5: JPEG | I5: 1.国税関係書類画面右上の「国税関係書類を登録する」ボタンを押下する 2.「手入力」を選択する 3.国税関係書類登録画面が開く 4.JPEGの画像を選択する 5.「登録」ボタンを押下する | J5: 登録できること | L5: OK | M5: OK | N5: OK | O5: - | P5: 外 | Q5: - | R5: - | S5: 金子
B6: 3 | C6: =INDIRECT(ADDRESS(ROW()-1, COLUMN())) -> 国税関係書類を登録するボタン | D6: =INDIRECT(ADDRESS(ROW()-1, COLUMN())) -> 手入力 | E6: =INDIRECT(ADDRESS(ROW()-1, COLUMN())) -> 画像 | F6: PNG | I6: 1.国税関係書類画面右上の「国税関係書類を登録する」ボタンを押下する 2.「手入力」を選択する 3.国税関係書類登録モ画面が開く 4.PNGの画像を選択する 5.「登録」ボタンを押下する | J6: 登録できること | L6: OK | M6: OK | N6: OK | O6: - | P6: 外 | Q6: - | R6: - | S6: 金子
B7: 4 | C7: =INDIRECT(ADDRESS(ROW()-1, COLUMN())) -> 国税関係書類を登録するボタン | D7: =INDIRECT(ADDRESS(ROW()-1, COLUMN())) -> 手入力 | E7: =INDIRECT(ADDRESS(ROW()-1, COLUMN())) -> 画像 | F7: PASS付きPDF | I7: 1.国税関係書類画面右上の「国税関係書類を登録する」ボタンを押下する 2.「手入力」を選択する 3.国税関係書類登録画面が開く 4.PASS付きPDFの画像を選択する 5.「登録」ボタンを押下する | J7: 登録できること | L7: OK | M7: OK | N7: OK | O7: - | P7: 外 | Q7: - | R7: - | S7: 金子
B8: 5 | C8: =INDIRECT(ADDRESS(ROW()-1, COLUMN())) -> 国税関係書類を登録するボタン | D8: =INDIRECT(ADDRESS(ROW()-1, COLUMN())) -> 手入力 | E8: =INDIRECT(ADDRESS(ROW()-1, COLUMN())) -> 画像 | F8: 大容量（300MB以上）の画像 （拡張子はJPEG,PNG,PDFのいずれかで） | I8: 1.国税関係書類画面右上の「国税関係書類を登録する」ボタンを押下する 2.「手入力」を選択する 3.国税関係書類登録画面が開く 4.300MB以上の画像を選択する 5.「登録」ボタンを押下する | J8: 登録できること | L8: OK | M8: OK | N8: OK | O8: - | P8: 外 | Q8: - | R8: - | S8: 金子
B9: 6 | C9: =INDIRECT(ADDRESS(ROW()-1, COLUMN())) -> 国税関係書類を登録するボタン | D9: =INDIRECT(ADDRESS(ROW()-1, COLUMN())) -> 手入力 | E9: =INDIRECT(ADDRESS(ROW()-1, COLUMN())) -> 画像 | F9: xls | I9: 1.国税関係書類画面右上の「国税関係書類を登録する」ボタンを押下する 2.「手入力」を選択する 3.国税関係書類登録画面が開く 4.xlsの画像を選択する 5.「登録」ボタンを押下する | J9: 登録できること | L9: OK | M9: OK | N9: OK | O9: - | P9: 外 | Q9: - | R9: - | S9: 金子
B10: 7 | C10: =INDIRECT(ADDRESS(ROW()-1, COLUMN())) -> 国税関係書類を登録するボタン | D10: =INDIRECT(ADDRESS(ROW()-1, COLUMN())) -> 手入力 | E10: =INDIRECT(ADDRESS(ROW()-1, COLUMN())) -> 画像 | F10: xlsx | I10: 1.国税関係書類画面右上の「国税関係書類を登録する」ボタンを押下する 2.「手入力」を選択する 3.国税関係書類登録画面が開く 4.xlsxの画像を選択する 5.「登録」ボタンを押下する | J10: 登録できること | L10: OK | M10: OK | N10: OK | O10: - | P10: 外 | Q10: - | R10: - | S10: 金子
B11: 8 | C11: =INDIRECT(ADDRESS(ROW()-1, COLUMN())) -> 国税関係書類を登録するボタン | D11: =INDIRECT(ADDRESS(ROW()-1, COLUMN())) -> 手入力 | E11: =INDIRECT(ADDRESS(ROW()-1, COLUMN())) -> 画像 | F11: doc | I11: 1.国税関係書類画面右上の「国税関係書類を登録する」ボタンを押下する 2.「手入力」を選択する 3.国税関係書類登録画面が開く 4.docの画像を選択する 5.「登録」ボタンを押下する | J11: 登録できること | L11: OK | M11: OK | N11: OK | O11: - | P11: 外 | Q11: - | R11: - | S11: 金子
B12: 9 | C12: =INDIRECT(ADDRESS(ROW()-1, COLUMN())) -> 国税関係書類を登録するボタン | D12: =INDIRECT(ADDRESS(ROW()-1, COLUMN())) -> 手入力 | E12: =INDIRECT(ADDRESS(ROW()-1, COLUMN())) -> 画像 | F12: docx | I12: 1.国税関係書類画面右上の「国税関係書類を登録する」ボタンを押下する 2.「手入力」を選択する 3.国税関係書類登録画面が開く 4.docxの画像を選択する 5.「登録」ボタンを押下する | J12: 登録できること | L12: OK | M12: OK | N12: OK | O12: - | P12: 外 | Q12: - | R12: - | S12: 金子
B13: 10 | C13: =INDIRECT(ADDRESS(ROW()-1, COLUMN())) -> 国税関係書類を登録するボタン | D13: =INDIRECT(ADDRESS(ROW()-1, COLUMN())) -> 手入力 | E13: =INDIRECT(ADDRESS(ROW()-1, COLUMN())) -> 画像 | F13: txt | I13: 1.国税関係書類画面右上の「国税関係書類を登録する」ボタンを押下する 2.「手入力」を選択する 3.国税関係書類登録画面が開く 4.txtの画像を選択する 5.「登録」ボタンを押下する | J13: 登録できること | L13: OK | M13: OK | N13: OK | O13: - | P13: 外 | Q13: - | R13: - | S13: 金子
B14: 11 | C14: =INDIRECT(ADDRESS(ROW()-1, COLUMN())) -> 国税関係書類を登録するボタン | D14: =INDIRECT(ADDRESS(ROW()-1, COLUMN())) -> 手入力 | E14: =INDIRECT(ADDRESS(ROW()-1, COLUMN())) -> 画像 | F14: csv | I14: 1.国税関係書類画面右上の「国税関係書類を登録する」ボタンを押下する 2.「手入力」を選択する 3.国税関係書類登録画面が開く 4.csvの画像を選択する 5.「登録」ボタンを押下する | J14: 登録できること | L14: OK | M14: OK | N14: OK | O14: - | P14: 外 | Q14: - | R14: - | S14: 金子
B15: 12 | C15: =INDIRECT(ADDRESS(ROW()-1, COLUMN())) -> 国税関係書類を登録するボタン | D15: =INDIRECT(ADDRESS(ROW()-1, COLUMN())) -> 手入力 | E15: =INDIRECT(ADDRESS(ROW()-1, COLUMN())) -> 画像 | F15: Zip | I15: 1.国税関係書類画面右上の「国税関係書類を登録する」ボタンを押下する 2.「手入力」を選択する 3.国税関係書類登録画面が開く 4.Zipファイルを選択する | J15: 「対応していない拡張子のため、変更できませんでした」というエラーメッセージが表示されて登録できないこと | L15: OK | M15: OK | N15: OK | O15: - | P15: 外 | Q15: - | R15: - | S15: 金子
B16: 13 | C16: =INDIRECT(ADDRESS(ROW()-1, COLUMN())) -> 国税関係書類を登録するボタン | D16: =INDIRECT(ADDRESS(ROW()-1, COLUMN())) -> 手入力 | E16: PDFビューア | F16: TOKIUMビューア | I16: TOKIUMビューアで画像の入れ替えや拡縮など各種操作を行う | J16: 表示崩れしないこと | L16: OK | M16: OK | N16: OK | O16: - | P16: OK | Q16: - | R16: - | S16: 金子 七浦
B17: 14 | C17: =INDIRECT(ADDRESS(ROW()-1, COLUMN())) -> 国税関係書類を登録するボタン | D17: =INDIRECT(ADDRESS(ROW()-1, COLUMN())) -> 手入力 | F17: ブラウザ標準ビューア | G17: chrome | I17: chromeでブラウザ標準ビューアを開き画像の入れ替えや拡縮など各種操作を行う | J17: 表示崩れしないこと | K17: ブラウザ標準ビューア →印刷ボタンが表示されてる方 | L17: OK | M17: 外 | N17: 外 | O17: - | P17: 外 | Q17: - | R17: - | S17: 七浦
B18: 15 | C18: =INDIRECT(ADDRESS(ROW()-1, COLUMN())) -> 国税関係書類を登録するボタン | D18: =INDIRECT(ADDRESS(ROW()-1, COLUMN())) -> 手入力 | G18: edge | I18: edgeでブラウザ標準ビューアを開き画像の入れ替えや拡縮など各種操作を行う | J18: 表示崩れしないこと | L18: 外 | M18: 外 | N18: OK | O18: - | P18: 外 | Q18: - | R18: - | S18: 七浦
B19: 16 | C19: =INDIRECT(ADDRESS(ROW()-1, COLUMN())) -> 国税関係書類を登録するボタン | D19: =INDIRECT(ADDRESS(ROW()-1, COLUMN())) -> 手入力 | G19: firefox | I19: firefoxでブラウザ標準ビューアを開き画像の入れ替えや拡縮など各種操作を行う | J19: 表示崩れしないこと | L19: 外 | M19: OK | N19: 外 | O19: - | P19: 外 | Q19: - | R19: - | S19: 七浦
B20: 17 | C20: =INDIRECT(ADDRESS(ROW()-1, COLUMN())) -> 国税関係書類を登録するボタン | D20: =INDIRECT(ADDRESS(ROW()-1, COLUMN())) -> 手入力 | G20: safari | I20: safariでブラウザ標準ビューアを開き画像の入れ替えや拡縮など各種操作を行う | J20: 表示崩れしないこと | L20: 外 | M20: 外 | N20: 外 | O20: - | P20: OK | Q20: - | R20: - | S20: 金子 七浦
B21: 18 | C21: =INDIRECT(ADDRESS(ROW()-1, COLUMN())) -> 国税関係書類を登録するボタン | D21: =INDIRECT(ADDRESS(ROW()-1, COLUMN())) -> 手入力 | E21: PNG,JPEGのビューア | I21: ビューアで画像の入れ替えや拡縮など各種操作を行う | J21: 表示崩れしないこと | L21: OK | M21: 外 | N21: 外 | O21: - | P21: 外 | Q21: - | R21: - | S21: 七浦
B22: 19 | C22: =INDIRECT(ADDRESS(ROW()-1, COLUMN())) -> 国税関係書類を登録するボタン | D22: =INDIRECT(ADDRESS(ROW()-1, COLUMN())) -> 手入力 | E22: その他の拡張子のビューア | I22: ビューアで画像の入れ替えとダウンロードを行う | J22: ビューアの機能が使えること | L22: OK | M22: 外 | N22: 外 | O22: - | P22: 外 | Q22: - | R22: - | S22: 七浦
B23: 20 | C23: =INDIRECT(ADDRESS(ROW()-1, COLUMN())) -> 国税関係書類を登録するボタン | D23: =INDIRECT(ADDRESS(ROW()-1, COLUMN())) -> 手入力 | E23: 書類種別 | F23: 文字入力 | I23: 書類種別名表示欄にマウスを乗せる | J23: 文字入力はできないこと | L23: OK | M23: OK | N23: OK | O23: - | P23: 外 | Q23: - | R23: - | S23: 金子
B24: 21 | C24: =INDIRECT(ADDRESS(ROW()-1, COLUMN())) -> 国税関係書類を登録するボタン | D24: =INDIRECT(ADDRESS(ROW()-1, COLUMN())) -> 手入力 | F24: 書類種別選択モーダル | I24: 書類種別の「選択」を押下する | J24: 書類種別選択モーダルが開くこと | L24: OK | M24: OK | N24: OK | O24: - | P24: 外 | Q24: - | R24: - | S24: 金子
B25: 22 | C25: =INDIRECT(ADDRESS(ROW()-1, COLUMN())) -> 国税関係書類を登録するボタン | D25: =INDIRECT(ADDRESS(ROW()-1, COLUMN())) -> 手入力 | F25: 検索 | I25: 書類種別選択モーダル内で任意の書類種別名を検索する | J25: 検索できること | L25: OK | M25: OK | N25: OK | O25: - | P25: 外 | Q25: - | R25: - | S25: 金子
B26: 23 | C26: =INDIRECT(ADDRESS(ROW()-1, COLUMN())) -> 国税関係書類を登録するボタン | D26: =INDIRECT(ADDRESS(ROW()-1, COLUMN())) -> 手入力 | F26: 検索条件の保持 | I26: 上記に続いて書類種別選択モーダルを一度閉じて再度開く | J26: 検索した条件はリセットされていること | L26: OK | M26: OK | N26: OK | O26: - | P26: 外 | Q26: - | R26: - | S26: 金子
B27: 24 | C27: =INDIRECT(ADDRESS(ROW()-1, COLUMN())) -> 国税関係書類を登録するボタン | D27: =INDIRECT(ADDRESS(ROW()-1, COLUMN())) -> 手入力 | F27: 書類種別名表示 | I27: 1.書類種別の「選択」を押下する 2.書類種別選択モーダルが開くので任意の書類種別名を選択する | J27: 書類種別に選択した書類種別名が表示されていること | L27: OK | M27: OK | N27: OK | O27: - | P27: 外 | Q27: - | R27: - | S27: 金子
B28: 25 | C28: =INDIRECT(ADDRESS(ROW()-1, COLUMN())) -> 国税関係書類を登録するボタン | D28: =INDIRECT(ADDRESS(ROW()-1, COLUMN())) -> 手入力 | F28: 書類種別名の保持 | I28: 上記に続いて書類種別選択モーダルを再度開く | J28: 選択した書類種別名にチェックが入っていること | L28: OK | M28: OK | N28: OK | O28: - | P28: 外 | Q28: - | R28: - | S28: 金子
B29: 26 | C29: =INDIRECT(ADDRESS(ROW()-1, COLUMN())) -> 国税関係書類を登録するボタン | D29: =INDIRECT(ADDRESS(ROW()-1, COLUMN())) -> 手入力 | E29: 書類タイトル | F29: 文字入力 | I29: 1.文字列を入力する 2.「✕」ボタンを押下する | J29: 文字の入力と削除ができること | L29: OK | M29: OK | N29: OK | O29: - | P29: 外 | Q29: - | R29: - | S29: 金子
B30: 27 | C30: =INDIRECT(ADDRESS(ROW()-1, COLUMN())) -> 国税関係書類を登録するボタン | D30: =INDIRECT(ADDRESS(ROW()-1, COLUMN())) -> 手入力 | E30: 取引日 | F30: 文字入力 | I30: yyyy/mm/dd の形式で日付を手入力し保存する | J30: 日付が反映されること | L30: OK | M30: OK | N30: OK | O30: - | P30: 外 | Q30: - | R30: - | S30: 金子
